Workbook

Sheet Instruçoes
A1: FIAP | B1: Modelo Financeiro para Novos Negócios ( Startup One ou Discovery)
A2: Intruções de Preenchimento
A3: 1. Geral
A4: 45658 | B4: Preencha somente os campos em amarelo das abas : "Premissa de Receitas", "Premissade Despesas, "Premissas de Investimento
A5: 45689 | B5: A aba "Folha de Pagamento" é apenas um valor referencial, para que depois você coloque o valor na aba "premissas e Despesas
A6: 45717 | B6: As abas "Projeção Financeira" e "Resumo"" são automatizads, ou seja, não precisam ser preenchidas
A7: 2. Premissa Receitas (O quanto o seu negócio gera de receita)
A8: 45659 | B8: Preencha o TAM/SAM/SOM estudado, em volume financeiro de faturamento de mercado
A9: 45690 | B9: Selecione o tipo de atividade na qual seu negócio atuará , o que definirá o cálculo de imposto
A10: 45718 | B10: Em seguida, preencha média aproximada de preço (ticket médio), para calcularmos a projeção de clientes. Defina também o perrcentual de cliente que deseja alcançar no primeiro ano e no primeiro mês, assim como a taxa % de cfrescimento mensal.
A11: 45749 | B11: Em seguida, preencha o modelo de Monetização. Você pode escolher mais de um. Nesta hora você deve percentiualizar qual a representatividade de cada modelo ( Ex. 70% Assinatura/ 30% B2B) e definir preço de venda e custo dos serviços/produtos, assim como percentual de vendas de cada um deles em cada bloco de monetização
A12: 3. Premissa Despesas ( o quanto o seu negócio gera de custos)
A13: 45660 | B13: Preencha os grupos de despesas , considerando uma somatoria de valores que gastaria mensalmente
A14: 45691 | B14: Para cada grupo de despesas, considere valhores de folha de pagamento mensal existente naquele grupo
A15: 45719 | B15: Defina a estimativa anual de reajustes de despesas , que ocorre natuaralmente todo ano
A16: 4. Premissa investimento Inicial ( o quanto você precisa para começar seu negócio, seja com investimentos próprios ou com captaçoes de mercdo)
A17: 45661 | B17: Preencha os grupos deinvestimento , considerando uma somatoria de valores que precisaria para começar este negócio

Sheet 1.Premissas Receitas
A1: Suposições de receita
A3: Tamanho de Mercado (Trazer números em valor financeiro de faturamento do setor escolhido)
A4: Tam | B4: Somatória das receitas geradas por todos os players do seu segmento. | E4: 91500000000
A5: Sam | B5: Somatória das receitas que você poderia ganhar vendendo o seu produto em um segmento. | E5: 20500000000
A6: Som | B6: Quantos $$$ destes realmente você vai conseguir considerando concorrentes, região, tendências, demanda esperada | E6: 134400000
A8: Atividade: | B8: 2 | C8: 2 | D8: 2
A9: 1 para Comércio
A10: 2 para Serviços
A11: 3 para Indústria
A14: Projeção de Clientes | B14: % SOM | C14: Total
A15: Preço Médio | B15: 96000 | F15: Crescimento Anual
A16: Numero de clientes em 5 anos | B16: =E6/B15 -> 1400 | C16: =B16 -> 1400 | F16: % Cresc. Ano 2 | G16: 0.4
A17: Numero de cliente no Primeiro ano | B17: 0.05 | C17: =B17*C16 -> 70 | F17: % Cresc. Ano 3 | G17: 0.3
A18: Número de Cliente no Primeiro Mês | B18: 0.1 | C18: =C17/21 -> 3.3333333 | F18: % Cresc. Ano 4 | G18: 0.2
A19: % Cres Mensal | B19: 0.03 | F19: % Cresc. Ano 5 | G19: 0.15
A22: Modelo de Monetização (Preencha apenas o(s) modelo(s) escolhido(s), que podem ser mais de um)
A24: Assinatura (SaaS) | B24: O que contempla? | C24: $ preço de venda | D24: $ Custo unitário | E24: Margem | F24: % Vendas | G24: Clientes Mês 1
A25: # de clientes Assinatura Fremium | B25: Free trial + estimativas limitadas (self-serve) | C25: 1 | D25: 0 | E25: =1-D25/C25 -> 1 | F25: 0.5 | G25: =F25*$B$29 -> 1
A26: # de clientes Assinatura 1 | B26: SaaS por volume de jobs preditos (ticket medio mensal) | C26: 500 | D26: 150 | E26: =1-D26/C26 -> 0.7 | F26: 0.35 | G26: =F26*$B$29 -> 0.7
A27: # de clientes Assinatura 2 | B27: Assinatura Enterprise por usuario | C27: 1400 | D27: 420 | E27: =1-D27/C27 -> 0.7 | F27: 0.15 | G27: =F27*$B$29 -> 0.3
A28: Perececentual de faturamento do Modelo | B28: 0.6
A29: Clientes no primeiro mês | B29: =$C$18*B28 -> 2
A30: % Churn - cancelamentos mensais | B30: 0.03
A32: Marketplace | B32: O que contempla? | C32: $ preço médio de venda | D32: $ Custo unitário | E32: Margem | F32: % Vendas | G32: Clientes Mês 1
A33: # de clientes marketplace % Comissão 1 | C33: 1 | D33: 0 | E33: =1-D33/C33 -> 1 | F33: 0 | G33: =F33*$B$37 -> 0
A34: # de clientes marketplace % Comissão 2 | C34: 1 | D34: 0 | E34: =1-D34/C34 -> 1 | G34: =F34*$B$37 -> 0
A35: # de clientes marketplace % Comissão 3 | C35: 1 | D35: 0 | E35: =1-D35/C35 -> 1 | G35: =F35*$B$37 -> 0
A36: Perececentual de faturamento do Modelo | B36: 0
A37: Clientes no primeiro mês | B37: =$C$18*B36 -> 0
A39: B2B | B39: O que contempla? | C39: $ preço de venda | D39: $ Custo unitário | E39: Margem | F39: % Vendas | G39: Clientes Mês 1
A40: # de clientes B2B Setup | B40: Setup + integracao (Dagster/Spark, onboarding) | C40: 15000 | D40: 5000 | E40: =1-D40/C40 -> 0.66666667 | F40: 1 | G40: =F40*$B$44 -> 1.3333333
A41: # de clientes B2B Mensalidade | B41: Success Fee medio mensal (8-12% do saving gerado) | C41: 8000 | D41: 800 | E41: =1-D41/C41 -> 0.9 | F41: 1 | G41: =F41*$B$44 -> 1.3333333
A42: # de clientes B2B Manutenção | C42: 1 | D42: 0 | E42: =1-D42/C42 -> 1 | F42: 0 | G42: =F42*$B$44 -> 0
A43: Perececentual de faturamento do Modelo | B43: 0.4
A44: Clientes no primeiro mês | B44: =$C$18*B43 -> 1.3333333
A47: Conteúdo Premium/Paywall | B47: O que contempla? | C47: $ preço de venda | D47: $ Custo unitário | E47: Margem | F47: % Vendas | G47: Clientes Mês 1
A48: # de clientes Conteudo/ Paywall 1 | C48: 1 | D48: 0 | E48: =1-D48/C48 -> 1 | F48: 0 | G48: =F48*$B$52 -> 0
A49: # de clientes Conteudo/ Paywall 2 | C49: 1 | D49: 0 | E49: =1-D49/C49 -> 1 | G49: =F49*$B$52 -> 0
A50: # de clientes Conteudo/ Paywall 3 | C50: 1 | D50: 0 | E50: =1-D50/C50 -> 1 | G50: =F50*$B$52 -> 0
A51: Perececentual de faturamento do Modelo | B51: 0
A52: Clientes no primeiro mês | B52: =$C$18*B51 -> 0
A55: Publicidade | B55: O que contempla? | C55: $ preço de venda | D55: $ Custo unitário | E55: Margem | F55: % Vendas | G55: Clientes Mês 1
A56: # de clientes publicidade Produto/Serviço 1 | C56: 1 | D56: 0 | E56: =1-D56/C56 -> 1 | F56: 0 | G56: =F56*$B$60 -> 0
A57: # de clientes publicidade Produto/Serviço 2 | C57: 1 | D57: 0 | E57: =1-D57/C57 -> 1 | G57: =F57*$B$60 -> 0
A58: # de clientes publicidade Produto/Serviço 3 | C58: 1 | D58: 0 | E58: =1-D58/C58 -> 1 | G58: =F58*$B$60 -> 0
A59: Perececentual de faturamento do Modelo | B59: 0
A60: Clientes no primeiro mês | B60: =$C$18*B59 -> 0
A62: Pay-per-use | B62: O que contempla? | C62: $ preço de venda | D62: $ Custo unitário | E62: Margem | F62: % Vendas | G62: Clientes Mês 1
A63: # Pay-per-use Produto/Serviço 1 | C63: 1 | D63: 0 | E63: =1-D63/C63 -> 1 | F63: 0 | G63: =F63*$B$67 -> 0
A64: # Pay-per-use Produto/Serviço 2 | C64: 1 | D64: 0 | E64: =1-D64/C64 -> 1 | G64: =F64*$B$67 -> 0
A65: # Pay-per-use Produto/Serviço 3 | C65: 1 | D65: 0 | E65: =1-D65/C65 -> 1 | G65: =F65*$B$67 -> 0
A66: Perececentual de faturamento do Modelo | B66: 0
A67: Clientes no primeiro mês | B67: =$C$18*B66 -> 0
A68: % Churn - cancelamentos mensais | B68: 0

Sheet 2.Folha de Pagamentos
A1: Folha de Pagamentos ( Valores ilustrativos)
A4: # | B4: Name | C4: Título | D4: Departamento | E4: Começo | F4: Final | G4: Salário Anual | H4: Aumento Anual | I4: Impostos
A6: 1 | B6: Fundador(a) 1 | C6: CEO | D6: G&A | E6: 46266 | F6: 73050 | G6: 180000 | H6: 0.05 | I6: 0.15
A7: =+A6+1 -> 2 | B7: Fundador(a) 2 | C7: CTO | D7: P&D | E7: 46266 | F7: 73050 | G7: 180000 | H7: 0.05 | I7: 0.15
A8: =+A7+1 -> 3 | B8: Eng. de Dados Senior | C8: Data Engineer Senior | D8: P&D | E8: 46296 | F8: 73050 | G8: 150000 | H8: 0.05 | I8: 0.15
A9: =+A8+1 -> 4 | B9: Eng. de Dados Pleno | C9: Data Engineer Pleno | D9: P&D | E9: 46388 | F9: 73050 | G9: 120000 | H9: 0.05 | I9: 0.15
A10: =+A9+1 -> 5 | B10: Head de Growth | C10: Head de Growth/Vendas | D10: M&V | E10: 46327 | F10: 73050 | G10: 130000 | H10: 0.05 | I10: 0.15
A11: =+A10+1 -> 6 | B11: Analista de CS | C11: Customer Success / FinOps Liaison | D11: M&V | E11: 46419 | F11: 73050 | G11: 90000 | H11: 0.05 | I11: 0.15
A12: =+A11+1 -> 7 | B12: Analista Admin | C12: Controller/Admin (part-time) | D12: G&A | E12: 46266 | F12: 73050 | G12: 60000 | H12: 0.05 | I12: 0.15
A13: =+A12+1 -> 8
A14: =+A13+1 -> 9
A15: =+A14+1 -> 10
A16: =+A15+1 -> 11
A17: =+A16+1 -> 12
A18: =+A17+1 -> 13
A19: =+A18+1 -> 14
A20: =+A19+1 -> 15
A21: =+A20+1 -> 16
A22: =+A21+1 -> 17
A23: =+A22+1 -> 18
A24: =+A23+1 -> 19
... A29: =+A28+1 -> 24

Sheet 3.Premissas de Despesas
A1: Suposições de despesas operacional
A3: Vendas e Marketing | B3: $ Mensal | C3: Ano 1
A4: Serviços de V&M, software, ferramentas, campanhas | B4: 8000 | C4: =B4*12 -> 96000
A5: Folha de pagamento de V&M | B5: 18333 | C5: =B5*12 -> 219996
A7: Pesquisa e Desenvolvimento | B7: $ Mensal | C7: Ano 1
A8: Serviços de P&D, software, ferramentas , custos T&I | B8: 12000 | C8: =B8*12 -> 144000
A9: Folha de pagamento de P&D | B9: 37500 | C9: =B9*12 -> 450000
A11: Geral & Admin | B11: $ Mensal | C11: Ano 1
A12: Aluguel, Energia, Luz e Custos Fixos, internet | B12: 3000 | C12: =B12*12 -> 36000
A13: VIagens e Despesas Extras | B13: 2000 | C13: =B13*12 -> 24000
A14: Serviços de G&A (contabilidade, advogados, consultorias), software, ferramentas - % da Receita | B14: 4000 | C14: =B14*12 -> 48000
A15: Folha de pagamentos de G&A | B15: 20000 | C15: =B15*12 -> 240000
A17: Outras receitas / despesas | C17: Ano 1
A18: Depreciação e Amortização | B18: 1000 | C18: =B18*12 -> 12000
A19: Pró-labore de Sócios | B19: 15000 | C19: =B19*12 -> 180000
A20: Outras despesas | B20: 0 | C20: =B20*12 -> 0
A22: Estimativa de reajustes nas despesas
A23: Ano 02 | B23: 0.1
A24: Ano 03 | B24: 0.15
A25: Ano 04 | B25: 0.2
A26: Ano 05 | B26: 0.25

Sheet 4.Premissas de Investimento
A1: Suposições de Investimentos/ Aporte Iniciais | B1: =B3+B7+B13 -> 170000
A3: Vendas e Marketing | B3: =SUM(B4:B5) -> 25000
A4: Lançamento da solução (Criaçao de Logo e campanha) | B4: 15000
A5: Evento de lançamento | B5: 10000
A7: Pesquisa e Desenvolvimento | B7: =SUM(B8:B11) -> 130000
A8: Contratação de sistemas e ferramentas | B8: 20000
A9: Desenvolvimento da solução | B9: 80000
A10: Equipamentos ( computadores ou devices) | B10: 30000
A11: Estoque inicial ( no caso de devices ou produtos) | B11: 0
A13: Geral & Admin | B13: =SUM(B14:B15) -> 15000
A14: Serviços de G&A (domínios, documentos e taxas de abertura de empresa) | B14: 5000
A15: Gastos Pré-Operacionais | B15: 10000

Sheet 5.Projeção Financeira
A1: Template de Projeção FInanceira
D3: Mês | G3: =+F3+1 -> 1 | H3: =+G3+1 -> 2 | I3: =+H3+1 -> 3 | J3: =+I3+1 -> 4 | K3: =+J3+1 -> 5 | L3: =+K3+1 -> 6 | M3: =+L3+1 -> 7 | N3: =+M3+1 -> 8 | ... BN3: =+BM3+1 -> 60 | BP3: Ano 1 | BQ3: Ano 2 | BR3: Ano 3 | BS3: Ano 4 | BT3: Ano 5
D4: Período | G4: Projeção | H4: Projeção | I4: Projeção | J4: Projeção | K4: Projeção | L4: Projeção | M4: Projeção | N4: Projeção | O4: Projeção | P4: Projeção | Q4: Projeção | R4: Projeção | S4: Projeção | T4: Projeção | U4: Projeção | V4: Projeção | W4: Projeção | X4: Projeção | Y4: Projeção | Z4: Projeção | AA4: Projeção | AB4: Projeção | AC4: Projeção | AD4: Projeção | AE4: Projeção | AF4: Projeção | AG4: Projeção | AH4: Projeção | AI4: Projeção | AJ4: Projeção | AK4: Projeção | AL4: Projeção | AM4: Projeção | AN4: Projeção | AO4: Projeção | AP4: Projeção | AQ4: Projeção | AR4: Projeção | AS4: Projeção | AT4: Projeção | AU4: Projeção | AV4: Projeção | AW4: Projeção | AX4: Projeção | AY4: Projeção | AZ4: Projeção | BA4: Projeção | BB4: Projeção | BC4: Projeção | BD4: Projeção | BE4: Projeção | BF4: Projeção | BG4: Projeção | BH4: Projeção | BI4: Projeção | BJ4: Projeção | BK4: Projeção | BL4: Projeção | BM4: Projeção | BN4: Projeção | BP4: Projeção | BQ4: Projeção | BR4: Projeção | BS4: Projeção | BT4: Projeção
A6: Vendas
B8: Novas vendas
C9: ='1.Premissas Receitas'!A25 -> # de clientes Assinatura Fremium | G9: ='1.Premissas Receitas'!G25 -> 1 | H9: =G9+(G9*'1.Premissas Receitas'!$B$19) -> 1.03 | I9: =H9+(H9*'1.Premissas Receitas'!$B$19) -> 1.0609 | J9: =I9+(I9*'1.Premissas Receitas'!$B$19) -> 1.092727 | K9: =J9+(J9*'1.Premissas Receitas'!$B$19) -> 1.1255088 | L9: =K9+(K9*'1.Premissas Receitas'!$B$19) -> 1.1592741 | M9: =L9+(L9*'1.Premissas Receitas'!$B$19) -> 1.1940523 | N9: =M9+(M9*'1.Premissas Receitas'!$B$19) -> 1.2298739 | O9: =N9+(N9*'1.Premissas Receitas'!$B$19) -> 1.2667701 | ... R9: =Q9+(Q9*'1.Premissas Receitas'!$B$19) -> 1.3842339 | S9: =R9+(R9*'1.Premissas Receitas'!$G$16) -> 1.9379274 | T9: =S9+(S9*'1.Premissas Receitas'!$B$19) -> 1.9960652 | U9: =T9+(T9*'1.Premissas Receitas'!$B$19) -> 2.0559472 | V9: =U9+(U9*'1.Premissas Receitas'!$B$19) -> 2.1176256 | W9: =V9+(V9*'1.Premissas Receitas'!$B$19) -> 2.1811544 | X9: =W9+(W9*'1.Premissas Receitas'!$B$19) -> 2.246589 | Y9: =X9+(X9*'1.Premissas Receitas'!$B$19) -> 2.3139867 | Z9: =Y9+(Y9*'1.Premissas Receitas'!$B$19) -> 2.3834063 | AA9: =Z9+(Z9*'1.Premissas Receitas'!$B$19) -> 2.4549085 | ... AD9: =AC9+(AC9*'1.Premissas Receitas'!$B$19) -> 2.6825448 | AE9: =AD9+(AD9*'1.Premissas Receitas'!$G$17) -> 3.4873082 | AF9: =AE9+(AE9*'1.Premissas Receitas'!$B$19) -> 3.5919275 | AG9: =AF9+(AF9*'1.Premissas Receitas'!$B$19) -> 3.6996853 | AH9: =AG9+(AG9*'1.Premissas Receitas'!$B$19) -> 3.8106758 | AI9: =AH9+(AH9*'1.Premissas Receitas'!$B$19) -> 3.9249961 | AJ9: =AI9+(AI9*'1.Premissas Receitas'!$B$19) -> 4.042746 | AK9: =AJ9+(AJ9*'1.Premissas Receitas'!$B$19) -> 4.1640284 | AL9: =AK9+(AK9*'1.Premissas Receitas'!$B$19) -> 4.2889492 | AM9: =AL9+(AL9*'1.Premissas Receitas'!$B$19) -> 4.4176177 | ... AP9: =AO9+(AO9*'1.Premissas Receitas'!$B$19) -> 4.8272501 | AQ9: =AP9+(AP9*'1.Premissas Receitas'!$G$18) -> 5.7927002 | AR9: =AQ9+(AQ9*'1.Premissas Receitas'!$B$19) -> 5.9664812 | AS9: =AR9+(AR9*'1.Premissas Receitas'!$B$19) -> 6.1454756 | AT9: =AS9+(AS9*'1.Premissas Receitas'!$B$19) -> 6.3298399 | AU9: =AT9+(AT9*'1.Premissas Receitas'!$B$19) -> 6.5197351 | AV9: =AU9+(AU9*'1.Premissas Receitas'!$B$19) -> 6.7153271 | AW9: =AV9+(AV9*'1.Premissas Receitas'!$B$19) -> 6.9167869 | AX9: =AW9+(AW9*'1.Premissas Receitas'!$B$19) -> 7.1242905 | AY9: =AX9+(AX9*'1.Premissas Receitas'!$B$19) -> 7.3380193 | ... BB9: =BA9+(BA9*'1.Premissas Receitas'!$B$19) -> 8.0184518 | BC9: =BB9+(BB9*'1.Premissas Receitas'!$G$19) -> 9.2212195 | BD9: =BC9+(BC9*'1.Premissas Receitas'!$B$19) -> 9.4978561 | BE9: =BD9+(BD9*'1.Premissas Receitas'!$B$19) -> 9.7827918 | BF9: =BE9+(BE9*'1.Premissas Receitas'!$B$19) -> 10.076276 | BG9: =BF9+(BF9*'1.Premissas Receitas'!$B$19) -> 10.378564 | BH9: =BG9+(BG9*'1.Premissas Receitas'!$B$19) -> 10.689921 | BI9: =BH9+(BH9*'1.Premissas Receitas'!$B$19) -> 11.010618 | BJ9: =BI9+(BI9*'1.Premissas Receitas'!$B$19) -> 11.340937 | BK9: =BJ9+(BJ9*'1.Premissas Receitas'!$B$19) -> 11.681165 | ... BN9: =BM9+(BM9*'1.Premissas Receitas'!$B$19) -> 12.764324 | BP9: =SUM(G9:R9) -> 14.19203 | BQ9: =SUM(T9:AD9) -> 25.565196 | BR9: =SUM(AE9:AP9) -> 49.491981 | BS9: =SUM(AQ9:BB9) -> 82.210172 | BT9: =SUM(BC9:BN9) -> 130.86782
C10: ='1.Premissas Receitas'!A26 -> # de clientes Assinatura 1 | G10: ='1.Premissas Receitas'!G26 -> 0.7 | H10: =G10+(G10*'1.Premissas Receitas'!$B$19) -> 0.721 | I10: =H10+(H10*'1.Premissas Receitas'!$B$19) -> 0.74263 | J10: =I10+(I10*'1.Premissas Receitas'!$B$19) -> 0.7649089 | K10: =J10+(J10*'1.Premissas Receitas'!$B$19) -> 0.78785617 | L10: =K10+(K10*'1.Premissas Receitas'!$B$19) -> 0.81149185 | M10: =L10+(L10*'1.Premissas Receitas'!$B$19) -> 0.83583661 | N10: =M10+(M10*'1.Premissas Receitas'!$B$19) -> 0.86091171 | O10: =N10+(N10*'1.Premissas Receitas'!$B$19) -> 0.88673906 | ... R10: =Q10+(Q10*'1.Premissas Receitas'!$B$19) -> 0.96896371 | S10: =R10+(R10*'1.Premissas Receitas'!$G$16) -> 1.3565492 | T10: =S10+(S10*'1.Premissas Receitas'!$B$19) -> 1.3972457 | U10: =T10+(T10*'1.Premissas Receitas'!$B$19) -> 1.439163 | V10: =U10+(U10*'1.Premissas Receitas'!$B$19) -> 1.4823379 | W10: =V10+(V10*'1.Premissas Receitas'!$B$19) -> 1.5268081 | X10: =W10+(W10*'1.Premissas Receitas'!$B$19) -> 1.5726123 | Y10: =X10+(X10*'1.Premissas Receitas'!$B$19) -> 1.6197907 | Z10: =Y10+(Y10*'1.Premissas Receitas'!$B$19) -> 1.6683844 | AA10: =Z10+(Z10*'1.Premissas Receitas'!$B$19) -> 1.7184359 | ... AD10: =AC10+(AC10*'1.Premissas Receitas'!$B$19) -> 1.8777813 | AE10: =AD10+(AD10*'1.Premissas Receitas'!$G$17) -> 2.4411157 | AF10: =AE10+(AE10*'1.Premissas Receitas'!$B$19) -> 2.5143492 | AG10: =AF10+(AF10*'1.Premissas Receitas'!$B$19) -> 2.5897797 | AH10: =AG10+(AG10*'1.Premissas Receitas'!$B$19) -> 2.6674731 | AI10: =AH10+(AH10*'1.Premissas Receitas'!$B$19) -> 2.7474973 | AJ10: =AI10+(AI10*'1.Premissas Receitas'!$B$19) -> 2.8299222 | AK10: =AJ10+(AJ10*'1.Premissas Receitas'!$B$19) -> 2.9148199 | AL10: =AK10+(AK10*'1.Premissas Receitas'!$B$19) -> 3.0022645 | AM10: =AL10+(AL10*'1.Premissas Receitas'!$B$19) -> 3.0923324 | ... AP10: =AO10+(AO10*'1.Premissas Receitas'!$B$19) -> 3.3790751 | AQ10: =AP10+(AP10*'1.Premissas Receitas'!$G$18) -> 4.0548901 | AR10: =AQ10+(AQ10*'1.Premissas Receitas'!$B$19) -> 4.1765368 | AS10: =AR10+(AR10*'1.Premissas Receitas'!$B$19) -> 4.3018329 | AT10: =AS10+(AS10*'1.Premissas Receitas'!$B$19) -> 4.4308879 | AU10: =AT10+(AT10*'1.Premissas Receitas'!$B$19) -> 4.5638145 | AV10: =AU10+(AU10*'1.Premissas Receitas'!$B$19) -> 4.700729 | AW10: =AV10+(AV10*'1.Premissas Receitas'!$B$19) -> 4.8417509 | AX10: =AW10+(AW10*'1.Premissas Receitas'!$B$19) -> 4.9870034 | AY10: =AX10+(AX10*'1.Premissas Receitas'!$B$19) -> 5.1366135 | ... BB10: =BA10+(BA10*'1.Premissas Receitas'!$B$19) -> 5.6129162 | BC10: =BB10+(BB10*'1.Premissas Receitas'!$G$19) -> 6.4548537 | BD10: =BC10+(BC10*'1.Premissas Receitas'!$B$19) -> 6.6484993 | BE10: =BD10+(BD10*'1.Premissas Receitas'!$B$19) -> 6.8479543 | BF10: =BE10+(BE10*'1.Premissas Receitas'!$B$19) -> 7.0533929 | BG10: =BF10+(BF10*'1.Premissas Receitas'!$B$19) -> 7.2649947 | BH10: =BG10+(BG10*'1.Premissas Receitas'!$B$19) -> 7.4829445 | BI10: =BH10+(BH10*'1.Premissas Receitas'!$B$19) -> 7.7074328 | BJ10: =BI10+(BI10*'1.Premissas Receitas'!$B$19) -> 7.9386558 | BK10: =BJ10+(BJ10*'1.Premissas Receitas'!$B$19) -> 8.1768155 | ... BN10: =BM10+(BM10*'1.Premissas Receitas'!$B$19) -> 8.9350271 | BP10: =SUM(G10:R10) -> 9.9344207 | BQ10: =SUM(T10:AD10) -> 17.895637 | BR10: =SUM(AE10:AP10) -> 34.644387 | BS10: =SUM(AQ10:BB10) -> 57.54712 | BT10: =SUM(BC10:BN10) -> 91.607474
C11: ='1.Premissas Receitas'!A27 -> # de clientes Assinatura 2 | G11: ='1.Premissas Receitas'!G27 -> 0.3 | H11: =G11+(G11*'1.Premissas Receitas'!$B$19) -> 0.309 | I11: =H11+(H11*'1.Premissas Receitas'!$B$19) -> 0.31827 | J11: =I11+(I11*'1.Premissas Receitas'!$B$19) -> 0.3278181 | K11: =J11+(J11*'1.Premissas Receitas'!$B$19) -> 0.33765264 | L11: =K11+(K11*'1.Premissas Receitas'!$B$19) -> 0.34778222 | M11: =L11+(L11*'1.Premissas Receitas'!$B$19) -> 0.35821569 | N11: =M11+(M11*'1.Premissas Receitas'!$B$19) -> 0.36896216 | O11: =N11+(N11*'1.Premissas Receitas'!$B$19) -> 0.38003102 | ... R11: =Q11+(Q11*'1.Premissas Receitas'!$B$19) -> 0.41527016 | S11: =R11+(R11*'1.Premissas Receitas'!$G$16) -> 0.58137823 | T11: =S11+(S11*'1.Premissas Receitas'!$B$19) -> 0.59881957 | U11: =T11+(T11*'1.Premissas Receitas'!$B$19) -> 0.61678416 | V11: =U11+(U11*'1.Premissas Receitas'!$B$19) -> 0.63528768 | W11: =V11+(V11*'1.Premissas Receitas'!$B$19) -> 0.65434631 | X11: =W11+(W11*'1.Premissas Receitas'!$B$19) -> 0.6739767 | Y11: =X11+(X11*'1.Premissas Receitas'!$B$19) -> 0.69419601 | Z11: =Y11+(Y11*'1.Premissas Receitas'!$B$19) -> 0.71502189 | AA11: =Z11+(Z11*'1.Premissas Receitas'!$B$19) -> 0.73647254 | ... AD11: =AC11+(AC11*'1.Premissas Receitas'!$B$19) -> 0.80476343 | AE11: =AD11+(AD11*'1.Premissas Receitas'!$G$17) -> 1.0461925 | AF11: =AE11+(AE11*'1.Premissas Receitas'!$B$19) -> 1.0775782 | AG11: =AF11+(AF11*'1.Premissas Receitas'!$B$19) -> 1.1099056 | AH11: =AG11+(AG11*'1.Premissas Receitas'!$B$19) -> 1.1432027 | AI11: =AH11+(AH11*'1.Premissas Receitas'!$B$19) -> 1.1774988 | AJ11: =AI11+(AI11*'1.Premissas Receitas'!$B$19) -> 1.2128238 | AK11: =AJ11+(AJ11*'1.Premissas Receitas'!$B$19) -> 1.2492085 | AL11: =AK11+(AK11*'1.Premissas Receitas'!$B$19) -> 1.2866848 | AM11: =AL11+(AL11*'1.Premissas Receitas'!$B$19) -> 1.3252853 | ... AP11: =AO11+(AO11*'1.Premissas Receitas'!$B$19) -> 1.448175 | AQ11: =AP11+(AP11*'1.Premissas Receitas'!$G$18) -> 1.73781 | AR11: =AQ11+(AQ11*'1.Premissas Receitas'!$B$19) -> 1.7899443 | AS11: =AR11+(AR11*'1.Premissas Receitas'!$B$19) -> 1.8436427 | AT11: =AS11+(AS11*'1.Premissas Receitas'!$B$19) -> 1.898952 | AU11: =AT11+(AT11*'1.Premissas Receitas'!$B$19) -> 1.9559205 | AV11: =AU11+(AU11*'1.Premissas Receitas'!$B$19) -> 2.0145981 | AW11: =AV11+(AV11*'1.Premissas Receitas'!$B$19) -> 2.0750361 | AX11: =AW11+(AW11*'1.Premissas Receitas'!$B$19) -> 2.1372872 | AY11: =AX11+(AX11*'1.Premissas Receitas'!$B$19) -> 2.2014058 | ... BB11: =BA11+(BA11*'1.Premissas Receitas'!$B$19) -> 2.4055355 | BC11: =BB11+(BB11*'1.Premissas Receitas'!$G$19) -> 2.7663659 | BD11: =BC11+(BC11*'1.Premissas Receitas'!$B$19) -> 2.8493568 | BE11: =BD11+(BD11*'1.Premissas Receitas'!$B$19) -> 2.9348375 | BF11: =BE11+(BE11*'1.Premissas Receitas'!$B$19) -> 3.0228827 | BG11: =BF11+(BF11*'1.Premissas Receitas'!$B$19) -> 3.1135691 | BH11: =BG11+(BG11*'1.Premissas Receitas'!$B$19) -> 3.2069762 | BI11: =BH11+(BH11*'1.Premissas Receitas'!$B$19) -> 3.3031855 | BJ11: =BI11+(BI11*'1.Premissas Receitas'!$B$19) -> 3.4022811 | BK11: =BJ11+(BJ11*'1.Premissas Receitas'!$B$19) -> 3.5043495 | ... BN11: =BM11+(BM11*'1.Premissas Receitas'!$B$19) -> 3.8292973 | BP11: =SUM(G11:R11) -> 4.2576089 | BQ11: =SUM(T11:AD11) -> 7.6695587 | BR11: =SUM(AE11:AP11) -> 14.847594 | BS11: =SUM(AQ11:BB11) -> 24.663052 | BT11: =SUM(BC11:BN11) -> 39.260346
C12: ='1.Premissas Receitas'!A33 -> # de clientes marketplace % Comissão 1 | G12: ='1.Premissas Receitas'!G33 -> 0 | H12: =G12+(G12*'1.Premissas Receitas'!$B$19) -> 0 | I12: =H12+(H12*'1.Premissas Receitas'!$B$19) -> 0 | J12: =I12+(I12*'1.Premissas Receitas'!$B$19) -> 0 | K12: =J12+(J12*'1.Premissas Receitas'!$B$19) -> 0 | L12: =K12+(K12*'1.Premissas Receitas'!$B$19) -> 0 | M12: =L12+(L12*'1.Premissas Receitas'!$B$19) -> 0 | N12: =M12+(M12*'1.Premissas Receitas'!$B$19) -> 0 | O12: =N12+(N12*'1.Premissas Receitas'!$B$19) -> 0 | ... R12: =Q12+(Q12*'1.Premissas Receitas'!$B$19) -> 0 | S12: =R12+(R12*'1.Premissas Receitas'!$G$16) -> 0 | T12: =S12+(S12*'1.Premissas Receitas'!$B$19) -> 0 | U12: =T12+(T12*'1.Premissas Receitas'!$B$19) -> 0 | V12: =U12+(U12*'1.Premissas Receitas'!$B$19) -> 0 | W12: =V12+(V12*'1.Premissas Receitas'!$B$19) -> 0 | X12: =W12+(W12*'1.Premissas Receitas'!$B$19) -> 0 | Y12: =X12+(X12*'1.Premissas Receitas'!$B$19) -> 0 | Z12: =Y12+(Y12*'1.Premissas Receitas'!$B$19) -> 0 | AA12: =Z12+(Z12*'1.Premissas Receitas'!$B$19) -> 0 | ... AD12: =AC12+(AC12*'1.Premissas Receitas'!$B$19) -> 0 | AE12: =AD12+(AD12*'1.Premissas Receitas'!$G$17) -> 0 | AF12: =AE12+(AE12*'1.Premissas Receitas'!$B$19) -> 0 | AG12: =AF12+(AF12*'1.Premissas Receitas'!$B$19) -> 0 | AH12: =AG12+(AG12*'1.Premissas Receitas'!$B$19) -> 0 | AI12: =AH12+(AH12*'1.Premissas Receitas'!$B$19) -> 0 | AJ12: =AI12+(AI12*'1.Premissas Receitas'!$B$19) -> 0 | AK12: =AJ12+(AJ12*'1.Premissas Receitas'!$B$19) -> 0 | AL12: =AK12+(AK12*'1.Premissas Receitas'!$B$19) -> 0 | AM12: =AL12+(AL12*'1.Premissas Receitas'!$B$19) -> 0 | ... AP12: =AO12+(AO12*'1.Premissas Receitas'!$B$19) -> 0 | AQ12: =AP12+(AP12*'1.Premissas Receitas'!$G$18) -> 0 | AR12: =AQ12+(AQ12*'1.Premissas Receitas'!$B$19) -> 0 | AS12: =AR12+(AR12*'1.Premissas Receitas'!$B$19) -> 0 | AT12: =AS12+(AS12*'1.Premissas Receitas'!$B$19) -> 0 | AU12: =AT12+(AT12*'1.Premissas Receitas'!$B$19) -> 0 | AV12: =AU12+(AU12*'1.Premissas Receitas'!$B$19) -> 0 | AW12: =AV12+(AV12*'1.Premissas Receitas'!$B$19) -> 0 | AX12: =AW12+(AW12*'1.Premissas Receitas'!$B$19) -> 0 | AY12: =AX12+(AX12*'1.Premissas Receitas'!$B$19) -> 0 | ... BB12: =BA12+(BA12*'1.Premissas Receitas'!$B$19) -> 0 | BC12: =BB12+(BB12*'1.Premissas Receitas'!$G$19) -> 0 | BD12: =BC12+(BC12*'1.Premissas Receitas'!$B$19) -> 0 | BE12: =BD12+(BD12*'1.Premissas Receitas'!$B$19) -> 0 | BF12: =BE12+(BE12*'1.Premissas Receitas'!$B$19) -> 0 | BG12: =BF12+(BF12*'1.Premissas Receitas'!$B$19) -> 0 | BH12: =BG12+(BG12*'1.Premissas Receitas'!$B$19) -> 0 | BI12: =BH12+(BH12*'1.Premissas Receitas'!$B$19) -> 0 | BJ12: =BI12+(BI12*'1.Premissas Receitas'!$B$19) -> 0 | BK12: =BJ12+(BJ12*'1.Premissas Receitas'!$B$19) -> 0 | ... BN12: =BM12+(BM12*'1.Premissas Receitas'!$B$19) -> 0 | BP12: =SUM(G12:R12) -> 0 | BQ12: =SUM(T12:AD12) -> 0 | BR12: =SUM(AE12:AP12) -> 0 | BS12: =SUM(AQ12:BB12) -> 0 | BT12: =SUM(BC12:BN12) -> 0
C13: ='1.Premissas Receitas'!A34 -> # de clientes marketplace % Comissão 2 | G13: ='1.Premissas Receitas'!G34 -> 0 | H13: =G13+(G13*'1.Premissas Receitas'!$B$19) -> 0 | I13: =H13+(H13*'1.Premissas Receitas'!$B$19) -> 0 | J13: =I13+(I13*'1.Premissas Receitas'!$B$19) -> 0 | K13: =J13+(J13*'1.Premissas Receitas'!$B$19) -> 0 | L13: =K13+(K13*'1.Premissas Receitas'!$B$19) -> 0 | M13: =L13+(L13*'1.Premissas Receitas'!$B$19) -> 0 | N13: =M13+(M13*'1.Premissas Receitas'!$B$19) -> 0 | O13: =N13+(N13*'1.Premissas Receitas'!$B$19) -> 0 | ... R13: =Q13+(Q13*'1.Premissas Receitas'!$B$19) -> 0 | S13: =R13+(R13*'1.Premissas Receitas'!$G$16) -> 0 | T13: =S13+(S13*'1.Premissas Receitas'!$B$19) -> 0 | U13: =T13+(T13*'1.Premissas Receitas'!$B$19) -> 0 | V13: =U13+(U13*'1.Premissas Receitas'!$B$19) -> 0 | W13: =V13+(V13*'1.Premissas Receitas'!$B$19) -> 0 | X13: =W13+(W13*'1.Premissas Receitas'!$B$19) -> 0 | Y13: =X13+(X13*'1.Premissas Receitas'!$B$19) -> 0 | Z13: =Y13+(Y13*'1.Premissas Receitas'!$B$19) -> 0 | AA13: =Z13+(Z13*'1.Premissas Receitas'!$B$19) -> 0 | ... AD13: =AC13+(AC13*'1.Premissas Receitas'!$B$19) -> 0 | AE13: =AD13+(AD13*'1.Premissas Receitas'!$G$17) -> 0 | AF13: =AE13+(AE13*'1.Premissas Receitas'!$B$19) -> 0 | AG13: =AF13+(AF13*'1.Premissas Receitas'!$B$19) -> 0 | AH13: =AG13+(AG13*'1.Premissas Receitas'!$B$19) -> 0 | AI13: =AH13+(AH13*'1.Premissas Receitas'!$B$19) -> 0 | AJ13: =AI13+(AI13*'1.Premissas Receitas'!$B$19) -> 0 | AK13: =AJ13+(AJ13*'1.Premissas Receitas'!$B$19) -> 0 | AL13: =AK13+(AK13*'1.Premissas Receitas'!$B$19) -> 0 | AM13: =AL13+(AL13*'1.Premissas Receitas'!$B$19) -> 0 | ... AP13: =AO13+(AO13*'1.Premissas Receitas'!$B$19) -> 0 | AQ13: =AP13+(AP13*'1.Premissas Receitas'!$G$18) -> 0 | AR13: =AQ13+(AQ13*'1.Premissas Receitas'!$B$19) -> 0 | AS13: =AR13+(AR13*'1.Premissas Receitas'!$B$19) -> 0 | AT13: =AS13+(AS13*'1.Premissas Receitas'!$B$19) -> 0 | AU13: =AT13+(AT13*'1.Premissas Receitas'!$B$19) -> 0 | AV13: =AU13+(AU13*'1.Premissas Receitas'!$B$19) -> 0 | AW13: =AV13+(AV13*'1.Premissas Receitas'!$B$19) -> 0 | AX13: =AW13+(AW13*'1.Premissas Receitas'!$B$19) -> 0 | AY13: =AX13+(AX13*'1.Premissas Receitas'!$B$19) -> 0 | ... BB13: =BA13+(BA13*'1.Premissas Receitas'!$B$19) -> 0 | BC13: =BB13+(BB13*'1.Premissas Receitas'!$G$19) -> 0 | BD13: =BC13+(BC13*'1.Premissas Receitas'!$B$19) -> 0 | BE13: =BD13+(BD13*'1.Premissas Receitas'!$B$19) -> 0 | BF13: =BE13+(BE13*'1.Premissas Receitas'!$B$19) -> 0 | BG13: =BF13+(BF13*'1.Premissas Receitas'!$B$19) -> 0 | BH13: =BG13+(BG13*'1.Premissas Receitas'!$B$19) -> 0 | BI13: =BH13+(BH13*'1.Premissas Receitas'!$B$19) -> 0 | BJ13: =BI13+(BI13*'1.Premissas Receitas'!$B$19) -> 0 | BK13: =BJ13+(BJ13*'1.Premissas Receitas'!$B$19) -> 0 | ... BN13: =BM13+(BM13*'1.Premissas Receitas'!$B$19) -> 0 | BP13: =SUM(G13:R13) -> 0 | BQ13: =SUM(T13:AD13) -> 0 | BR13: =SUM(AE13:AP13) -> 0 | BS13: =SUM(AQ13:BB13) -> 0 | BT13: =SUM(BC13:BN13) -> 0
C14: ='1.Premissas Receitas'!A35 -> # de clientes marketplace % Comissão 3 | G14: ='1.Premissas Receitas'!G35 -> 0 | H14: =G14+(G14*'1.Premissas Receitas'!$B$19) -> 0 | I14: =H14+(H14*'1.Premissas Receitas'!$B$19) -> 0 | J14: =I14+(I14*'1.Premissas Receitas'!$B$19) -> 0 | K14: =J14+(J14*'1.Premissas Receitas'!$B$19) -> 0 | L14: =K14+(K14*'1.Premissas Receitas'!$B$19) -> 0 | M14: =L14+(L14*'1.Premissas Receitas'!$B$19) -> 0 | N14: =M14+(M14*'1.Premissas Receitas'!$B$19) -> 0 | O14: =N14+(N14*'1.Premissas Receitas'!$B$19) -> 0 | ... R14: =Q14+(Q14*'1.Premissas Receitas'!$B$19) -> 0 | S14: =R14+(R14*'1.Premissas Receitas'!$G$16) -> 0 | T14: =S14+(S14*'1.Premissas Receitas'!$B$19) -> 0 | U14: =T14+(T14*'1.Premissas Receitas'!$B$19) -> 0 | V14: =U14+(U14*'1.Premissas Receitas'!$B$19) -> 0 | W14: =V14+(V14*'1.Premissas Receitas'!$B$19) -> 0 | X14: =W14+(W14*'1.Premissas Receitas'!$B$19) -> 0 | Y14: =X14+(X14*'1.Premissas Receitas'!$B$19) -> 0 | Z14: =Y14+(Y14*'1.Premissas Receitas'!$B$19) -> 0 | AA14: =Z14+(Z14*'1.Premissas Receitas'!$B$19) -> 0 | ... AD14: =AC14+(AC14*'1.Premissas Receitas'!$B$19) -> 0 | AE14: =AD14+(AD14*'1.Premissas Receitas'!$G$17) -> 0 | AF14: =AE14+(AE14*'1.Premissas Receitas'!$B$19) -> 0 | AG14: =AF14+(AF14*'1.Premissas Receitas'!$B$19) -> 0 | AH14: =AG14+(AG14*'1.Premissas Receitas'!$B$19) -> 0 | AI14: =AH14+(AH14*'1.Premissas Receitas'!$B$19) -> 0 | AJ14: =AI14+(AI14*'1.Premissas Receitas'!$B$19) -> 0 | AK14: =AJ14+(AJ14*'1.Premissas Receitas'!$B$19) -> 0 | AL14: =AK14+(AK14*'1.Premissas Receitas'!$B$19) -> 0 | AM14: =AL14+(AL14*'1.Premissas Receitas'!$B$19) -> 0 | ... AP14: =AO14+(AO14*'1.Premissas Receitas'!$B$19) -> 0 | AQ14: =AP14+(AP14*'1.Premissas Receitas'!$G$18) -> 0 | AR14: =AQ14+(AQ14*'1.Premissas Receitas'!$B$19) -> 0 | AS14: =AR14+(AR14*'1.Premissas Receitas'!$B$19) -> 0 | AT14: =AS14+(AS14*'1.Premissas Receitas'!$B$19) -> 0 | AU14: =AT14+(AT14*'1.Premissas Receitas'!$B$19) -> 0 | AV14: =AU14+(AU14*'1.Premissas Receitas'!$B$19) -> 0 | AW14: =AV14+(AV14*'1.Premissas Receitas'!$B$19) -> 0 | AX14: =AW14+(AW14*'1.Premissas Receitas'!$B$19) -> 0 | AY14: =AX14+(AX14*'1.Premissas Receitas'!$B$19) -> 0 | ... BB14: =BA14+(BA14*'1.Premissas Receitas'!$B$19) -> 0 | BC14: =BB14+(BB14*'1.Premissas Receitas'!$G$19) -> 0 | BD14: =BC14+(BC14*'1.Premissas Receitas'!$B$19) -> 0 | BE14: =BD14+(BD14*'1.Premissas Receitas'!$B$19) -> 0 | BF14: =BE14+(BE14*'1.Premissas Receitas'!$B$19) -> 0 | BG14: =BF14+(BF14*'1.Premissas Receitas'!$B$19) -> 0 | BH14: =BG14+(BG14*'1.Premissas Receitas'!$B$19) -> 0 | BI14: =BH14+(BH14*'1.Premissas Receitas'!$B$19) -> 0 | BJ14: =BI14+(BI14*'1.Premissas Receitas'!$B$19) -> 0 | BK14: =BJ14+(BJ14*'1.Premissas Receitas'!$B$19) -> 0 | ... BN14: =BM14+(BM14*'1.Premissas Receitas'!$B$19) -> 0 | BP14: =SUM(G14:R14) -> 0 | BQ14: =SUM(T14:AD14) -> 0 | BR14: =SUM(AE14:AP14) -> 0 | BS14: =SUM(AQ14:BB14) -> 0 | BT14: =SUM(BC14:BN14) -> 0
C15: ='1.Premissas Receitas'!A40 -> # de clientes B2B Setup | G15: ='1.Premissas Receitas'!G40 -> 1.3333333 | H15: =G15+(G15*'1.Premissas Receitas'!$B$19) -> 1.3733333 | I15: =H15+(H15*'1.Premissas Receitas'!$B$19) -> 1.4145333 | J15: =I15+(I15*'1.Premissas Receitas'!$B$19) -> 1.4569693 | K15: =J15+(J15*'1.Premissas Receitas'!$B$19) -> 1.5006784 | L15: =K15+(K15*'1.Premissas Receitas'!$B$19) -> 1.5456988 | M15: =L15+(L15*'1.Premissas Receitas'!$B$19) -> 1.5920697 | N15: =M15+(M15*'1.Premissas Receitas'!$B$19) -> 1.6398318 | O15: =N15+(N15*'1.Premissas Receitas'!$B$19) -> 1.6890268 | ... R15: =Q15+(Q15*'1.Premissas Receitas'!$B$19) -> 1.8456452 | S15: =R15+(R15*'1.Premissas Receitas'!$G$16) -> 2.5839032 | T15: =S15+(S15*'1.Premissas Receitas'!$B$19) -> 2.6614203 | U15: =T15+(T15*'1.Premissas Receitas'!$B$19) -> 2.7412629 | V15: =U15+(U15*'1.Premissas Receitas'!$B$19) -> 2.8235008 | W15: =V15+(V15*'1.Premissas Receitas'!$B$19) -> 2.9082058 | X15: =W15+(W15*'1.Premissas Receitas'!$B$19) -> 2.995452 | Y15: =X15+(X15*'1.Premissas Receitas'!$B$19) -> 3.0853156 | Z15: =Y15+(Y15*'1.Premissas Receitas'!$B$19) -> 3.177875 | AA15: =Z15+(Z15*'1.Premissas Receitas'!$B$19) -> 3.2732113 | ... AD15: =AC15+(AC15*'1.Premissas Receitas'!$B$19) -> 3.5767264 | AE15: =AD15+(AD15*'1.Premissas Receitas'!$G$17) -> 4.6497443 | AF15: =AE15+(AE15*'1.Premissas Receitas'!$B$19) -> 4.7892366 | AG15: =AF15+(AF15*'1.Premissas Receitas'!$B$19) -> 4.9329137 | AH15: =AG15+(AG15*'1.Premissas Receitas'!$B$19) -> 5.0809011 | AI15: =AH15+(AH15*'1.Premissas Receitas'!$B$19) -> 5.2333281 | AJ15: =AI15+(AI15*'1.Premissas Receitas'!$B$19) -> 5.390328 | AK15: =AJ15+(AJ15*'1.Premissas Receitas'!$B$19) -> 5.5520378 | AL15: =AK15+(AK15*'1.Premissas Receitas'!$B$19) -> 5.718599 | AM15: =AL15+(AL15*'1.Premissas Receitas'!$B$19) -> 5.8901569 | ... AP15: =AO15+(AO15*'1.Premissas Receitas'!$B$19) -> 6.4363335 | AQ15: =AP15+(AP15*'1.Premissas Receitas'!$G$18) -> 7.7236002 | AR15: =AQ15+(AQ15*'1.Premissas Receitas'!$B$19) -> 7.9553082 | AS15: =AR15+(AR15*'1.Premissas Receitas'!$B$19) -> 8.1939675 | AT15: =AS15+(AS15*'1.Premissas Receitas'!$B$19) -> 8.4397865 | AU15: =AT15+(AT15*'1.Premissas Receitas'!$B$19) -> 8.6929801 | AV15: =AU15+(AU15*'1.Premissas Receitas'!$B$19) -> 8.9537695 | AW15: =AV15+(AV15*'1.Premissas Receitas'!$B$19) -> 9.2223826 | AX15: =AW15+(AW15*'1.Premissas Receitas'!$B$19) -> 9.4990541 | AY15: =AX15+(AX15*'1.Premissas Receitas'!$B$19) -> 9.7840257 | ... BB15: =BA15+(BA15*'1.Premissas Receitas'!$B$19) -> 10.691269 | BC15: =BB15+(BB15*'1.Premissas Receitas'!$G$19) -> 12.294959 | BD15: =BC15+(BC15*'1.Premissas Receitas'!$B$19) -> 12.663808 | BE15: =BD15+(BD15*'1.Premissas Receitas'!$B$19) -> 13.043722 | BF15: =BE15+(BE15*'1.Premissas Receitas'!$B$19) -> 13.435034 | BG15: =BF15+(BF15*'1.Premissas Receitas'!$B$19) -> 13.838085 | BH15: =BG15+(BG15*'1.Premissas Receitas'!$B$19) -> 14.253228 | BI15: =BH15+(BH15*'1.Premissas Receitas'!$B$19) -> 14.680824 | BJ15: =BI15+(BI15*'1.Premissas Receitas'!$B$19) -> 15.121249 | BK15: =BJ15+(BJ15*'1.Premissas Receitas'!$B$19) -> 15.574887 | ... BN15: =BM15+(BM15*'1.Premissas Receitas'!$B$19) -> 17.019099 | BP15: =SUM(G15:R15) -> 18.922706 | BQ15: =SUM(T15:AD15) -> 34.086928 | BR15: =SUM(AE15:AP15) -> 65.989308 | BS15: =SUM(AQ15:BB15) -> 109.61356 | BT15: =SUM(BC15:BN15) -> 174.49043
C16: ='1.Premissas Receitas'!A41 -> # de clientes B2B Mensalidade | G16: ='1.Premissas Receitas'!G41 -> 1.3333333 | H16: =G16+(G16*'1.Premissas Receitas'!$B$19) -> 1.3733333 | I16: =H16+(H16*'1.Premissas Receitas'!$B$19) -> 1.4145333 | J16: =I16+(I16*'1.Premissas Receitas'!$B$19) -> 1.4569693 | K16: =J16+(J16*'1.Premissas Receitas'!$B$19) -> 1.5006784 | L16: =K16+(K16*'1.Premissas Receitas'!$B$19) -> 1.5456988 | M16: =L16+(L16*'1.Premissas Receitas'!$B$19) -> 1.5920697 | N16: =M16+(M16*'1.Premissas Receitas'!$B$19) -> 1.6398318 | O16: =N16+(N16*'1.Premissas Receitas'!$B$19) -> 1.6890268 | ... R16: =Q16+(Q16*'1.Premissas Receitas'!$B$19) -> 1.8456452 | S16: =R16+(R16*'1.Premissas Receitas'!$G$16) -> 2.5839032 | T16: =S16+(S16*'1.Premissas Receitas'!$B$19) -> 2.6614203 | U16: =T16+(T16*'1.Premissas Receitas'!$B$19) -> 2.7412629 | V16: =U16+(U16*'1.Premissas Receitas'!$B$19) -> 2.8235008 | W16: =V16+(V16*'1.Premissas Receitas'!$B$19) -> 2.9082058 | X16: =W16+(W16*'1.Premissas Receitas'!$B$19) -> 2.995452 | Y16: =X16+(X16*'1.Premissas Receitas'!$B$19) -> 3.0853156 | Z16: =Y16+(Y16*'1.Premissas Receitas'!$B$19) -> 3.177875 | AA16: =Z16+(Z16*'1.Premissas Receitas'!$B$19) -> 3.2732113 | ... AD16: =AC16+(AC16*'1.Premissas Receitas'!$B$19) -> 3.5767264 | AE16: =AD16+(AD16*'1.Premissas Receitas'!$G$17) -> 4.6497443 | AF16: =AE16+(AE16*'1.Premissas Receitas'!$B$19) -> 4.7892366 | AG16: =AF16+(AF16*'1.Premissas Receitas'!$B$19) -> 4.9329137 | AH16: =AG16+(AG16*'1.Premissas Receitas'!$B$19) -> 5.0809011 | AI16: =AH16+(AH16*'1.Premissas Receitas'!$B$19) -> 5.2333281 | AJ16: =AI16+(AI16*'1.Premissas Receitas'!$B$19) -> 5.390328 | AK16: =AJ16+(AJ16*'1.Premissas Receitas'!$B$19) -> 5.5520378 | AL16: =AK16+(AK16*'1.Premissas Receitas'!$B$19) -> 5.718599 | AM16: =AL16+(AL16*'1.Premissas Receitas'!$B$19) -> 5.8901569 | ... AP16: =AO16+(AO16*'1.Premissas Receitas'!$B$19) -> 6.4363335 | AQ16: =AP16+(AP16*'1.Premissas Receitas'!$G$18) -> 7.7236002 | AR16: =AQ16+(AQ16*'1.Premissas Receitas'!$B$19) -> 7.9553082 | AS16: =AR16+(AR16*'1.Premissas Receitas'!$B$19) -> 8.1939675 | AT16: =AS16+(AS16*'1.Premissas Receitas'!$B$19) -> 8.4397865 | AU16: =AT16+(AT16*'1.Premissas Receitas'!$B$19) -> 8.6929801 | AV16: =AU16+(AU16*'1.Premissas Receitas'!$B$19) -> 8.9537695 | AW16: =AV16+(AV16*'1.Premissas Receitas'!$B$19) -> 9.2223826 | AX16: =AW16+(AW16*'1.Premissas Receitas'!$B$19) -> 9.4990541 | AY16: =AX16+(AX16*'1.Premissas Receitas'!$B$19) -> 9.7840257 | ... BB16: =BA16+(BA16*'1.Premissas Receitas'!$B$19) -> 10.691269 | BC16: =BB16+(BB16*'1.Premissas Receitas'!$G$19) -> 12.294959 | BD16: =BC16+(BC16*'1.Premissas Receitas'!$B$19) -> 12.663808 | BE16: =BD16+(BD16*'1.Premissas Receitas'!$B$19) -> 13.043722 | BF16: =BE16+(BE16*'1.Premissas Receitas'!$B$19) -> 13.435034 | BG16: =BF16+(BF16*'1.Premissas Receitas'!$B$19) -> 13.838085 | BH16: =BG16+(BG16*'1.Premissas Receitas'!$B$19) -> 14.253228 | BI16: =BH16+(BH16*'1.Premissas Receitas'!$B$19) -> 14.680824 | BJ16: =BI16+(BI16*'1.Premissas Receitas'!$B$19) -> 15.121249 | BK16: =BJ16+(BJ16*'1.Premissas Receitas'!$B$19) -> 15.574887 | ... BN16: =BM16+(BM16*'1.Premissas Receitas'!$B$19) -> 17.019099 | BP16: =SUM(G16:R16) -> 18.922706 | BQ16: =SUM(T16:AD16) -> 34.086928 | BR16: =SUM(AE16:AP16) -> 65.989308 | BS16: =SUM(AQ16:BB16) -> 109.61356 | BT16: =SUM(BC16:BN16) -> 174.49043
C17: ='1.Premissas Receitas'!A42 -> # de clientes B2B Manutenção | G17: ='1.Premissas Receitas'!G42 -> 0 | H17: =G17+(G17*'1.Premissas Receitas'!$B$19) -> 0 | I17: =H17+(H17*'1.Premissas Receitas'!$B$19) -> 0 | J17: =I17+(I17*'1.Premissas Receitas'!$B$19) -> 0 | K17: =J17+(J17*'1.Premissas Receitas'!$B$19) -> 0 | L17: =K17+(K17*'1.Premissas Receitas'!$B$19) -> 0 | M17: =L17+(L17*'1.Premissas Receitas'!$B$19) -> 0 | N17: =M17+(M17*'1.Premissas Receitas'!$B$19) -> 0 | O17: =N17+(N17*'1.Premissas Receitas'!$B$19) -> 0 | ... R17: =Q17+(Q17*'1.Premissas Receitas'!$B$19) -> 0 | S17: =R17+(R17*'1.Premissas Receitas'!$G$16) -> 0 | T17: =S17+(S17*'1.Premissas Receitas'!$B$19) -> 0 | U17: =T17+(T17*'1.Premissas Receitas'!$B$19) -> 0 | V17: =U17+(U17*'1.Premissas Receitas'!$B$19) -> 0 | W17: =V17+(V17*'1.Premissas Receitas'!$B$19) -> 0 | X17: =W17+(W17*'1.Premissas Receitas'!$B$19) -> 0 | Y17: =X17+(X17*'1.Premissas Receitas'!$B$19) -> 0 | Z17: =Y17+(Y17*'1.Premissas Receitas'!$B$19) -> 0 | AA17: =Z17+(Z17*'1.Premissas Receitas'!$B$19) -> 0 | ... AD17: =AC17+(AC17*'1.Premissas Receitas'!$B$19) -> 0 | AE17: =AD17+(AD17*'1.Premissas Receitas'!$G$17) -> 0 | AF17: =AE17+(AE17*'1.Premissas Receitas'!$B$19) -> 0 | AG17: =AF17+(AF17*'1.Premissas Receitas'!$B$19) -> 0 | AH17: =AG17+(AG17*'1.Premissas Receitas'!$B$19) -> 0 | AI17: =AH17+(AH17*'1.Premissas Receitas'!$B$19) -> 0 | AJ17: =AI17+(AI17*'1.Premissas Receitas'!$B$19) -> 0 | AK17: =AJ17+(AJ17*'1.Premissas Receitas'!$B$19) -> 0 | AL17: =AK17+(AK17*'1.Premissas Receitas'!$B$19) -> 0 | AM17: =AL17+(AL17*'1.Premissas Receitas'!$B$19) -> 0 | ... AP17: =AO17+(AO17*'1.Premissas Receitas'!$B$19) -> 0 | AQ17: =AP17+(AP17*'1.Premissas Receitas'!$G$18) -> 0 | AR17: =AQ17+(AQ17*'1.Premissas Receitas'!$B$19) -> 0 | AS17: =AR17+(AR17*'1.Premissas Receitas'!$B$19) -> 0 | AT17: =AS17+(AS17*'1.Premissas Receitas'!$B$19) -> 0 | AU17: =AT17+(AT17*'1.Premissas Receitas'!$B$19) -> 0 | AV17: =AU17+(AU17*'1.Premissas Receitas'!$B$19) -> 0 | AW17: =AV17+(AV17*'1.Premissas Receitas'!$B$19) -> 0 | AX17: =AW17+(AW17*'1.Premissas Receitas'!$B$19) -> 0 | AY17: =AX17+(AX17*'1.Premissas Receitas'!$B$19) -> 0 | ... BB17: =BA17+(BA17*'1.Premissas Receitas'!$B$19) -> 0 | BC17: =BB17+(BB17*'1.Premissas Receitas'!$G$19) -> 0 | BD17: =BC17+(BC17*'1.Premissas Receitas'!$B$19) -> 0 | BE17: =BD17+(BD17*'1.Premissas Receitas'!$B$19) -> 0 | BF17: =BE17+(BE17*'1.Premissas Receitas'!$B$19) -> 0 | BG17: =BF17+(BF17*'1.Premissas Receitas'!$B$19) -> 0 | BH17: =BG17+(BG17*'1.Premissas Receitas'!$B$19) -> 0 | BI17: =BH17+(BH17*'1.Premissas Receitas'!$B$19) -> 0 | BJ17: =BI17+(BI17*'1.Premissas Receitas'!$B$19) -> 0 | BK17: =BJ17+(BJ17*'1.Premissas Receitas'!$B$19) -> 0 | ... BN17: =BM17+(BM17*'1.Premissas Receitas'!$B$19) -> 0 | BP17: =SUM(G17:R17) -> 0 | BQ17: =SUM(T17:AD17) -> 0 | BR17: =SUM(AE17:AP17) -> 0 | BS17: =SUM(AQ17:BB17) -> 0 | BT17: =SUM(BC17:BN17) -> 0
C18: ='1.Premissas Receitas'!A48 -> # de clientes Conteudo/ Paywall 1 | G18: ='1.Premissas Receitas'!G48 -> 0 | H18: =G18+(G18*'1.Premissas Receitas'!$B$19) -> 0 | I18: =H18+(H18*'1.Premissas Receitas'!$B$19) -> 0 | J18: =I18+(I18*'1.Premissas Receitas'!$B$19) -> 0 | K18: =J18+(J18*'1.Premissas Receitas'!$B$19) -> 0 | L18: =K18+(K18*'1.Premissas Receitas'!$B$19) -> 0 | M18: =L18+(L18*'1.Premissas Receitas'!$B$19) -> 0 | N18: =M18+(M18*'1.Premissas Receitas'!$B$19) -> 0 | O18: =N18+(N18*'1.Premissas Receitas'!$B$19) -> 0 | ... R18: =Q18+(Q18*'1.Premissas Receitas'!$B$19) -> 0 | S18: =R18+(R18*'1.Premissas Receitas'!$G$16) -> 0 | T18: =S18+(S18*'1.Premissas Receitas'!$B$19) -> 0 | U18: =T18+(T18*'1.Premissas Receitas'!$B$19) -> 0 | V18: =U18+(U18*'1.Premissas Receitas'!$B$19) -> 0 | W18: =V18+(V18*'1.Premissas Receitas'!$B$19) -> 0 | X18: =W18+(W18*'1.Premissas Receitas'!$B$19) -> 0 | Y18: =X18+(X18*'1.Premissas Receitas'!$B$19) -> 0 | Z18: =Y18+(Y18*'1.Premissas Receitas'!$B$19) -> 0 | AA18: =Z18+(Z18*'1.Premissas Receitas'!$B$19) -> 0 | ... AD18: =AC18+(AC18*'1.Premissas Receitas'!$B$19) -> 0 | AE18: =AD18+(AD18*'1.Premissas Receitas'!$G$17) -> 0 | AF18: =AE18+(AE18*'1.Premissas Receitas'!$B$19) -> 0 | AG18: =AF18+(AF18*'1.Premissas Receitas'!$B$19) -> 0 | AH18: =AG18+(AG18*'1.Premissas Receitas'!$B$19) -> 0 | AI18: =AH18+(AH18*'1.Premissas Receitas'!$B$19) -> 0 | AJ18: =AI18+(AI18*'1.Premissas Receitas'!$B$19) -> 0 | AK18: =AJ18+(AJ18*'1.Premissas Receitas'!$B$19) -> 0 | AL18: =AK18+(AK18*'1.Premissas Receitas'!$B$19) -> 0 | AM18: =AL18+(AL18*'1.Premissas Receitas'!$B$19) -> 0 | ... AP18: =AO18+(AO18*'1.Premissas Receitas'!$B$19) -> 0 | AQ18: =AP18+(AP18*'1.Premissas Receitas'!$G$18) -> 0 | AR18: =AQ18+(AQ18*'1.Premissas Receitas'!$B$19) -> 0 | AS18: =AR18+(AR18*'1.Premissas Receitas'!$B$19) -> 0 | AT18: =AS18+(AS18*'1.Premissas Receitas'!$B$19) -> 0 | AU18: =AT18+(AT18*'1.Premissas Receitas'!$B$19) -> 0 | AV18: =AU18+(AU18*'1.Premissas Receitas'!$B$19) -> 0 | AW18: =AV18+(AV18*'1.Premissas Receitas'!$B$19) -> 0 | AX18: =AW18+(AW18*'1.Premissas Receitas'!$B$19) -> 0 | AY18: =AX18+(AX18*'1.Premissas Receitas'!$B$19) -> 0 | ... BB18: =BA18+(BA18*'1.Premissas Receitas'!$B$19) -> 0 | BC18: =BB18+(BB18*'1.Premissas Receitas'!$G$19) -> 0 | BD18: =BC18+(BC18*'1.Premissas Receitas'!$B$19) -> 0 | BE18: =BD18+(BD18*'1.Premissas Receitas'!$B$19) -> 0 | BF18: =BE18+(BE18*'1.Premissas Receitas'!$B$19) -> 0 | BG18: =BF18+(BF18*'1.Premissas Receitas'!$B$19) -> 0 | BH18: =BG18+(BG18*'1.Premissas Receitas'!$B$19) -> 0 | BI18: =BH18+(BH18*'1.Premissas Receitas'!$B$19) -> 0 | BJ18: =BI18+(BI18*'1.Premissas Receitas'!$B$19) -> 0 | BK18: =BJ18+(BJ18*'1.Premissas Receitas'!$B$19) -> 0 | ... BN18: =BM18+(BM18*'1.Premissas Receitas'!$B$19) -> 0 | BP18: =SUM(G18:R18) -> 0 | BQ18: =SUM(T18:AD18) -> 0 | BR18: =SUM(AE18:AP18) -> 0 | BS18: =SUM(AQ18:BB18) -> 0 | BT18: =SUM(BC18:BN18) -> 0
C19: ='1.Premissas Receitas'!A49 -> # de clientes Conteudo/ Paywall 2 | G19: ='1.Premissas Receitas'!G49 -> 0 | H19: =G19+(G19*'1.Premissas Receitas'!$B$19) -> 0 | I19: =H19+(H19*'1.Premissas Receitas'!$B$19) -> 0 | J19: =I19+(I19*'1.Premissas Receitas'!$B$19) -> 0 | K19: =J19+(J19*'1.Premissas Receitas'!$B$19) -> 0 | L19: =K19+(K19*'1.Premissas Receitas'!$B$19) -> 0 | M19: =L19+(L19*'1.Premissas Receitas'!$B$19) -> 0 | N19: =M19+(M19*'1.Premissas Receitas'!$B$19) -> 0 | O19: =N19+(N19*'1.Premissas Receitas'!$B$19) -> 0 | ... R19: =Q19+(Q19*'1.Premissas Receitas'!$B$19) -> 0 | S19: =R19+(R19*'1.Premissas Receitas'!$G$16) -> 0 | T19: =S19+(S19*'1.Premissas Receitas'!$B$19) -> 0 | U19: =T19+(T19*'1.Premissas Receitas'!$B$19) -> 0 | V19: =U19+(U19*'1.Premissas Receitas'!$B$19) -> 0 | W19: =V19+(V19*'1.Premissas Receitas'!$B$19) -> 0 | X19: =W19+(W19*'1.Premissas Receitas'!$B$19) -> 0 | Y19: =X19+(X19*'1.Premissas Receitas'!$B$19) -> 0 | Z19: =Y19+(Y19*'1.Premissas Receitas'!$B$19) -> 0 | AA19: =Z19+(Z19*'1.Premissas Receitas'!$B$19) -> 0 | ... AD19: =AC19+(AC19*'1.Premissas Receitas'!$B$19) -> 0 | AE19: =AD19+(AD19*'1.Premissas Receitas'!$G$17) -> 0 | AF19: =AE19+(AE19*'1.Premissas Receitas'!$B$19) -> 0 | AG19: =AF19+(AF19*'1.Premissas Receitas'!$B$19) -> 0 | AH19: =AG19+(AG19*'1.Premissas Receitas'!$B$19) -> 0 | AI19: =AH19+(AH19*'1.Premissas Receitas'!$B$19) -> 0 | AJ19: =AI19+(AI19*'1.Premissas Receitas'!$B$19) -> 0 | AK19: =AJ19+(AJ19*'1.Premissas Receitas'!$B$19) -> 0 | AL19: =AK19+(AK19*'1.Premissas Receitas'!$B$19) -> 0 | AM19: =AL19+(AL19*'1.Premissas Receitas'!$B$19) -> 0 | ... AP19: =AO19+(AO19*'1.Premissas Receitas'!$B$19) -> 0 | AQ19: =AP19+(AP19*'1.Premissas Receitas'!$G$18) -> 0 | AR19: =AQ19+(AQ19*'1.Premissas Receitas'!$B$19) -> 0 | AS19: =AR19+(AR19*'1.Premissas Receitas'!$B$19) -> 0 | AT19: =AS19+(AS19*'1.Premissas Receitas'!$B$19) -> 0 | AU19: =AT19+(AT19*'1.Premissas Receitas'!$B$19) -> 0 | AV19: =AU19+(AU19*'1.Premissas Receitas'!$B$19) -> 0 | AW19: =AV19+(AV19*'1.Premissas Receitas'!$B$19) -> 0 | AX19: =AW19+(AW19*'1.Premissas Receitas'!$B$19) -> 0 | AY19: =AX19+(AX19*'1.Premissas Receitas'!$B$19) -> 0 | ... BB19: =BA19+(BA19*'1.Premissas Receitas'!$B$19) -> 0 | BC19: =BB19+(BB19*'1.Premissas Receitas'!$G$19) -> 0 | BD19: =BC19+(BC19*'1.Premissas Receitas'!$B$19) -> 0 | BE19: =BD19+(BD19*'1.Premissas Receitas'!$B$19) -> 0 | BF19: =BE19+(BE19*'1.Premissas Receitas'!$B$19) -> 0 | BG19: =BF19+(BF19*'1.Premissas Receitas'!$B$19) -> 0 | BH19: =BG19+(BG19*'1.Premissas Receitas'!$B$19) -> 0 | BI19: =BH19+(BH19*'1.Premissas Receitas'!$B$19) -> 0 | BJ19: =BI19+(BI19*'1.Premissas Receitas'!$B$19) -> 0 | BK19: =BJ19+(BJ19*'1.Premissas Receitas'!$B$19) -> 0 | ... BN19: =BM19+(BM19*'1.Premissas Receitas'!$B$19) -> 0 | BP19: =SUM(G19:R19) -> 0 | BQ19: =SUM(T19:AD19) -> 0 | BR19: =SUM(AE19:AP19) -> 0 | BS19: =SUM(AQ19:BB19) -> 0 | BT19: =SUM(BC19:BN19) -> 0
C20: ='1.Premissas Receitas'!A50 -> # de clientes Conteudo/ Paywall 3 | G20: ='1.Premissas Receitas'!G50 -> 0 | H20: =G20+(G20*'1.Premissas Receitas'!$B$19) -> 0 | I20: =H20+(H20*'1.Premissas Receitas'!$B$19) -> 0 | J20: =I20+(I20*'1.Premissas Receitas'!$B$19) -> 0 | K20: =J20+(J20*'1.Premissas Receitas'!$B$19) -> 0 | L20: =K20+(K20*'1.Premissas Receitas'!$B$19) -> 0 | M20: =L20+(L20*'1.Premissas Receitas'!$B$19) -> 0 | N20: =M20+(M20*'1.Premissas Receitas'!$B$19) -> 0 | O20: =N20+(N20*'1.Premissas Receitas'!$B$19) -> 0 | ... R20: =Q20+(Q20*'1.Premissas Receitas'!$B$19) -> 0 | S20: =R20+(R20*'1.Premissas Receitas'!$G$16) -> 0 | T20: =S20+(S20*'1.Premissas Receitas'!$B$19) -> 0 | U20: =T20+(T20*'1.Premissas Receitas'!$B$19) -> 0 | V20: =U20+(U20*'1.Premissas Receitas'!$B$19) -> 0 | W20: =V20+(V20*'1.Premissas Receitas'!$B$19) -> 0 | X20: =W20+(W20*'1.Premissas Receitas'!$B$19) -> 0 | Y20: =X20+(X20*'1.Premissas Receitas'!$B$19) -> 0 | Z20: =Y20+(Y20*'1.Premissas Receitas'!$B$19) -> 0 | AA20: =Z20+(Z20*'1.Premissas Receitas'!$B$19) -> 0 | ... AD20: =AC20+(AC20*'1.Premissas Receitas'!$B$19) -> 0 | AE20: =AD20+(AD20*'1.Premissas Receitas'!$G$17) -> 0 | AF20: =AE20+(AE20*'1.Premissas Receitas'!$B$19) -> 0 | AG20: =AF20+(AF20*'1.Premissas Receitas'!$B$19) -> 0 | AH20: =AG20+(AG20*'1.Premissas Receitas'!$B$19) -> 0 | AI20: =AH20+(AH20*'1.Premissas Receitas'!$B$19) -> 0 | AJ20: =AI20+(AI20*'1.Premissas Receitas'!$B$19) -> 0 | AK20: =AJ20+(AJ20*'1.Premissas Receitas'!$B$19) -> 0 | AL20: =AK20+(AK20*'1.Premissas Receitas'!$B$19) -> 0 | AM20: =AL20+(AL20*'1.Premissas Receitas'!$B$19) -> 0 | ... AP20: =AO20+(AO20*'1.Premissas Receitas'!$B$19) -> 0 | AQ20: =AP20+(AP20*'1.Premissas Receitas'!$G$18) -> 0 | AR20: =AQ20+(AQ20*'1.Premissas Receitas'!$B$19) -> 0 | AS20: =AR20+(AR20*'1.Premissas Receitas'!$B$19) -> 0 | AT20: =AS20+(AS20*'1.Premissas Receitas'!$B$19) -> 0 | AU20: =AT20+(AT20*'1.Premissas Receitas'!$B$19) -> 0 | AV20: =AU20+(AU20*'1.Premissas Receitas'!$B$19) -> 0 | AW20: =AV20+(AV20*'1.Premissas Receitas'!$B$19) -> 0 | AX20: =AW20+(AW20*'1.Premissas Receitas'!$B$19) -> 0 | AY20: =AX20+(AX20*'1.Premissas Receitas'!$B$19) -> 0 | ... BB20: =BA20+(BA20*'1.Premissas Receitas'!$B$19) -> 0 | BC20: =BB20+(BB20*'1.Premissas Receitas'!$G$19) -> 0 | BD20: =BC20+(BC20*'1.Premissas Receitas'!$B$19) -> 0 | BE20: =BD20+(BD20*'1.Premissas Receitas'!$B$19) -> 0 | BF20: =BE20+(BE20*'1.Premissas Receitas'!$B$19) -> 0 | BG20: =BF20+(BF20*'1.Premissas Receitas'!$B$19) -> 0 | BH20: =BG20+(BG20*'1.Premissas Receitas'!$B$19) -> 0 | BI20: =BH20+(BH20*'1.Premissas Receitas'!$B$19) -> 0 | BJ20: =BI20+(BI20*'1.Premissas Receitas'!$B$19) -> 0 | BK20: =BJ20+(BJ20*'1.Premissas Receitas'!$B$19) -> 0 | ... BN20: =BM20+(BM20*'1.Premissas Receitas'!$B$19) -> 0 | BP20: =SUM(G20:R20) -> 0 | BQ20: =SUM(T20:AD20) -> 0 | BR20: =SUM(AE20:AP20) -> 0 | BS20: =SUM(AQ20:BB20) -> 0 | BT20: =SUM(BC20:BN20) -> 0
C21: ='1.Premissas Receitas'!A56 -> # de clientes publicidade Produto/Serviço 1 | G21: ='1.Premissas Receitas'!G56 -> 0 | H21: =G21+(G21*'1.Premissas Receitas'!$B$19) -> 0 | I21: =H21+(H21*'1.Premissas Receitas'!$B$19) -> 0 | J21: =I21+(I21*'1.Premissas Receitas'!$B$19) -> 0 | K21: =J21+(J21*'1.Premissas Receitas'!$B$19) -> 0 | L21: =K21+(K21*'1.Premissas Receitas'!$B$19) -> 0 | M21: =L21+(L21*'1.Premissas Receitas'!$B$19) -> 0 | N21: =M21+(M21*'1.Premissas Receitas'!$B$19) -> 0 | O21: =N21+(N21*'1.Premissas Receitas'!$B$19) -> 0 | ... R21: =Q21+(Q21*'1.Premissas Receitas'!$B$19) -> 0 | S21: =R21+(R21*'1.Premissas Receitas'!$G$16) -> 0 | T21: =S21+(S21*'1.Premissas Receitas'!$B$19) -> 0 | U21: =T21+(T21*'1.Premissas Receitas'!$B$19) -> 0 | V21: =U21+(U21*'1.Premissas Receitas'!$B$19) -> 0 | W21: =V21+(V21*'1.Premissas Receitas'!$B$19) -> 0 | X21: =W21+(W21*'1.Premissas Receitas'!$B$19) -> 0 | Y21: =X21+(X21*'1.Premissas Receitas'!$B$19) -> 0 | Z21: =Y21+(Y21*'1.Premissas Receitas'!$B$19) -> 0 | AA21: =Z21+(Z21*'1.Premissas Receitas'!$B$19) -> 0 | ... AD21: =AC21+(AC21*'1.Premissas Receitas'!$B$19) -> 0 | AE21: =AD21+(AD21*'1.Premissas Receitas'!$G$17) -> 0 | AF21: =AE21+(AE21*'1.Premissas Receitas'!$B$19) -> 0 | AG21: =AF21+(AF21*'1.Premissas Receitas'!$B$19) -> 0 | AH21: =AG21+(AG21*'1.Premissas Receitas'!$B$19) -> 0 | AI21: =AH21+(AH21*'1.Premissas Receitas'!$B$19) -> 0 | AJ21: =AI21+(AI21*'1.Premissas Receitas'!$B$19) -> 0 | AK21: =AJ21+(AJ21*'1.Premissas Receitas'!$B$19) -> 0 | AL21: =AK21+(AK21*'1.Premissas Receitas'!$B$19) -> 0 | AM21: =AL21+(AL21*'1.Premissas Receitas'!$B$19) -> 0 | ... AP21: =AO21+(AO21*'1.Premissas Receitas'!$B$19) -> 0 | AQ21: =AP21+(AP21*'1.Premissas Receitas'!$G$18) -> 0 | AR21: =AQ21+(AQ21*'1.Premissas Receitas'!$B$19) -> 0 | AS21: =AR21+(AR21*'1.Premissas Receitas'!$B$19) -> 0 | AT21: =AS21+(AS21*'1.Premissas Receitas'!$B$19) -> 0 | AU21: =AT21+(AT21*'1.Premissas Receitas'!$B$19) -> 0 | AV21: =AU21+(AU21*'1.Premissas Receitas'!$B$19) -> 0 | AW21: =AV21+(AV21*'1.Premissas Receitas'!$B$19) -> 0 | AX21: =AW21+(AW21*'1.Premissas Receitas'!$B$19) -> 0 | AY21: =AX21+(AX21*'1.Premissas Receitas'!$B$19) -> 0 | ... BB21: =BA21+(BA21*'1.Premissas Receitas'!$B$19) -> 0 | BC21: =BB21+(BB21*'1.Premissas Receitas'!$G$19) -> 0 | BD21: =BC21+(BC21*'1.Premissas Receitas'!$B$19) -> 0 | BE21: =BD21+(BD21*'1.Premissas Receitas'!$B$19) -> 0 | BF21: =BE21+(BE21*'1.Premissas Receitas'!$B$19) -> 0 | BG21: =BF21+(BF21*'1.Premissas Receitas'!$B$19) -> 0 | BH21: =BG21+(BG21*'1.Premissas Receitas'!$B$19) -> 0 | BI21: =BH21+(BH21*'1.Premissas Receitas'!$B$19) -> 0 | BJ21: =BI21+(BI21*'1.Premissas Receitas'!$B$19) -> 0 | BK21: =BJ21+(BJ21*'1.Premissas Receitas'!$B$19) -> 0 | ... BN21: =BM21+(BM21*'1.Premissas Receitas'!$B$19) -> 0 | BP21: =SUM(G21:R21) -> 0 | BQ21: =SUM(T21:AD21) -> 0 | BR21: =SUM(AE21:AP21) -> 0 | BS21: =SUM(AQ21:BB21) -> 0 | BT21: =SUM(BC21:BN21) -> 0
C22: ='1.Premissas Receitas'!A57 -> # de clientes publicidade Produto/Serviço 2 | G22: ='1.Premissas Receitas'!G57 -> 0 | H22: =G22+(G22*'1.Premissas Receitas'!$B$19) -> 0 | I22: =H22+(H22*'1.Premissas Receitas'!$B$19) -> 0 | J22: =I22+(I22*'1.Premissas Receitas'!$B$19) -> 0 | K22: =J22+(J22*'1.Premissas Receitas'!$B$19) -> 0 | L22: =K22+(K22*'1.Premissas Receitas'!$B$19) -> 0 | M22: =L22+(L22*'1.Premissas Receitas'!$B$19) -> 0 | N22: =M22+(M22*'1.Premissas Receitas'!$B$19) -> 0 | O22: =N22+(N22*'1.Premissas Receitas'!$B$19) -> 0 | ... R22: =Q22+(Q22*'1.Premissas Receitas'!$B$19) -> 0 | S22: =R22+(R22*'1.Premissas Receitas'!$G$16) -> 0 | T22: =S22+(S22*'1.Premissas Receitas'!$B$19) -> 0 | U22: =T22+(T22*'1.Premissas Receitas'!$B$19) -> 0 | V22: =U22+(U22*'1.Premissas Receitas'!$B$19) -> 0 | W22: =V22+(V22*'1.Premissas Receitas'!$B$19) -> 0 | X22: =W22+(W22*'1.Premissas Receitas'!$B$19) -> 0 | Y22: =X22+(X22*'1.Premissas Receitas'!$B$19) -> 0 | Z22: =Y22+(Y22*'1.Premissas Receitas'!$B$19) -> 0 | AA22: =Z22+(Z22*'1.Premissas Receitas'!$B$19) -> 0 | ... AD22: =AC22+(AC22*'1.Premissas Receitas'!$B$19) -> 0 | AE22: =AD22+(AD22*'1.Premissas Receitas'!$G$17) -> 0 | AF22: =AE22+(AE22*'1.Premissas Receitas'!$B$19) -> 0 | AG22: =AF22+(AF22*'1.Premissas Receitas'!$B$19) -> 0 | AH22: =AG22+(AG22*'1.Premissas Receitas'!$B$19) -> 0 | AI22: =AH22+(AH22*'1.Premissas Receitas'!$B$19) -> 0 | AJ22: =AI22+(AI22*'1.Premissas Receitas'!$B$19) -> 0 | AK22: =AJ22+(AJ22*'1.Premissas Receitas'!$B$19) -> 0 | AL22: =AK22+(AK22*'1.Premissas Receitas'!$B$19) -> 0 | AM22: =AL22+(AL22*'1.Premissas Receitas'!$B$19) -> 0 | ... AP22: =AO22+(AO22*'1.Premissas Receitas'!$B$19) -> 0 | AQ22: =AP22+(AP22*'1.Premissas Receitas'!$G$18) -> 0 | AR22: =AQ22+(AQ22*'1.Premissas Receitas'!$B$19) -> 0 | AS22: =AR22+(AR22*'1.Premissas Receitas'!$B$19) -> 0 | AT22: =AS22+(AS22*'1.Premissas Receitas'!$B$19) -> 0 | AU22: =AT22+(AT22*'1.Premissas Receitas'!$B$19) -> 0 | AV22: =AU22+(AU22*'1.Premissas Receitas'!$B$19) -> 0 | AW22: =AV22+(AV22*'1.Premissas Receitas'!$B$19) -> 0 | AX22: =AW22+(AW22*'1.Premissas Receitas'!$B$19) -> 0 | AY22: =AX22+(AX22*'1.Premissas Receitas'!$B$19) -> 0 | ... BB22: =BA22+(BA22*'1.Premissas Receitas'!$B$19) -> 0 | BC22: =BB22+(BB22*'1.Premissas Receitas'!$G$19) -> 0 | BD22: =BC22+(BC22*'1.Premissas Receitas'!$B$19) -> 0 | BE22: =BD22+(BD22*'1.Premissas Receitas'!$B$19) -> 0 | BF22: =BE22+(BE22*'1.Premissas Receitas'!$B$19) -> 0 | BG22: =BF22+(BF22*'1.Premissas Receitas'!$B$19) -> 0 | BH22: =BG22+(BG22*'1.Premissas Receitas'!$B$19) -> 0 | BI22: =BH22+(BH22*'1.Premissas Receitas'!$B$19) -> 0 | BJ22: =BI22+(BI22*'1.Premissas Receitas'!$B$19) -> 0 | BK22: =BJ22+(BJ22*'1.Premissas Receitas'!$B$19) -> 0 | ... BN22: =BM22+(BM22*'1.Premissas Receitas'!$B$19) -> 0 | BP22: =SUM(G22:R22) -> 0 | BQ22: =SUM(T22:AD22) -> 0 | BR22: =SUM(AE22:AP22) -> 0 | BS22: =SUM(AQ22:BB22) -> 0 | BT22: =SUM(BC22:BN22) -> 0
C23: ='1.Premissas Receitas'!A58 -> # de clientes publicidade Produto/Serviço 3 | G23: ='1.Premissas Receitas'!G58 -> 0 | H23: =G23+(G23*'1.Premissas Receitas'!$B$19) -> 0 | I23: =H23+(H23*'1.Premissas Receitas'!$B$19) -> 0 | J23: =I23+(I23*'1.Premissas Receitas'!$B$19) -> 0 | K23: =J23+(J23*'1.Premissas Receitas'!$B$19) -> 0 | L23: =K23+(K23*'1.Premissas Receitas'!$B$19) -> 0 | M23: =L23+(L23*'1.Premissas Receitas'!$B$19) -> 0 | N23: =M23+(M23*'1.Premissas Receitas'!$B$19) -> 0 | O23: =N23+(N23*'1.Premissas Receitas'!$B$19) -> 0 | ... R23: =Q23+(Q23*'1.Premissas Receitas'!$B$19) -> 0 | S23: =R23+(R23*'1.Premissas Receitas'!$G$16) -> 0 | T23: =S23+(S23*'1.Premissas Receitas'!$B$19) -> 0 | U23: =T23+(T23*'1.Premissas Receitas'!$B$19) -> 0 | V23: =U23+(U23*'1.Premissas Receitas'!$B$19) -> 0 | W23: =V23+(V23*'1.Premissas Receitas'!$B$19) -> 0 | X23: =W23+(W23*'1.Premissas Receitas'!$B$19) -> 0 | Y23: =X23+(X23*'1.Premissas Receitas'!$B$19) -> 0 | Z23: =Y23+(Y23*'1.Premissas Receitas'!$B$19) -> 0 | AA23: =Z23+(Z23*'1.Premissas Receitas'!$B$19) -> 0 | ... AD23: =AC23+(AC23*'1.Premissas Receitas'!$B$19) -> 0 | AE23: =AD23+(AD23*'1.Premissas Receitas'!$G$17) -> 0 | AF23: =AE23+(AE23*'1.Premissas Receitas'!$B$19) -> 0 | AG23: =AF23+(AF23*'1.Premissas Receitas'!$B$19) -> 0 | AH23: =AG23+(AG23*'1.Premissas Receitas'!$B$19) -> 0 | AI23: =AH23+(AH23*'1.Premissas Receitas'!$B$19) -> 0 | AJ23: =AI23+(AI23*'1.Premissas Receitas'!$B$19) -> 0 | AK23: =AJ23+(AJ23*'1.Premissas Receitas'!$B$19) -> 0 | AL23: =AK23+(AK23*'1.Premissas Receitas'!$B$19) -> 0 | AM23: =AL23+(AL23*'1.Premissas Receitas'!$B$19) -> 0 | ... AP23: =AO23+(AO23*'1.Premissas Receitas'!$B$19) -> 0 | AQ23: =AP23+(AP23*'1.Premissas Receitas'!$G$18) -> 0 | AR23: =AQ23+(AQ23*'1.Premissas Receitas'!$B$19) -> 0 | AS23: =AR23+(AR23*'1.Premissas Receitas'!$B$19) -> 0 | AT23: =AS23+(AS23*'1.Premissas Receitas'!$B$19) -> 0 | AU23: =AT23+(AT23*'1.Premissas Receitas'!$B$19) -> 0 | AV23: =AU23+(AU23*'1.Premissas Receitas'!$B$19) -> 0 | AW23: =AV23+(AV23*'1.Premissas Receitas'!$B$19) -> 0 | AX23: =AW23+(AW23*'1.Premissas Receitas'!$B$19) -> 0 | AY23: =AX23+(AX23*'1.Premissas Receitas'!$B$19) -> 0 | ... BB23: =BA23+(BA23*'1.Premissas Receitas'!$B$19) -> 0 | BC23: =BB23+(BB23*'1.Premissas Receitas'!$G$19) -> 0 | BD23: =BC23+(BC23*'1.Premissas Receitas'!$B$19) -> 0 | BE23: =BD23+(BD23*'1.Premissas Receitas'!$B$19) -> 0 | BF23: =BE23+(BE23*'1.Premissas Receitas'!$B$19) -> 0 | BG23: =BF23+(BF23*'1.Premissas Receitas'!$B$19) -> 0 | BH23: =BG23+(BG23*'1.Premissas Receitas'!$B$19) -> 0 | BI23: =BH23+(BH23*'1.Premissas Receitas'!$B$19) -> 0 | BJ23: =BI23+(BI23*'1.Premissas Receitas'!$B$19) -> 0 | BK23: =BJ23+(BJ23*'1.Premissas Receitas'!$B$19) -> 0 | ... BN23: =BM23+(BM23*'1.Premissas Receitas'!$B$19) -> 0 | BP23: =SUM(G23:R23) -> 0 | BQ23: =SUM(T23:AD23) -> 0 | BR23: =SUM(AE23:AP23) -> 0 | BS23: =SUM(AQ23:BB23) -> 0 | BT23: =SUM(BC23:BN23) -> 0
C24: ='1.Premissas Receitas'!A63 -> # Pay-per-use Produto/Serviço 1 | G24: ='1.Premissas Receitas'!G63 -> 0 | H24: =G24+(G24*'1.Premissas Receitas'!$B$19) -> 0 | I24: =H24+(H24*'1.Premissas Receitas'!$B$19) -> 0 | J24: =I24+(I24*'1.Premissas Receitas'!$B$19) -> 0 | K24: =J24+(J24*'1.Premissas Receitas'!$B$19) -> 0 | L24: =K24+(K24*'1.Premissas Receitas'!$B$19) -> 0 | M24: =L24+(L24*'1.Premissas Receitas'!$B$19) -> 0 | N24: =M24+(M24*'1.Premissas Receitas'!$B$19) -> 0 | O24: =N24+(N24*'1.Premissas Receitas'!$B$19) -> 0 | ... R24: =Q24+(Q24*'1.Premissas Receitas'!$B$19) -> 0 | S24: =R24+(R24*'1.Premissas Receitas'!$G$16) -> 0 | T24: =S24+(S24*'1.Premissas Receitas'!$B$19) -> 0 | U24: =T24+(T24*'1.Premissas Receitas'!$B$19) -> 0 | V24: =U24+(U24*'1.Premissas Receitas'!$B$19) -> 0 | W24: =V24+(V24*'1.Premissas Receitas'!$B$19) -> 0 | X24: =W24+(W24*'1.Premissas Receitas'!$B$19) -> 0 | Y24: =X24+(X24*'1.Premissas Receitas'!$B$19) -> 0 | Z24: =Y24+(Y24*'1.Premissas Receitas'!$B$19) -> 0 | AA24: =Z24+(Z24*'1.Premissas Receitas'!$B$19) -> 0 | ... AD24: =AC24+(AC24*'1.Premissas Receitas'!$B$19) -> 0 | AE24: =AD24+(AD24*'1.Premissas Receitas'!$G$17) -> 0 | AF24: =AE24+(AE24*'1.Premissas Receitas'!$B$19) -> 0 | AG24: =AF24+(AF24*'1.Premissas Receitas'!$B$19) -> 0 | AH24: =AG24+(AG24*'1.Premissas Receitas'!$B$19) -> 0 | AI24: =AH24+(AH24*'1.Premissas Receitas'!$B$19) -> 0 | AJ24: =AI24+(AI24*'1.Premissas Receitas'!$B$19) -> 0 | AK24: =AJ24+(AJ24*'1.Premissas Receitas'!$B$19) -> 0 | AL24: =AK24+(AK24*'1.Premissas Receitas'!$B$19) -> 0 | AM24: =AL24+(AL24*'1.Premissas Receitas'!$B$19) -> 0 | ... AP24: =AO24+(AO24*'1.Premissas Receitas'!$B$19) -> 0 | AQ24: =AP24+(AP24*'1.Premissas Receitas'!$G$18) -> 0 | AR24: =AQ24+(AQ24*'1.Premissas Receitas'!$B$19) -> 0 | AS24: =AR24+(AR24*'1.Premissas Receitas'!$B$19) -> 0 | AT24: =AS24+(AS24*'1.Premissas Receitas'!$B$19) -> 0 | AU24: =AT24+(AT24*'1.Premissas Receitas'!$B$19) -> 0 | AV24: =AU24+(AU24*'1.Premissas Receitas'!$B$19) -> 0 | AW24: =AV24+(AV24*'1.Premissas Receitas'!$B$19) -> 0 | AX24: =AW24+(AW24*'1.Premissas Receitas'!$B$19) -> 0 | AY24: =AX24+(AX24*'1.Premissas Receitas'!$B$19) -> 0 | ... BB24: =BA24+(BA24*'1.Premissas Receitas'!$B$19) -> 0 | BC24: =BB24+(BB24*'1.Premissas Receitas'!$G$19) -> 0 | BD24: =BC24+(BC24*'1.Premissas Receitas'!$B$19) -> 0 | BE24: =BD24+(BD24*'1.Premissas Receitas'!$B$19) -> 0 | BF24: =BE24+(BE24*'1.Premissas Receitas'!$B$19) -> 0 | BG24: =BF24+(BF24*'1.Premissas Receitas'!$B$19) -> 0 | BH24: =BG24+(BG24*'1.Premissas Receitas'!$B$19) -> 0 | BI24: =BH24+(BH24*'1.Premissas Receitas'!$B$19) -> 0 | BJ24: =BI24+(BI24*'1.Premissas Receitas'!$B$19) -> 0 | BK24: =BJ24+(BJ24*'1.Premissas Receitas'!$B$19) -> 0 | ... BN24: =BM24+(BM24*'1.Premissas Receitas'!$B$19) -> 0 | BP24: =SUM(G24:R24) -> 0 | BQ24: =SUM(T24:AD24) -> 0 | BR24: =SUM(AE24:AP24) -> 0 | BS24: =SUM(AQ24:BB24) -> 0 | BT24: =SUM(BC24:BN24) -> 0
C25: ='1.Premissas Receitas'!A64 -> # Pay-per-use Produto/Serviço 2 | G25: ='1.Premissas Receitas'!G64 -> 0 | H25: =G25+(G25*'1.Premissas Receitas'!$B$19) -> 0 | I25: =H25+(H25*'1.Premissas Receitas'!$B$19) -> 0 | J25: =I25+(I25*'1.Premissas Receitas'!$B$19) -> 0 | K25: =J25+(J25*'1.Premissas Receitas'!$B$19) -> 0 | L25: =K25+(K25*'1.Premissas Receitas'!$B$19) -> 0 | M25: =L25+(L25*'1.Premissas Receitas'!$B$19) -> 0 | N25: =M25+(M25*'1.Premissas Receitas'!$B$19) -> 0 | O25: =N25+(N25*'1.Premissas Receitas'!$B$19) -> 0 | ... R25: =Q25+(Q25*'1.Premissas Receitas'!$B$19) -> 0 | S25: =R25+(R25*'1.Premissas Receitas'!$G$16) -> 0 | T25: =S25+(S25*'1.Premissas Receitas'!$B$19) -> 0 | U25: =T25+(T25*'1.Premissas Receitas'!$B$19) -> 0 | V25: =U25+(U25*'1.Premissas Receitas'!$B$19) -> 0 | W25: =V25+(V25*'1.Premissas Receitas'!$B$19) -> 0 | X25: =W25+(W25*'1.Premissas Receitas'!$B$19) -> 0 | Y25: =X25+(X25*'1.Premissas Receitas'!$B$19) -> 0 | Z25: =Y25+(Y25*'1.Premissas Receitas'!$B$19) -> 0 | AA25: =Z25+(Z25*'1.Premissas Receitas'!$B$19) -> 0 | ... AD25: =AC25+(AC25*'1.Premissas Receitas'!$B$19) -> 0 | AE25: =AD25+(AD25*'1.Premissas Receitas'!$G$17) -> 0 | AF25: =AE25+(AE25*'1.Premissas Receitas'!$B$19) -> 0 | AG25: =AF25+(AF25*'1.Premissas Receitas'!$B$19) -> 0 | AH25: =AG25+(AG25*'1.Premissas Receitas'!$B$19) -> 0 | AI25: =AH25+(AH25*'1.Premissas Receitas'!$B$19) -> 0 | AJ25: =AI25+(AI25*'1.Premissas Receitas'!$B$19) -> 0 | AK25: =AJ25+(AJ25*'1.Premissas Receitas'!$B$19) -> 0 | AL25: =AK25+(AK25*'1.Premissas Receitas'!$B$19) -> 0 | AM25: =AL25+(AL25*'1.Premissas Receitas'!$B$19) -> 0 | ... AP25: =AO25+(AO25*'1.Premissas Receitas'!$B$19) -> 0 | AQ25: =AP25+(AP25*'1.Premissas Receitas'!$G$18) -> 0 | AR25: =AQ25+(AQ25*'1.Premissas Receitas'!$B$19) -> 0 | AS25: =AR25+(AR25*'1.Premissas Receitas'!$B$19) -> 0 | AT25: =AS25+(AS25*'1.Premissas Receitas'!$B$19) -> 0 | AU25: =AT25+(AT25*'1.Premissas Receitas'!$B$19) -> 0 | AV25: =AU25+(AU25*'1.Premissas Receitas'!$B$19) -> 0 | AW25: =AV25+(AV25*'1.Premissas Receitas'!$B$19) -> 0 | AX25: =AW25+(AW25*'1.Premissas Receitas'!$B$19) -> 0 | AY25: =AX25+(AX25*'1.Premissas Receitas'!$B$19) -> 0 | ... BB25: =BA25+(BA25*'1.Premissas Receitas'!$B$19) -> 0 | BC25: =BB25+(BB25*'1.Premissas Receitas'!$G$19) -> 0 | BD25: =BC25+(BC25*'1.Premissas Receitas'!$B$19) -> 0 | BE25: =BD25+(BD25*'1.Premissas Receitas'!$B$19) -> 0 | BF25: =BE25+(BE25*'1.Premissas Receitas'!$B$19) -> 0 | BG25: =BF25+(BF25*'1.Premissas Receitas'!$B$19) -> 0 | BH25: =BG25+(BG25*'1.Premissas Receitas'!$B$19) -> 0 | BI25: =BH25+(BH25*'1.Premissas Receitas'!$B$19) -> 0 | BJ25: =BI25+(BI25*'1.Premissas Receitas'!$B$19) -> 0 | BK25: =BJ25+(BJ25*'1.Premissas Receitas'!$B$19) -> 0 | ... BN25: =BM25+(BM25*'1.Premissas Receitas'!$B$19) -> 0 | BP25: =SUM(G25:R25) -> 0 | BQ25: =SUM(T25:AD25) -> 0 | BR25: =SUM(AE25:AP25) -> 0 | BS25: =SUM(AQ25:BB25) -> 0 | BT25: =SUM(BC25:BN25) -> 0
C26: ='1.Premissas Receitas'!A65 -> # Pay-per-use Produto/Serviço 3 | G26: ='1.Premissas Receitas'!G65 -> 0 | H26: =G26+(G26*'1.Premissas Receitas'!$B$19) -> 0 | I26: =H26+(H26*'1.Premissas Receitas'!$B$19) -> 0 | J26: =I26+(I26*'1.Premissas Receitas'!$B$19) -> 0 | K26: =J26+(J26*'1.Premissas Receitas'!$B$19) -> 0 | L26: =K26+(K26*'1.Premissas Receitas'!$B$19) -> 0 | M26: =L26+(L26*'1.Premissas Receitas'!$B$19) -> 0 | N26: =M26+(M26*'1.Premissas Receitas'!$B$19) -> 0 | O26: =N26+(N26*'1.Premissas Receitas'!$B$19) -> 0 | ... R26: =Q26+(Q26*'1.Premissas Receitas'!$B$19) -> 0 | S26: =R26+(R26*'1.Premissas Receitas'!$G$16) -> 0 | T26: =S26+(S26*'1.Premissas Receitas'!$B$19) -> 0 | U26: =T26+(T26*'1.Premissas Receitas'!$B$19) -> 0 | V26: =U26+(U26*'1.Premissas Receitas'!$B$19) -> 0 | W26: =V26+(V26*'1.Premissas Receitas'!$B$19) -> 0 | X26: =W26+(W26*'1.Premissas Receitas'!$B$19) -> 0 | Y26: =X26+(X26*'1.Premissas Receitas'!$B$19) -> 0 | Z26: =Y26+(Y26*'1.Premissas Receitas'!$B$19) -> 0 | AA26: =Z26+(Z26*'1.Premissas Receitas'!$B$19) -> 0 | ... AD26: =AC26+(AC26*'1.Premissas Receitas'!$B$19) -> 0 | AE26: =AD26+(AD26*'1.Premissas Receitas'!$G$17) -> 0 | AF26: =AE26+(AE26*'1.Premissas Receitas'!$B$19) -> 0 | AG26: =AF26+(AF26*'1.Premissas Receitas'!$B$19) -> 0 | AH26: =AG26+(AG26*'1.Premissas Receitas'!$B$19) -> 0 | AI26: =AH26+(AH26*'1.Premissas Receitas'!$B$19) -> 0 | AJ26: =AI26+(AI26*'1.Premissas Receitas'!$B$19) -> 0 | AK26: =AJ26+(AJ26*'1.Premissas Receitas'!$B$19) -> 0 | AL26: =AK26+(AK26*'1.Premissas Receitas'!$B$19) -> 0 | AM26: =AL26+(AL26*'1.Premissas Receitas'!$B$19) -> 0 | ... AP26: =AO26+(AO26*'1.Premissas Receitas'!$B$19) -> 0 | AQ26: =AP26+(AP26*'1.Premissas Receitas'!$G$18) -> 0 | AR26: =AQ26+(AQ26*'1.Premissas Receitas'!$B$19) -> 0 | AS26: =AR26+(AR26*'1.Premissas Receitas'!$B$19) -> 0 | AT26: =AS26+(AS26*'1.Premissas Receitas'!$B$19) -> 0 | AU26: =AT26+(AT26*'1.Premissas Receitas'!$B$19) -> 0 | AV26: =AU26+(AU26*'1.Premissas Receitas'!$B$19) -> 0 | AW26: =AV26+(AV26*'1.Premissas Receitas'!$B$19) -> 0 | AX26: =AW26+(AW26*'1.Premissas Receitas'!$B$19) -> 0 | AY26: =AX26+(AX26*'1.Premissas Receitas'!$B$19) -> 0 | ... BB26: =BA26+(BA26*'1.Premissas Receitas'!$B$19) -> 0 | BC26: =BB26+(BB26*'1.Premissas Receitas'!$G$19) -> 0 | BD26: =BC26+(BC26*'1.Premissas Receitas'!$B$19) -> 0 | BE26: =BD26+(BD26*'1.Premissas Receitas'!$B$19) -> 0 | BF26: =BE26+(BE26*'1.Premissas Receitas'!$B$19) -> 0 | BG26: =BF26+(BF26*'1.Premissas Receitas'!$B$19) -> 0 | BH26: =BG26+(BG26*'1.Premissas Receitas'!$B$19) -> 0 | BI26: =BH26+(BH26*'1.Premissas Receitas'!$B$19) -> 0 | BJ26: =BI26+(BI26*'1.Premissas Receitas'!$B$19) -> 0 | BK26: =BJ26+(BJ26*'1.Premissas Receitas'!$B$19) -> 0 | ... BN26: =BM26+(BM26*'1.Premissas Receitas'!$B$19) -> 0 | BP26: =SUM(G26:R26) -> 0 | BQ26: =SUM(T26:AD26) -> 0 | BR26: =SUM(AE26:AP26) -> 0 | BS26: =SUM(AQ26:BB26) -> 0 | BT26: =SUM(BC26:BN26) -> 0
B27: Total de novas vendas | G27: =SUM(G9:G26) -> 4.6666667 | H27: =SUM(H9:H26) -> 4.8066667 | I27: =SUM(I9:I26) -> 4.9508667 | J27: =SUM(J9:J26) -> 5.0993927 | K27: =SUM(K9:K26) -> 5.2523744 | L27: =SUM(L9:L26) -> 5.4099457 | M27: =SUM(M9:M26) -> 5.5722441 | N27: =SUM(N9:N26) -> 5.7394114 | ... BN27: =SUM(BN9:BN26) -> 59.566847 | BP27: =SUM(BP9:BP26) -> 66.229471 | BQ27: =SUM(BQ9:BQ26) -> 119.30425 | BR27: =SUM(BR9:BR26) -> 230.96258 | BS27: =SUM(BS9:BS26) -> 383.64747 | BT27: =SUM(BT9:BT26) -> 610.71649
B29: Churn - Cancelamentos
C30: =C9 -> # de clientes Assinatura Fremium | H30: =G9*'1.Premissas Receitas'!$B$30 -> 0.03 | I30: =H9*'1.Premissas Receitas'!$B$30 -> 0.0309 | J30: =I9*'1.Premissas Receitas'!$B$30 -> 0.031827 | K30: =J9*'1.Premissas Receitas'!$B$30 -> 0.03278181 | L30: =K9*'1.Premissas Receitas'!$B$30 -> 0.033765264 | M30: =L9*'1.Premissas Receitas'!$B$30 -> 0.034778222 | N30: =M9*'1.Premissas Receitas'!$B$30 -> 0.035821569 | O30: =N9*'1.Premissas Receitas'!$B$30 -> 0.036896216 | ... BM30: =BL9*'1.Premissas Receitas'!$B$30 -> 0.360948 | BP30: =SUM(G30:R30) -> 0.38423387 | BQ30: =SUM(T30:AD30) -> 0.74461735 | BR30: =SUM(AE30:AP30) -> 1.4204183 | BS30: =SUM(AQ30:BB30) -> 2.3705691 | BT30: =SUM(BC30:BN30) -> 3.411882
C31: =C10 -> # de clientes Assinatura 1 | H31: =G10*'1.Premissas Receitas'!$B$30 -> 0.021 | I31: =H10*'1.Premissas Receitas'!$B$30 -> 0.02163 | J31: =I10*'1.Premissas Receitas'!$B$30 -> 0.0222789 | K31: =J10*'1.Premissas Receitas'!$B$30 -> 0.022947267 | L31: =K10*'1.Premissas Receitas'!$B$30 -> 0.023635685 | M31: =L10*'1.Premissas Receitas'!$B$30 -> 0.024344756 | N31: =M10*'1.Premissas Receitas'!$B$30 -> 0.025075098 | O31: =N10*'1.Premissas Receitas'!$B$30 -> 0.025827351 | ... BM31: =BL10*'1.Premissas Receitas'!$B$30 -> 0.2526636 | BP31: =SUM(G31:R31) -> 0.26896371 | BQ31: =SUM(T31:AD31) -> 0.52123215 | BR31: =SUM(AE31:AP31) -> 0.99429279 | BS31: =SUM(AQ31:BB31) -> 1.6593984 | BT31: =SUM(BC31:BN31) -> 2.3883174
C32: =C11 -> # de clientes Assinatura 2 | H32: =G11*'1.Premissas Receitas'!$B$30 -> 0.009 | I32: =H11*'1.Premissas Receitas'!$B$30 -> 0.00927 | J32: =I11*'1.Premissas Receitas'!$B$30 -> 0.0095481 | K32: =J11*'1.Premissas Receitas'!$B$30 -> 0.009834543 | L32: =K11*'1.Premissas Receitas'!$B$30 -> 0.010129579 | M32: =L11*'1.Premissas Receitas'!$B$30 -> 0.010433467 | N32: =M11*'1.Premissas Receitas'!$B$30 -> 0.010746471 | O32: =N11*'1.Premissas Receitas'!$B$30 -> 0.011068865 | ... BM32: =BL11*'1.Premissas Receitas'!$B$30 -> 0.1082844 | BP32: =SUM(G32:R32) -> 0.11527016 | BQ32: =SUM(T32:AD32) -> 0.22338521 | BR32: =SUM(AE32:AP32) -> 0.42612548 | BS32: =SUM(AQ32:BB32) -> 0.71117073 | BT32: =SUM(BC32:BN32) -> 1.0235646
C33: =C24 -> # Pay-per-use Produto/Serviço 1 | H33: =G24*'1.Premissas Receitas'!$B$68 -> 0 | I33: =H24*'1.Premissas Receitas'!$B$68 -> 0 | J33: =I24*'1.Premissas Receitas'!$B$68 -> 0 | K33: =J24*'1.Premissas Receitas'!$B$68 -> 0 | L33: =K24*'1.Premissas Receitas'!$B$68 -> 0 | M33: =L24*'1.Premissas Receitas'!$B$68 -> 0 | N33: =M24*'1.Premissas Receitas'!$B$68 -> 0 | O33: =N24*'1.Premissas Receitas'!$B$68 -> 0 | ... BM33: =BL24*'1.Premissas Receitas'!$B$68 -> 0 | BP33: =SUM(G33:R33) -> 0 | BQ33: =SUM(T33:AD33) -> 0 | BR33: =SUM(AE33:AP33) -> 0 | BS33: =SUM(AQ33:BB33) -> 0 | BT33: =SUM(BC33:BN33) -> 0
C34: =C25 -> # Pay-per-use Produto/Serviço 2 | H34: =G25*'1.Premissas Receitas'!$B$68 -> 0 | I34: =H25*'1.Premissas Receitas'!$B$68 -> 0 | J34: =I25*'1.Premissas Receitas'!$B$68 -> 0 | K34: =J25*'1.Premissas Receitas'!$B$68 -> 0 | L34: =K25*'1.Premissas Receitas'!$B$68 -> 0 | M34: =L25*'1.Premissas Receitas'!$B$68 -> 0 | N34: =M25*'1.Premissas Receitas'!$B$68 -> 0 | O34: =N25*'1.Premissas Receitas'!$B$68 -> 0 | ... BM34: =BL25*'1.Premissas Receitas'!$B$68 -> 0 | BP34: =SUM(G34:R34) -> 0 | BQ34: =SUM(T34:AD34) -> 0 | BR34: =SUM(AE34:AP34) -> 0 | BS34: =SUM(AQ34:BB34) -> 0 | BT34: =SUM(BC34:BN34) -> 0
C35: =C26 -> # Pay-per-use Produto/Serviço 3 | H35: =G26*'1.Premissas Receitas'!$B$68 -> 0 | I35: =H26*'1.Premissas Receitas'!$B$68 -> 0 | J35: =I26*'1.Premissas Receitas'!$B$68 -> 0 | K35: =J26*'1.Premissas Receitas'!$B$68 -> 0 | L35: =K26*'1.Premissas Receitas'!$B$68 -> 0 | M35: =L26*'1.Premissas Receitas'!$B$68 -> 0 | N35: =M26*'1.Premissas Receitas'!$B$68 -> 0 | O35: =N26*'1.Premissas Receitas'!$B$68 -> 0 | ... BM35: =BL26*'1.Premissas Receitas'!$B$68 -> 0 | BP35: =SUM(G35:R35) -> 0 | BQ35: =SUM(T35:AD35) -> 0 | BR35: =SUM(AE35:AP35) -> 0 | BS35: =SUM(AQ35:BB35) -> 0 | BT35: =SUM(BC35:BN35) -> 0
B36: Cancelamentos totais | G36: =SUM(G30:G35) -> 0 | H36: =SUM(H30:H35) -> 0.06 | I36: =SUM(I30:I35) -> 0.0618 | J36: =SUM(J30:J35) -> 0.063654 | K36: =SUM(K30:K35) -> 0.06556362 | L36: =SUM(L30:L35) -> 0.067530529 | M36: =SUM(M30:M35) -> 0.069556444 | N36: =SUM(N30:N35) -> 0.071643138 | ... BN36: =SUM(BN30:BN35) -> 0 | BP36: =SUM(BP30:BP35) -> 0.76846774 | BQ36: =SUM(BQ30:BQ35) -> 1.4892347 | BR36: =SUM(BR30:BR35) -> 2.8408365 | BS36: =SUM(BS30:BS35) -> 4.7411382 | BT36: =SUM(BT30:BT35) -> 6.823764
A40: Receita de Vendas
B42: Receita do Início do Período | G42: =+F61 -> 0 | H42: =+G61 -> 31437.667 | I42: =+H61 -> 63818.463 | J42: =+I61 -> 97170.684 | K42: =+J61 -> 131523.47 | L42: =+K61 -> 166906.84 | M42: =+L61 -> 203351.71 | N42: =+M61 -> 240889.93 | ... BN42: =+BM61 -> 9164105 | BP42: =+BO61 -> 0 | BQ42: =+BP61 -> 446164.29 | BR42: =+BQ61 -> 1249874.4 | BS42: =+BR61 -> 2805786.8 | BT42: =+BS61 -> 5390282.8
C43: =C9 -> # de clientes Assinatura Fremium | F43: ='1.Premissas Receitas'!C25 -> 1 | G43: =$F$43*G9 -> 1 | H43: =$F$43*H9 -> 1.03 | I43: =$F$43*I9 -> 1.0609 | J43: =$F$43*J9 -> 1.092727 | K43: =$F$43*K9 -> 1.1255088 | L43: =$F$43*L9 -> 1.1592741 | M43: =$F$43*M9 -> 1.1940523 | N43: =$F$43*N9 -> 1.2298739 | ... BN43: =$F$43*BN9 -> 12.764324 | BP43: =SUM(G43:R43) -> 14.19203 | BQ43: =SUM(T43:AD43) -> 25.565196 | BR43: =SUM(AE43:AP43) -> 49.491981 | BS43: =SUM(AQ43:BB43) -> 82.210172 | BT43: =SUM(BC43:BN43) -> 130.86782
C44: =C10 -> # de clientes Assinatura 1 | F44: ='1.Premissas Receitas'!C26 -> 500 | G44: =$F$44*G10 -> 350 | H44: =$F$44*H10 -> 360.5 | I44: =$F$44*I10 -> 371.315 | J44: =$F$44*J10 -> 382.45445 | K44: =$F$44*K10 -> 393.92808 | L44: =$F$44*L10 -> 405.74593 | M44: =$F$44*M10 -> 417.9183 | N44: =$F$44*N10 -> 430.45585 | ... BN44: =$F$44*BN10 -> 4467.5135 | BP44: =SUM(G44:R44) -> 4967.2103 | BQ44: =SUM(T44:AD44) -> 8947.8185 | BR44: =SUM(AE44:AP44) -> 17322.193 | BS44: =SUM(AQ44:BB44) -> 28773.56 | BT44: =SUM(BC44:BN44) -> 45803.737
C45: =C11 -> # de clientes Assinatura 2 | F45: ='1.Premissas Receitas'!C27 -> 1400 | G45: =$F$45*G11 -> 420 | H45: =$F$45*H11 -> 432.6 | I45: =$F$45*I11 -> 445.578 | J45: =$F$45*J11 -> 458.94534 | K45: =$F$45*K11 -> 472.7137 | L45: =$F$45*L11 -> 486.89511 | M45: =$F$45*M11 -> 501.50196 | N45: =$F$45*N11 -> 516.54702 | ... BN45: =$F$45*BN11 -> 5361.0162 | BP45: =SUM(G45:R45) -> 5960.6524 | BQ45: =SUM(T45:AD45) -> 10737.382 | BR45: =SUM(AE45:AP45) -> 20786.632 | BS45: =SUM(AQ45:BB45) -> 34528.272 | BT45: =SUM(BC45:BN45) -> 54964.484
C46: =C12 -> # de clientes marketplace % Comissão 1 | F46: ='1.Premissas Receitas'!C33 -> 1 | G46: =$F$46*G12 -> 0 | H46: =$F$46*H12 -> 0 | I46: =$F$46*I12 -> 0 | J46: =$F$46*J12 -> 0 | K46: =$F$46*K12 -> 0 | L46: =$F$46*L12 -> 0 | M46: =$F$46*M12 -> 0 | N46: =$F$46*N12 -> 0 | ... BN46: =$F$46*BN12 -> 0 | BP46: =SUM(G46:R46) -> 0 | BQ46: =SUM(T46:AD46) -> 0 | BR46: =SUM(AE46:AP46) -> 0 | BS46: =SUM(AQ46:BB46) -> 0 | BT46: =SUM(BC46:BN46) -> 0
C47: =C13 -> # de clientes marketplace % Comissão 2 | F47: ='1.Premissas Receitas'!C34 -> 1 | G47: =$F$47*G13 -> 0 | H47: =$F$47*H13 -> 0 | I47: =$F$47*I13 -> 0 | J47: =$F$47*J13 -> 0 | K47: =$F$47*K13 -> 0 | L47: =$F$47*L13 -> 0 | M47: =$F$47*M13 -> 0 | N47: =$F$47*N13 -> 0 | ... BN47: =$F$47*BN13 -> 0 | BP47: =SUM(G47:R47) -> 0 | BQ47: =SUM(T47:AD47) -> 0 | BR47: =SUM(AE47:AP47) -> 0 | BS47: =SUM(AQ47:BB47) -> 0 | BT47: =SUM(BC47:BN47) -> 0
C48: =C14 -> # de clientes marketplace % Comissão 3 | F48: ='1.Premissas Receitas'!C35 -> 1 | G48: =$F$48*G14 -> 0 | H48: =$F$48*H14 -> 0 | I48: =$F$48*I14 -> 0 | J48: =$F$48*J14 -> 0 | K48: =$F$48*K14 -> 0 | L48: =$F$48*L14 -> 0 | M48: =$F$48*M14 -> 0 | N48: =$F$48*N14 -> 0 | ... BN48: =$F$48*BN14 -> 0 | BP48: =SUM(G48:R48) -> 0 | BQ48: =SUM(T48:AD48) -> 0 | BR48: =SUM(AE48:AP48) -> 0 | BS48: =SUM(AQ48:BB48) -> 0 | BT48: =SUM(BC48:BN48) -> 0
C49: =C15 -> # de clientes B2B Setup | F49: ='1.Premissas Receitas'!C40 -> 15000 | G49: =$F$49*G15 -> 20000 | H49: =$F$49*H15 -> 20600 | I49: =$F$49*I15 -> 21218 | J49: =$F$49*J15 -> 21854.54 | K49: =$F$49*K15 -> 22510.176 | L49: =$F$49*L15 -> 23185.481 | M49: =$F$49*M15 -> 23881.046 | N49: =$F$49*N15 -> 24597.477 | ... BN49: =$F$49*BN15 -> 255286.49 | BP49: =SUM(G49:R49) -> 283840.59 | BQ49: =SUM(T49:AD49) -> 511303.92 | BR49: =SUM(AE49:AP49) -> 989839.62 | BS49: =SUM(AQ49:BB49) -> 1644203.4 | BT49: =SUM(BC49:BN49) -> 2617356.4
C50: =C16 -> # de clientes B2B Mensalidade | F50: ='1.Premissas Receitas'!C41 -> 8000 | G50: =$F$50*G16 -> 10666.667 | H50: =$F$50*H16 -> 10986.667 | I50: =$F$50*I16 -> 11316.267 | J50: =$F$50*J16 -> 11655.755 | K50: =$F$50*K16 -> 12005.427 | L50: =$F$50*L16 -> 12365.59 | M50: =$F$50*M16 -> 12736.558 | N50: =$F$50*N16 -> 13118.655 | ... BN50: =$F$50*BN16 -> 136152.79 | BP50: =SUM(G50:R50) -> 151381.65 | BQ50: =SUM(T50:AD50) -> 272695.42 | BR50: =SUM(AE50:AP50) -> 527914.47 | BS50: =SUM(AQ50:BB50) -> 876908.5 | BT50: =SUM(BC50:BN50) -> 1395923.4
C51: =C17 -> # de clientes B2B Manutenção | F51: ='1.Premissas Receitas'!C42 -> 1 | G51: =$F$51*G17 -> 0 | H51: =$F$51*H17 -> 0 | I51: =$F$51*I17 -> 0 | J51: =$F$51*J17 -> 0 | K51: =$F$51*K17 -> 0 | L51: =$F$51*L17 -> 0 | M51: =$F$51*M17 -> 0 | N51: =$F$51*N17 -> 0 | ... BN51: =$F$51*BN17 -> 0 | BP51: =SUM(G51:R51) -> 0 | BQ51: =SUM(T51:AD51) -> 0 | BR51: =SUM(AE51:AP51) -> 0 | BS51: =SUM(AQ51:BB51) -> 0 | BT51: =SUM(BC51:BN51) -> 0
C52: =C18 -> # de clientes Conteudo/ Paywall 1 | F52: ='1.Premissas Receitas'!C48 -> 1 | G52: =$F$52*G18 -> 0 | H52: =$F$52*H18 -> 0 | I52: =$F$52*I18 -> 0 | J52: =$F$52*J18 -> 0 | K52: =$F$52*K18 -> 0 | L52: =$F$52*L18 -> 0 | M52: =$F$52*M18 -> 0 | N52: =$F$52*N18 -> 0 | ... BN52: =$F$52*BN18 -> 0 | BP52: =SUM(G52:R52) -> 0 | BQ52: =SUM(T52:AD52) -> 0 | BR52: =SUM(AE52:AP52) -> 0 | BS52: =SUM(AQ52:BB52) -> 0 | BT52: =SUM(BC52:BN52) -> 0
C53: =C19 -> # de clientes Conteudo/ Paywall 2 | F53: ='1.Premissas Receitas'!C49 -> 1 | G53: =$F$53*G19 -> 0 | H53: =$F$53*H19 -> 0 | I53: =$F$53*I19 -> 0 | J53: =$F$53*J19 -> 0 | K53: =$F$53*K19 -> 0 | L53: =$F$53*L19 -> 0 | M53: =$F$53*M19 -> 0 | N53: =$F$53*N19 -> 0 | ... BN53: =$F$53*BN19 -> 0 | BP53: =SUM(G53:R53) -> 0 | BQ53: =SUM(T53:AD53) -> 0 | BR53: =SUM(AE53:AP53) -> 0 | BS53: =SUM(AQ53:BB53) -> 0 | BT53: =SUM(BC53:BN53) -> 0
C54: =C20 -> # de clientes Conteudo/ Paywall 3 | F54: ='1.Premissas Receitas'!C50 -> 1 | G54: =$F$52*G20 -> 0 | H54: =$F$51*H21 -> 0 | I54: =$F$52*I20 -> 0 | J54: =$F$52*J20 -> 0 | K54: =$F$52*K20 -> 0 | L54: =$F$52*L20 -> 0 | M54: =$F$52*M20 -> 0 | N54: =$F$52*N20 -> 0 | O54: =$F$52*O20 -> 0 | P54: =$F$52*P20 -> 0 | ... BN54: =$F$52*BN20 -> 0 | BP54: =SUM(G54:R54) -> 0 | BQ54: =SUM(T54:AD54) -> 0 | BR54: =SUM(AE54:AP54) -> 0 | BS54: =SUM(AQ54:BB54) -> 0 | BT54: =SUM(BC54:BN54) -> 0
C55: =C21 -> # de clientes publicidade Produto/Serviço 1 | F55: ='1.Premissas Receitas'!C56 -> 1 | G55: =$F$52*G21 -> 0 | H55: =$F$51*H22 -> 0 | I55: =$F$52*I21 -> 0 | J55: =$F$52*J21 -> 0 | K55: =$F$52*K21 -> 0 | L55: =$F$52*L21 -> 0 | M55: =$F$52*M21 -> 0 | N55: =$F$52*N21 -> 0 | O55: =$F$52*O21 -> 0 | P55: =$F$52*P21 -> 0 | ... BN55: =$F$52*BN21 -> 0 | BP55: =SUM(G55:R55) -> 0 | BQ55: =SUM(T55:AD55) -> 0 | BR55: =SUM(AE55:AP55) -> 0 | BS55: =SUM(AQ55:BB55) -> 0 | BT55: =SUM(BC55:BN55) -> 0
C56: =C22 -> # de clientes publicidade Produto/Serviço 2 | F56: ='1.Premissas Receitas'!C57 -> 1 | G56: =$F$52*G22 -> 0 | H56: =$F$51*H23 -> 0 | I56: =$F$52*I22 -> 0 | J56: =$F$52*J22 -> 0 | K56: =$F$52*K22 -> 0 | L56: =$F$52*L22 -> 0 | M56: =$F$52*M22 -> 0 | N56: =$F$52*N22 -> 0 | O56: =$F$52*O22 -> 0 | P56: =$F$52*P22 -> 0 | ... BN56: =$F$52*BN22 -> 0 | BP56: =SUM(G56:R56) -> 0 | BQ56: =SUM(T56:AD56) -> 0 | BR56: =SUM(AE56:AP56) -> 0 | BS56: =SUM(AQ56:BB56) -> 0 | BT56: =SUM(BC56:BN56) -> 0
C57: =C23 -> # de clientes publicidade Produto/Serviço 3 | F57: ='1.Premissas Receitas'!C58 -> 1 | G57: =$F$52*G23 -> 0 | H57: =$F$51*H24 -> 0 | I57: =$F$52*I23 -> 0 | J57: =$F$52*J23 -> 0 | K57: =$F$52*K23 -> 0 | L57: =$F$52*L23 -> 0 | M57: =$F$52*M23 -> 0 | N57: =$F$52*N23 -> 0 | O57: =$F$52*O23 -> 0 | P57: =$F$52*P23 -> 0 | ... BN57: =$F$52*BN23 -> 0 | BP57: =SUM(G57:R57) -> 0 | BQ57: =SUM(T57:AD57) -> 0 | BR57: =SUM(AE57:AP57) -> 0 | BS57: =SUM(AQ57:BB57) -> 0 | BT57: =SUM(BC57:BN57) -> 0
C58: =C24 -> # Pay-per-use Produto/Serviço 1 | F58: ='1.Premissas Receitas'!C63 -> 1 | G58: =$F$52*G24 -> 0 | H58: =$F$58*H21 -> 0 | I58: =$F$52*I24 -> 0 | J58: =$F$52*J24 -> 0 | K58: =$F$52*K24 -> 0 | L58: =$F$52*L24 -> 0 | M58: =$F$52*M24 -> 0 | N58: =$F$52*N24 -> 0 | O58: =$F$52*O24 -> 0 | P58: =$F$52*P24 -> 0 | ... BN58: =$F$52*BN24 -> 0 | BP58: =SUM(G58:R58) -> 0 | BQ58: =SUM(T58:AD58) -> 0 | BR58: =SUM(AE58:AP58) -> 0 | BS58: =SUM(AQ58:BB58) -> 0 | BT58: =SUM(BC58:BN58) -> 0
C59: =C25 -> # Pay-per-use Produto/Serviço 2 | F59: ='1.Premissas Receitas'!C64 -> 1 | G59: =$F$52*G25 -> 0 | H59: =$F$59*H22 -> 0 | I59: =$F$52*I25 -> 0 | J59: =$F$52*J25 -> 0 | K59: =$F$52*K25 -> 0 | L59: =$F$52*L25 -> 0 | M59: =$F$52*M25 -> 0 | N59: =$F$52*N25 -> 0 | O59: =$F$52*O25 -> 0 | P59: =$F$52*P25 -> 0 | ... BN59: =$F$52*BN25 -> 0 | BP59: =SUM(G59:R59) -> 0 | BQ59: =SUM(T59:AD59) -> 0 | BR59: =SUM(AE59:AP59) -> 0 | BS59: =SUM(AQ59:BB59) -> 0 | BT59: =SUM(BC59:BN59) -> 0
C60: =C26 -> # Pay-per-use Produto/Serviço 3 | F60: ='1.Premissas Receitas'!C65 -> 1 | G60: =$F$52*G26 -> 0 | H60: =$F$60*H23 -> 0 | I60: =$F$52*I26 -> 0 | J60: =$F$52*J26 -> 0 | K60: =$F$52*K26 -> 0 | L60: =$F$52*L26 -> 0 | M60: =$F$52*M26 -> 0 | N60: =$F$52*N26 -> 0 | O60: =$F$52*O26 -> 0 | P60: =$F$52*P26 -> 0 | ... BN60: =$F$52*BN26 -> 0 | BP60: =SUM(G60:R60) -> 0 | BQ60: =SUM(T60:AD60) -> 0 | BR60: =SUM(AE60:AP60) -> 0 | BS60: =SUM(AQ60:BB60) -> 0 | BT60: =SUM(BC60:BN60) -> 0
B61: Receita Anual do Final do Período | G61: =SUM(G42:G60) -> 31437.667 | H61: =SUM(H42:H60) -> 63818.463 | I61: =SUM(I42:I60) -> 97170.684 | J61: =SUM(J42:J60) -> 131523.47 | K61: =SUM(K42:K60) -> 166906.84 | L61: =SUM(L42:L60) -> 203351.71 | M61: =SUM(M42:M60) -> 240889.93 | N61: =SUM(N42:N60) -> 279554.3 | ... BN61: =SUM(BN42:BN60) -> 9565385.6 | BP61: =SUM(BP42:BP60) -> 446164.29 | BQ61: =SUM(BQ42:BQ60) -> 1249874.4 | BR61: =SUM(BR42:BR60) -> 2805786.8 | BS61: =SUM(BS42:BS60) -> 5390282.8 | BT61: =SUM(BT42:BT60) -> 9504461.7
B62: % De crescimento mensal | G62: =+IFERROR(G61/F61-1,"-") -> - | H62: =+IFERROR(H61/G61-1,"-") -> 1.03 | I62: =+IFERROR(I61/H61-1,"-") -> 0.52261084 | J62: =+IFERROR(J61/I61-1,"-") -> 0.35353036 | K62: =+IFERROR(K61/J61-1,"-") -> 0.26902705 | L62: =+IFERROR(L61/K61-1,"-") -> 0.21835457 | M62: =+IFERROR(M61/L61-1,"-") -> 0.1845975 | N62: =+IFERROR(N61/M61-1,"-") -> 0.16050635 | ... BN62: =+IFERROR(BN61/BM61-1,"-") -> 0.043788299
B64: (-) Churn do Início do Período | G64: =+-G36 -> 0 | H64: =+-H36 -> -0.06 | I64: =+-I36 -> -0.0618 | J64: =+-J36 -> -0.063654 | K64: =+-K36 -> -0.06556362 | L64: =+-L36 -> -0.067530529 | M64: =+-M36 -> -0.069556444 | N64: =+-N36 -> -0.071643138 | ... BN64: =+-BN36 -> 0
C65: =C30 -> # de clientes Assinatura Fremium | F65: ='1.Premissas Receitas'!C25 -> 1 | G65: =-G30*$F$65 -> 0 | H65: =-H30*$F$65 -> -0.03 | I65: =-I30*$F$65 -> -0.0309 | J65: =-J30*$F$65 -> -0.031827 | K65: =-K30*$F$65 -> -0.03278181 | L65: =-L30*$F$65 -> -0.033765264 | M65: =-M30*$F$65 -> -0.034778222 | N65: =-N30*$F$65 -> -0.035821569 | ... BN65: =-BN30*$F$65 -> 0 | BP65: =SUM(G65:R65) -> -0.38423387 | BQ65: =SUM(T65:AD65) -> -0.74461735 | BR65: =SUM(AE65:AP65) -> -1.4204183 | BS65: =SUM(AQ65:BB65) -> -2.3705691 | BT65: =SUM(BC65:BN65) -> -3.411882
C66: =C31 -> # de clientes Assinatura 1 | F66: ='1.Premissas Receitas'!C26 -> 500 | G66: =-G31*$F$66 -> 0 | H66: =-H31*$F$66 -> -10.5 | I66: =-I31*$F$66 -> -10.815 | J66: =-J31*$F$66 -> -11.13945 | K66: =-K31*$F$66 -> -11.473634 | L66: =-L31*$F$66 -> -11.817843 | M66: =-M31*$F$66 -> -12.172378 | N66: =-N31*$F$66 -> -12.537549 | ... BN66: =-BN31*$F$66 -> 0 | BP66: =SUM(G66:R66) -> -134.48185 | BQ66: =SUM(T66:AD66) -> -260.61607 | BR66: =SUM(AE66:AP66) -> -497.1464 | BS66: =SUM(AQ66:BB66) -> -829.69919 | BT66: =SUM(BC66:BN66) -> -1194.1587
C67: =C32 -> # de clientes Assinatura 2 | F67: ='1.Premissas Receitas'!C27 -> 1400 | G67: =-G32*$F$67 -> 0 | H67: =-H32*$F$67 -> -12.6 | I67: =-I32*$F$67 -> -12.978 | J67: =-J32*$F$67 -> -13.36734 | K67: =-K32*$F$67 -> -13.76836 | L67: =-L32*$F$67 -> -14.181411 | M67: =-M32*$F$67 -> -14.606853 | N67: =-N32*$F$67 -> -15.045059 | ... BN67: =-BN32*$F$67 -> 0 | BP67: =SUM(G67:R67) -> -161.37823 | BQ67: =SUM(T67:AD67) -> -312.73929 | BR67: =SUM(AE67:AP67) -> -596.57567 | BS67: =SUM(AQ67:BB67) -> -995.63903 | BT67: =SUM(BC67:BN67) -> -1432.9904
C68: =C33 -> # Pay-per-use Produto/Serviço 1 | F68: ='1.Premissas Receitas'!C63 -> 1 | G68: =-G33*$F$68 -> 0 | H68: =-H33*$F$68 -> 0 | I68: =-I33*$F$68 -> 0 | J68: =-J33*$F$68 -> 0 | K68: =-K33*$F$68 -> 0 | L68: =-L33*$F$68 -> 0 | M68: =-M33*$F$68 -> 0 | N68: =-N33*$F$68 -> 0 | ... BN68: =-BN33*$F$68 -> 0 | BP68: =SUM(G68:R68) -> 0 | BQ68: =SUM(T68:AD68) -> 0 | BR68: =SUM(AE68:AP68) -> 0 | BS68: =SUM(AQ68:BB68) -> 0 | BT68: =SUM(BC68:BN68) -> 0
C69: =C34 -> # Pay-per-use Produto/Serviço 2 | F69: ='1.Premissas Receitas'!C64 -> 1 | G69: =-G34*$F$69 -> 0 | H69: =-H34*$F$69 -> 0 | I69: =-I34*$F$69 -> 0 | J69: =-J34*$F$69 -> 0 | K69: =-K34*$F$69 -> 0 | L69: =-L34*$F$69 -> 0 | M69: =-M34*$F$69 -> 0 | N69: =-N34*$F$69 -> 0 | ... BN69: =-BN34*$F$69 -> 0 | BP69: =SUM(G69:R69) -> 0 | BQ69: =SUM(T69:AD69) -> 0 | BR69: =SUM(AE69:AP69) -> 0 | BS69: =SUM(AQ69:BB69) -> 0 | BT69: =SUM(BC69:BN69) -> 0
C70: =C35 -> # Pay-per-use Produto/Serviço 3 | F70: ='1.Premissas Receitas'!C65 -> 1 | G70: =-G35*$F$70 -> 0 | H70: =-H35*$F$70 -> 0 | I70: =-I35*$F$70 -> 0 | J70: =-J35*$F$70 -> 0 | K70: =-K35*$F$70 -> 0 | L70: =-L35*$F$70 -> 0 | M70: =-M35*$F$70 -> 0 | N70: =-N35*$F$70 -> 0 | ... BN70: =-BN35*$F$70 -> 0 | BP70: =SUM(G70:R70) -> 0 | BQ70: =SUM(T70:AD70) -> 0 | BR70: =SUM(AE70:AP70) -> 0 | BS70: =SUM(AQ70:BB70) -> 0 | BT70: =SUM(BC70:BN70) -> 0
B71: Churn Anual do Final do Período | G71: =SUM(G64:G70) -> 0 | H71: =SUM(H64:H70) -> -23.19 | I71: =SUM(I64:I70) -> -23.8857 | J71: =SUM(J64:J70) -> -24.602271 | K71: =SUM(K64:K70) -> -25.340339 | L71: =SUM(L64:L70) -> -26.100549 | M71: =SUM(M64:M70) -> -26.883566 | N71: =SUM(N64:N70) -> -27.690073 | ... BN71: =SUM(BN64:BN70) -> 0 | BP71: =SUM(BP64:BP70) -> -296.24431 | BQ71: =SUM(BQ64:BQ70) -> -574.09998 | BR71: =SUM(BR64:BR70) -> -1095.1425 | BS71: =SUM(BS64:BS70) -> -1827.7088 | BT71: =SUM(BT64:BT70) -> -2630.561
B73: Receita Total Anual do Final do Período | G73: =G61+G71 -> 31437.667 | H73: =H61+H71 -> 63795.273 | I73: =I61+I71 -> 97146.798 | J73: =J61+J71 -> 131498.87 | K73: =K61+K71 -> 166881.5 | L73: =L61+L71 -> 203325.61 | M73: =M61+M71 -> 240863.05 | N73: =N61+N71 -> 279526.61 | ... BN73: =BN61+BN71 -> 9565385.6 | BP73: =BP61+BP71 -> 445868.05 | BQ73: =BQ61+BQ71 -> 1249300.3 | BR73: =BR61+BR71 -> 2804691.7 | BS73: =BS61+BS71 -> 5388455.1 | BT73: =BT61+BT71 -> 9501831.1
A75: Impostos
B77: Impostos | G77: =IF('1.Premissas Receitas'!$B$8=1,0.18,IF('1.Premissas Receitas'!$B$8=2,0.05,0.1))*G61 -> 1571.8833 | H77: =IF('1.Premissas Receitas'!$B$8=1,0.18,IF('1.Premissas Receitas'!$B$8=2,0.05,0.1))*H61 -> 3190.9232 | I77: =IF('1.Premissas Receitas'!$B$8=1,0.18,IF('1.Premissas Receitas'!$B$8=2,0.05,0.1))*I61 -> 4858.5342 | J77: =IF('1.Premissas Receitas'!$B$8=1,0.18,IF('1.Premissas Receitas'!$B$8=2,0.05,0.1))*J61 -> 6576.1736 | K77: =IF('1.Premissas Receitas'!$B$8=1,0.18,IF('1.Premissas Receitas'!$B$8=2,0.05,0.1))*K61 -> 8345.3421 | L77: =IF('1.Premissas Receitas'!$B$8=1,0.18,IF('1.Premissas Receitas'!$B$8=2,0.05,0.1))*L61 -> 10167.586 | M77: =IF('1.Premissas Receitas'!$B$8=1,0.18,IF('1.Premissas Receitas'!$B$8=2,0.05,0.1))*M61 -> 12044.497 | N77: =IF('1.Premissas Receitas'!$B$8=1,0.18,IF('1.Premissas Receitas'!$B$8=2,0.05,0.1))*N61 -> 13977.715 | ... R77: =IF('1.Premissas Receitas'!$B$8=1,0.18,IF('1.Premissas Receitas'!$B$8=2,0.05,0.1))*R61 -> 22308.215 | S77: =IF('1.Premissas Receitas'!$C$8=1,0.18,IF('1.Premissas Receitas'!$C$8=2,0.05,0.1))*S61 -> 25354.411 | T77: =IF('1.Premissas Receitas'!$C$8=1,0.18,IF('1.Premissas Receitas'!$C$8=2,0.05,0.1))*T61 -> 28491.992 | U77: =IF('1.Premissas Receitas'!$C$8=1,0.18,IF('1.Premissas Receitas'!$C$8=2,0.05,0.1))*U61 -> 31723.701 | V77: =IF('1.Premissas Receitas'!$C$8=1,0.18,IF('1.Premissas Receitas'!$C$8=2,0.05,0.1))*V61 -> 35052.362 | W77: =IF('1.Premissas Receitas'!$C$8=1,0.18,IF('1.Premissas Receitas'!$C$8=2,0.05,0.1))*W61 -> 38480.882 | X77: =IF('1.Premissas Receitas'!$C$8=1,0.18,IF('1.Premissas Receitas'!$C$8=2,0.05,0.1))*X61 -> 42012.258 | Y77: =IF('1.Premissas Receitas'!$C$8=1,0.18,IF('1.Premissas Receitas'!$C$8=2,0.05,0.1))*Y61 -> 45649.575 | Z77: =IF('1.Premissas Receitas'!$C$8=1,0.18,IF('1.Premissas Receitas'!$C$8=2,0.05,0.1))*Z61 -> 49396.012 | ... AD77: =IF('1.Premissas Receitas'!$C$8=1,0.18,IF('1.Premissas Receitas'!$C$8=2,0.05,0.1))*AD61 -> 65539.916 | AE77: =IF('1.Premissas Receitas'!$D$8=1,0.18,IF('1.Premissas Receitas'!$D$8=2,0.05,0.1))*AE61 -> 71021.557 | AF77: =IF('1.Premissas Receitas'!$D$8=1,0.18,IF('1.Premissas Receitas'!$D$8=2,0.05,0.1))*AF61 -> 76667.648 | AG77: =IF('1.Premissas Receitas'!$D$8=1,0.18,IF('1.Premissas Receitas'!$D$8=2,0.05,0.1))*AG61 -> 82483.122 | AH77: =IF('1.Premissas Receitas'!$D$8=1,0.18,IF('1.Premissas Receitas'!$D$8=2,0.05,0.1))*AH61 -> 88473.06 | AI77: =IF('1.Premissas Receitas'!$D$8=1,0.18,IF('1.Premissas Receitas'!$D$8=2,0.05,0.1))*AI61 -> 94642.696 | AJ77: =IF('1.Premissas Receitas'!$D$8=1,0.18,IF('1.Premissas Receitas'!$D$8=2,0.05,0.1))*AJ61 -> 100997.42 | AK77: =IF('1.Premissas Receitas'!$D$8=1,0.18,IF('1.Premissas Receitas'!$D$8=2,0.05,0.1))*AK61 -> 107542.79 | AL77: =IF('1.Premissas Receitas'!$D$8=1,0.18,IF('1.Premissas Receitas'!$D$8=2,0.05,0.1))*AL61 -> 114284.52 | ... AP77: =IF('1.Premissas Receitas'!$D$8=1,0.18,IF('1.Premissas Receitas'!$D$8=2,0.05,0.1))*AP61 -> 143335.54 | AQ77: =IF('1.Premissas Receitas'!$E$8=1,0.18,IF('1.Premissas Receitas'!$E$8=2,0.05,0.1))*AQ61 -> 304881.97 | AR77: =IF('1.Premissas Receitas'!$E$8=1,0.18,IF('1.Premissas Receitas'!$E$8=2,0.05,0.1))*AR61 -> 323639.19 | AS77: =IF('1.Premissas Receitas'!$E$8=1,0.18,IF('1.Premissas Receitas'!$E$8=2,0.05,0.1))*AS61 -> 342959.14 | AT77: =IF('1.Premissas Receitas'!$E$8=1,0.18,IF('1.Premissas Receitas'!$E$8=2,0.05,0.1))*AT61 -> 362858.68 | AU77: =IF('1.Premissas Receitas'!$E$8=1,0.18,IF('1.Premissas Receitas'!$E$8=2,0.05,0.1))*AU61 -> 383355.2 | AV77: =IF('1.Premissas Receitas'!$E$8=1,0.18,IF('1.Premissas Receitas'!$E$8=2,0.05,0.1))*AV61 -> 404466.62 | AW77: =IF('1.Premissas Receitas'!$E$8=1,0.18,IF('1.Premissas Receitas'!$E$8=2,0.05,0.1))*AW61 -> 426211.39 | AX77: =IF('1.Premissas Receitas'!$E$8=1,0.18,IF('1.Premissas Receitas'!$E$8=2,0.05,0.1))*AX61 -> 448608.49 | ... BB77: =IF('1.Premissas Receitas'!$E$8=1,0.18,IF('1.Premissas Receitas'!$E$8=2,0.05,0.1))*BB61 -> 545120.67 | BC77: =IF('1.Premissas Receitas'!$F$8=1,0.18,IF('1.Premissas Receitas'!$F$8=2,0.05,0.1))*BC61 -> 574110.03 | BD77: =IF('1.Premissas Receitas'!$F$8=1,0.18,IF('1.Premissas Receitas'!$F$8=2,0.05,0.1))*BD61 -> 603969.08 | BE77: =IF('1.Premissas Receitas'!$F$8=1,0.18,IF('1.Premissas Receitas'!$F$8=2,0.05,0.1))*BE61 -> 634723.89 | BF77: =IF('1.Premissas Receitas'!$F$8=1,0.18,IF('1.Premissas Receitas'!$F$8=2,0.05,0.1))*BF61 -> 666401.35 | BG77: =IF('1.Premissas Receitas'!$F$8=1,0.18,IF('1.Premissas Receitas'!$F$8=2,0.05,0.1))*BG61 -> 699029.13 | BH77: =IF('1.Premissas Receitas'!$F$8=1,0.18,IF('1.Premissas Receitas'!$F$8=2,0.05,0.1))*BH61 -> 732635.75 | BI77: =IF('1.Premissas Receitas'!$F$8=1,0.18,IF('1.Premissas Receitas'!$F$8=2,0.05,0.1))*BI61 -> 767250.56 | BJ77: =IF('1.Premissas Receitas'!$F$8=1,0.18,IF('1.Premissas Receitas'!$F$8=2,0.05,0.1))*BJ61 -> 802903.82 | ... BN77: =IF('1.Premissas Receitas'!$F$8=1,0.18,IF('1.Premissas Receitas'!$F$8=2,0.05,0.1))*BN61 -> 956538.56 | BP77: =IF('1.Premissas Receitas'!$B$8=1,0.18,IF('1.Premissas Receitas'!$B$8=2,0.05,0.1))*BP61 -> 22308.215 | BQ77: =IF('1.Premissas Receitas'!$C$8=1,0.18,IF('1.Premissas Receitas'!$C$8=2,0.05,0.1))*BQ61 -> 62493.72 | BR77: =IF('1.Premissas Receitas'!$D$8=1,0.18,IF('1.Premissas Receitas'!$D$8=2,0.05,0.1))*BR61 -> 140289.34 | BS77: =IF('1.Premissas Receitas'!$E$8=1,0.18,IF('1.Premissas Receitas'!$E$8=2,0.05,0.1))*BS61 -> 539028.28 | BT77: =IF('1.Premissas Receitas'!$F$8=1,0.18,IF('1.Premissas Receitas'!$F$8=2,0.05,0.1))*BT61 -> 950446.17
A79: Custo de receita
B81: Custo sob Serviços - Início do Período | G81: =+F100 -> 0 | H81: =+G100 -> 7964.3333 | I81: =+H100 -> 8203.2633 | J81: =+I100 -> 8449.3612 | K81: =+J100 -> 8702.8421 | L81: =+K100 -> 8963.9273 | M81: =+L100 -> 9232.8452 | N81: =+M100 -> 9509.8305 | ... BN81: =+BM100 -> 98698.383 | BP81: =+BO100 -> 0 | BQ81: =+BP100 -> 113030.05 | BR81: =+BQ100 -> 203609.74 | BS81: =+BR100 -> 394170.63 | BT81: =+BS100 -> 654749.21
C82: =C43 -> # de clientes Assinatura Fremium | F82: ='1.Premissas Receitas'!D25 -> 0 | G82: =$F$82*G9 -> 0 | H82: =$F$82*H9 -> 0 | I82: =$F$82*I9 -> 0 | J82: =$F$82*J9 -> 0 | K82: =$F$82*K9 -> 0 | L82: =$F$82*L9 -> 0 | M82: =$F$82*M9 -> 0 | N82: =$F$82*N9 -> 0 | ... BN82: =$F$82*BN9 -> 0 | BP82: =SUM(G82:R82) -> 0 | BQ82: =SUM(T82:AD82) -> 0 | BR82: =SUM(AE82:AP82) -> 0 | BS82: =SUM(AQ82:BB82) -> 0 | BT82: =SUM(BC82:BN82) -> 0
C83: =C44 -> # de clientes Assinatura 1 | F83: ='1.Premissas Receitas'!D26 -> 150 | G83: =$F$83*G10 -> 105 | H83: =$F$83*H10 -> 108.15 | I83: =$F$83*I10 -> 111.3945 | J83: =$F$83*J10 -> 114.73633 | K83: =$F$83*K10 -> 118.17843 | L83: =$F$83*L10 -> 121.72378 | M83: =$F$83*M10 -> 125.37549 | N83: =$F$83*N10 -> 129.13676 | ... BN83: =$F$83*BN10 -> 1340.2541 | BP83: =SUM(G83:R83) -> 1490.1631 | BQ83: =SUM(T83:AD83) -> 2684.3456 | BR83: =SUM(AE83:AP83) -> 5196.658 | BS83: =SUM(AQ83:BB83) -> 8632.0681 | BT83: =SUM(BC83:BN83) -> 13741.121
C84: =C45 -> # de clientes Assinatura 2 | F84: ='1.Premissas Receitas'!D27 -> 420 | G84: =$F$84*G11 -> 126 | H84: =$F$84*H11 -> 129.78 | I84: =$F$84*I11 -> 133.6734 | J84: =$F$84*J11 -> 137.6836 | K84: =$F$84*K11 -> 141.81411 | L84: =$F$84*L11 -> 146.06853 | M84: =$F$84*M11 -> 150.45059 | N84: =$F$84*N11 -> 154.96411 | ... BN84: =$F$84*BN11 -> 1608.3049 | BP84: =SUM(G84:R84) -> 1788.1957 | BQ84: =SUM(T84:AD84) -> 3221.2147 | BR84: =SUM(AE84:AP84) -> 6235.9896 | BS84: =SUM(AQ84:BB84) -> 10358.482 | BT84: =SUM(BC84:BN84) -> 16489.345
C85: =C46 -> # de clientes marketplace % Comissão 1 | F85: ='1.Premissas Receitas'!D33 -> 0 | G85: =$F$85*G12 -> 0 | H85: =$F$85*H12 -> 0 | I85: =$F$85*I12 -> 0 | J85: =$F$85*J12 -> 0 | K85: =$F$85*K12 -> 0 | L85: =$F$85*L12 -> 0 | M85: =$F$85*M12 -> 0 | N85: =$F$85*N12 -> 0 | ... BN85: =$F$85*BN12 -> 0 | BP85: =SUM(G85:R85) -> 0 | BQ85: =SUM(T85:AD85) -> 0 | BR85: =SUM(AE85:AP85) -> 0 | BS85: =SUM(AQ85:BB85) -> 0 | BT85: =SUM(BC85:BN85) -> 0
C86: =C47 -> # de clientes marketplace % Comissão 2 | F86: ='1.Premissas Receitas'!D34 -> 0 | G86: =$F$86*G13 -> 0 | H86: =$F$86*H13 -> 0 | I86: =$F$86*I13 -> 0 | J86: =$F$86*J13 -> 0 | K86: =$F$86*K13 -> 0 | L86: =$F$86*L13 -> 0 | M86: =$F$86*M13 -> 0 | N86: =$F$86*N13 -> 0 | ... BN86: =$F$86*BN13 -> 0 | BP86: =SUM(G86:R86) -> 0 | BQ86: =SUM(T86:AD86) -> 0 | BR86: =SUM(AE86:AP86) -> 0 | BS86: =SUM(AQ86:BB86) -> 0 | BT86: =SUM(BC86:BN86) -> 0
C87: =C48 -> # de clientes marketplace % Comissão 3 | F87: ='1.Premissas Receitas'!D35 -> 0 | G87: =$F$87*G14 -> 0 | H87: =$F$87*H14 -> 0 | I87: =$F$87*I14 -> 0 | J87: =$F$87*J14 -> 0 | K87: =$F$87*K14 -> 0 | L87: =$F$87*L14 -> 0 | M87: =$F$87*M14 -> 0 | N87: =$F$87*N14 -> 0 | ... BN87: =$F$87*BN14 -> 0 | BP87: =SUM(G87:R87) -> 0 | BQ87: =SUM(T87:AD87) -> 0 | BR87: =SUM(AE87:AP87) -> 0 | BS87: =SUM(AQ87:BB87) -> 0 | BT87: =SUM(BC87:BN87) -> 0
C88: =C49 -> # de clientes B2B Setup | F88: ='1.Premissas Receitas'!D40 -> 5000 | G88: =$F$88*G15 -> 6666.6667 | H88: =$F$88*H15 -> 6866.6667 | I88: =$F$88*I15 -> 7072.6667 | J88: =$F$88*J15 -> 7284.8467 | K88: =$F$88*K15 -> 7503.3921 | L88: =$F$88*L15 -> 7728.4938 | M88: =$F$88*M15 -> 7960.3486 | N88: =$F$88*N15 -> 8199.1591 | ... BN88: =$F$88*BN15 -> 85095.496 | BP88: =SUM(G88:R88) -> 94613.53 | BQ88: =SUM(T88:AD88) -> 170434.64 | BR88: =SUM(AE88:AP88) -> 329946.54 | BS88: =SUM(AQ88:BB88) -> 548067.81 | BT88: =SUM(BC88:BN88) -> 872452.13
C89: =C50 -> # de clientes B2B Mensalidade | F89: ='1.Premissas Receitas'!D41 -> 800 | G89: =$F$89*G16 -> 1066.6667 | H89: =$F$89*H16 -> 1098.6667 | I89: =$F$89*I16 -> 1131.6267 | J89: =$F$89*J16 -> 1165.5755 | K89: =$F$89*K16 -> 1200.5427 | L89: =$F$89*L16 -> 1236.559 | M89: =$F$89*M16 -> 1273.6558 | N89: =$F$89*N16 -> 1311.8655 | ... BN89: =$F$89*BN16 -> 13615.279 | BP89: =SUM(G89:R89) -> 15138.165 | BQ89: =SUM(T89:AD89) -> 27269.542 | BR89: =SUM(AE89:AP89) -> 52791.447 | BS89: =SUM(AQ89:BB89) -> 87690.85 | BT89: =SUM(BC89:BN89) -> 139592.34
C90: =C51 -> # de clientes B2B Manutenção | F90: ='1.Premissas Receitas'!D42 -> 0 | G90: =$F$90*G17 -> 0 | H90: =$F$90*H17 -> 0 | I90: =$F$90*I17 -> 0 | J90: =$F$90*J17 -> 0 | K90: =$F$90*K17 -> 0 | L90: =$F$90*L17 -> 0 | M90: =$F$90*M17 -> 0 | N90: =$F$90*N17 -> 0 | ... BN90: =$F$90*BN17 -> 0 | BP90: =SUM(G90:R90) -> 0 | BQ90: =SUM(T90:AD90) -> 0 | BR90: =SUM(AE90:AP90) -> 0 | BS90: =SUM(AQ90:BB90) -> 0 | BT90: =SUM(BC90:BN90) -> 0
C91: =C52 -> # de clientes Conteudo/ Paywall 1 | F91: ='1.Premissas Receitas'!D48 -> 0 | G91: =$F$91*G18 -> 0 | H91: =$F$91*H18 -> 0 | I91: =$F$91*I18 -> 0 | J91: =$F$91*J18 -> 0 | K91: =$F$91*K18 -> 0 | L91: =$F$91*L18 -> 0 | M91: =$F$91*M18 -> 0 | N91: =$F$91*N18 -> 0 | ... BN91: =$F$91*BN18 -> 0 | BP91: =SUM(G91:R91) -> 0 | BQ91: =SUM(T91:AD91) -> 0 | BR91: =SUM(AE91:AP91) -> 0 | BS91: =SUM(AQ91:BB91) -> 0 | BT91: =SUM(BC91:BN91) -> 0
C92: =C53 -> # de clientes Conteudo/ Paywall 2 | F92: ='1.Premissas Receitas'!D49 -> 0 | G92: =$F$92*G19 -> 0 | H92: =$F$92*H19 -> 0 | I92: =$F$92*I19 -> 0 | J92: =$F$92*J19 -> 0 | K92: =$F$92*K19 -> 0 | L92: =$F$92*L19 -> 0 | M92: =$F$92*M19 -> 0 | N92: =$F$92*N19 -> 0 | ... BN92: =$F$92*BN19 -> 0 | BP92: =SUM(G92:R92) -> 0 | BQ92: =SUM(T92:AD92) -> 0 | BR92: =SUM(AE92:AP92) -> 0 | BS92: =SUM(AQ92:BB92) -> 0 | BT92: =SUM(BC92:BN92) -> 0
C93: =C54 -> # de clientes Conteudo/ Paywall 3 | F93: ='1.Premissas Receitas'!D50 -> 0 | G93: =$F$93*G20 -> 0 | H93: =$F$93*H20 -> 0 | I93: =$F$93*I20 -> 0 | J93: =$F$93*J20 -> 0 | K93: =$F$93*K20 -> 0 | L93: =$F$93*L20 -> 0 | M93: =$F$93*M20 -> 0 | N93: =$F$93*N20 -> 0 | ... BN93: =$F$93*BN20 -> 0 | BP93: =SUM(G93:R93) -> 0 | BQ93: =SUM(T93:AD93) -> 0 | BR93: =SUM(AE93:AP93) -> 0 | BS93: =SUM(AQ93:BB93) -> 0 | BT93: =SUM(BC93:BN93) -> 0
C94: =C55 -> # de clientes publicidade Produto/Serviço 1 | F94: ='1.Premissas Receitas'!D56 -> 0 | G94: =$F$94*G21 -> 0 | H94: =$F$94*H21 -> 0 | I94: =$F$94*I21 -> 0 | J94: =$F$94*J21 -> 0 | K94: =$F$94*K21 -> 0 | L94: =$F$94*L21 -> 0 | M94: =$F$94*M21 -> 0 | N94: =$F$94*N21 -> 0 | ... BN94: =$F$94*BN21 -> 0 | BP94: =SUM(G94:R94) -> 0 | BQ94: =SUM(T94:AD94) -> 0 | BR94: =SUM(AE94:AP94) -> 0 | BS94: =SUM(AQ94:BB94) -> 0 | BT94: =SUM(BC94:BN94) -> 0
C95: =C56 -> # de clientes publicidade Produto/Serviço 2 | F95: ='1.Premissas Receitas'!D57 -> 0 | G95: =$F$95*G22 -> 0 | H95: =$F$95*H22 -> 0 | I95: =$F$95*I22 -> 0 | J95: =$F$95*J22 -> 0 | K95: =$F$95*K22 -> 0 | L95: =$F$95*L22 -> 0 | M95: =$F$95*M22 -> 0 | N95: =$F$95*N22 -> 0 | ... BN95: =$F$95*BN22 -> 0 | BP95: =SUM(G95:R95) -> 0 | BQ95: =SUM(T95:AD95) -> 0 | BR95: =SUM(AE95:AP95) -> 0 | BS95: =SUM(AQ95:BB95) -> 0 | BT95: =SUM(BC95:BN95) -> 0
C96: =C57 -> # de clientes publicidade Produto/Serviço 3 | F96: ='1.Premissas Receitas'!D58 -> 0 | G96: =$F$96*G23 -> 0 | H96: =$F$96*H23 -> 0 | I96: =$F$96*I23 -> 0 | J96: =$F$96*J23 -> 0 | K96: =$F$96*K23 -> 0 | L96: =$F$96*L23 -> 0 | M96: =$F$96*M23 -> 0 | N96: =$F$96*N23 -> 0 | ... BN96: =$F$96*BN23 -> 0 | BP96: =SUM(G96:R96) -> 0 | BQ96: =SUM(T96:AD96) -> 0 | BR96: =SUM(AE96:AP96) -> 0 | BS96: =SUM(AQ96:BB96) -> 0 | BT96: =SUM(BC96:BN96) -> 0
C97: =C58 -> # Pay-per-use Produto/Serviço 1 | F97: ='1.Premissas Receitas'!D63 -> 0 | G97: =$F$97*G24 -> 0 | H97: =$F$97*H24 -> 0 | I97: =$F$97*I24 -> 0 | J97: =$F$97*J24 -> 0 | K97: =$F$97*K24 -> 0 | L97: =$F$97*L24 -> 0 | M97: =$F$97*M24 -> 0 | N97: =$F$97*N24 -> 0 | ... BN97: =$F$97*BN24 -> 0 | BP97: =SUM(G97:R97) -> 0 | BQ97: =SUM(T97:AD97) -> 0 | BR97: =SUM(AE97:AP97) -> 0 | BS97: =SUM(AQ97:BB97) -> 0 | BT97: =SUM(BC97:BN97) -> 0
C98: =C59 -> # Pay-per-use Produto/Serviço 2 | F98: ='1.Premissas Receitas'!D64 -> 0 | G98: =$F$98*G25 -> 0 | H98: =$F$98*H25 -> 0 | I98: =$F$98*I25 -> 0 | J98: =$F$98*J25 -> 0 | K98: =$F$98*K25 -> 0 | L98: =$F$98*L25 -> 0 | M98: =$F$98*M25 -> 0 | N98: =$F$98*N25 -> 0 | ... BN98: =$F$98*BN25 -> 0 | BP98: =SUM(G98:R98) -> 0 | BQ98: =SUM(T98:AD98) -> 0 | BR98: =SUM(AE98:AP98) -> 0 | BS98: =SUM(AQ98:BB98) -> 0 | BT98: =SUM(BC98:BN98) -> 0
C99: =C60 -> # Pay-per-use Produto/Serviço 3 | F99: ='1.Premissas Receitas'!D65 -> 0 | G99: =$F$99*G26 -> 0 | H99: =$F$99*H26 -> 0 | I99: =$F$99*I26 -> 0 | J99: =$F$99*J26 -> 0 | K99: =$F$99*K26 -> 0 | L99: =$F$99*L26 -> 0 | M99: =$F$99*M26 -> 0 | N99: =$F$99*N26 -> 0 | ... BN99: =$F$99*BN26 -> 0 | BP99: =SUM(G99:R99) -> 0 | BQ99: =SUM(T99:AD99) -> 0 | BR99: =SUM(AE99:AP99) -> 0 | BS99: =SUM(AQ99:BB99) -> 0 | BT99: =SUM(BC99:BN99) -> 0
A100: Custo sob Serviço - Final do Período | G100: =+SUM(G82:G99) -> 7964.3333 | H100: =+SUM(H82:H99) -> 8203.2633 | I100: =+SUM(I82:I99) -> 8449.3612 | J100: =+SUM(J82:J99) -> 8702.8421 | K100: =+SUM(K82:K99) -> 8963.9273 | L100: =+SUM(L82:L99) -> 9232.8452 | M100: =+SUM(M82:M99) -> 9509.8305 | N100: =+SUM(N82:N99) -> 9795.1254 | ... BN100: =+SUM(BN82:BN99) -> 101659.33 | BP100: =+SUM(BP82:BP99) -> 113030.05 | BQ100: =+SUM(BQ82:BQ99) -> 203609.74 | BR100: =+SUM(BR82:BR99) -> 394170.63 | BS100: =+SUM(BS82:BS99) -> 654749.21 | BT100: =+SUM(BT82:BT99) -> 1042274.9
A102: Lucro bruto | G102: =+G73-G100-G77 -> 21901.45 | H102: =+H73-H100-H77 -> 52401.087 | I102: =+I73-I100-I77 -> 83838.903 | J102: =+J73-J100-J77 -> 116219.85 | K102: =+K73-K100-K77 -> 149572.23 | L102: =+L73-L100-L77 -> 183925.18 | M102: =+M73-M100-M77 -> 219308.72 | N102: =+N73-N100-N77 -> 255753.77 | ... BN102: =+BN73-BN100-BN77 -> 8507187.7 | BP102: =+BP73-BP100-BP77 -> 310529.78 | BQ102: =+BQ73-BQ100-BQ77 -> 983196.84 | BR102: =+BR73-BR100-BR77 -> 2270231.7 | BS102: =+BS73-BS100-BS77 -> 4194677.6 | BT102: =+BT73-BT100-BT77 -> 7509110
B103: % Margem Bruta | G103: =IFERROR((G61-G63)/G61,0) -> 1 | H103: =IFERROR((H61-H63)/H61,0) -> 1 | I103: =IFERROR((I61-I63)/I61,0) -> 1 | J103: =IFERROR((J61-J63)/J61,0) -> 1 | K103: =IFERROR((K61-K63)/K61,0) -> 1 | L103: =IFERROR((L61-L63)/L61,0) -> 1 | M103: =IFERROR((M61-M63)/M61,0) -> 1 | N103: =IFERROR((N61-N63)/N61,0) -> 1 | ... BI103: =IFERROR((BI61-BI63)/BI61,0) -> 1 | BJ103: =+IFERROR(BJ73/BJ100,"-") -> 88.889682 | BK103: =+IFERROR(BK73/BK100,"-") -> 90.247886 | BL103: =+IFERROR(BL73/BL100,"-") -> 91.566532 | BM103: =+IFERROR(BM73/BM100,"-") -> 92.84677 | BN103: =+IFERROR(BN73/BN100,"-") -> 94.092546 | BP103: =+IFERROR(BP73/BP100,"-") -> 3.9446858 | BQ103: =+IFERROR(BQ73/BQ100,"-") -> 6.135759 | BR103: =+IFERROR(BR73/BR100,"-") -> 7.1154252 | BS103: =+IFERROR(BS73/BS100,"-") -> 8.2298 | BT103: =+IFERROR(BT73/BT100,"-") -> 9.1164344
A105: Despesas Operacionais
B106: Vendas e Marketing
C107: Serviços de V&M, software, ferramentas - % da receita | F107: ='3.Premissas de Despesas'!B4 -> 8000 | G107: =$F107 -> 8000 | H107: =$F107 -> 8000 | I107: =$F107 -> 8000 | J107: =$F107 -> 8000 | K107: =$F107 -> 8000 | L107: =$F107 -> 8000 | M107: =$F107 -> 8000 | N107: =$F107 -> 8000 | ... R107: =$F107 -> 8000 | S107: =$F107+(F107*'3.Premissas de Despesas'!$B$23) -> 8800 | T107: =$S$107 -> 8800 | U107: =$S$107 -> 8800 | V107: =$S$107 -> 8800 | W107: =$S$107 -> 8800 | X107: =$S$107 -> 8800 | Y107: =$S$107 -> 8800 | Z107: =$S$107 -> 8800 | AA107: =$S$107 -> 8800 | ... AD107: =$S$107 -> 8800 | AE107: =$F107+(R107*'3.Premissas de Despesas'!$B$24) -> 9200 | AF107: =$AE$107 -> 9200 | AG107: =$AE$107 -> 9200 | AH107: =$AE$107 -> 9200 | AI107: =$AE$107 -> 9200 | AJ107: =$AE$107 -> 9200 | AK107: =$AE$107 -> 9200 | AL107: =$AE$107 -> 9200 | AM107: =$AE$107 -> 9200 | ... AP107: =$AE$107 -> 9200 | AQ107: =$F107+(AD107*'3.Premissas de Despesas'!$B$25) -> 9760 | AR107: =$AQ$107 -> 9760 | AS107: =$AQ$107 -> 9760 | AT107: =$AQ$107 -> 9760 | AU107: =$AQ$107 -> 9760 | AV107: =$AQ$107 -> 9760 | AW107: =$AQ$107 -> 9760 | AX107: =$AQ$107 -> 9760 | AY107: =$AQ$107 -> 9760 | ... BB107: =$AQ$107 -> 9760 | BC107: =$F107+(AP107*'3.Premissas de Despesas'!$B$26) -> 10300 | BD107: =$BC$107 -> 10300 | BE107: =$BC$107 -> 10300 | BF107: =$BC$107 -> 10300 | BG107: =$BC$107 -> 10300 | BH107: =$BC$107 -> 10300 | BI107: =$BC$107 -> 10300 | BJ107: =$BC$107 -> 10300 | BK107: =$BC$107 -> 10300 | ... BN107: =$BC$107 -> 10300 | BP107: =SUM(G107:R107) -> 96000 | BQ107: =SUM(T107:AD107) -> 96800 | BR107: =SUM(AE107:AP107) -> 110400 | BS107: =SUM(AQ107:BB107) -> 117120 | BT107: =SUM(BC107:BN107) -> 123600
C108: Folha de pagamento de V&M | F108: ='3.Premissas de Despesas'!B5 -> 18333 | G108: =$F108 -> 18333 | H108: =$F108 -> 18333 | I108: =$F108 -> 18333 | J108: =$F108 -> 18333 | K108: =$F108 -> 18333 | L108: =$F108 -> 18333 | M108: =$F108 -> 18333 | N108: =$F108 -> 18333 | ... R108: =$F108 -> 18333 | S108: =$F108+(F108*'3.Premissas de Despesas'!$B$23) -> 20166.3 | T108: =$S$108 -> 20166.3 | U108: =$S$108 -> 20166.3 | V108: =$S$108 -> 20166.3 | W108: =$S$108 -> 20166.3 | X108: =$S$108 -> 20166.3 | Y108: =$S$108 -> 20166.3 | Z108: =$S$108 -> 20166.3 | AA108: =$S$108 -> 20166.3 | ... AD108: =$S$108 -> 20166.3 | AE108: =$F108+(R108*'3.Premissas de Despesas'!$B$24) -> 21082.95 | AF108: =$AE$108 -> 21082.95 | AG108: =$AE$108 -> 21082.95 | AH108: =$AE$108 -> 21082.95 | AI108: =$AE$108 -> 21082.95 | AJ108: =$AE$108 -> 21082.95 | AK108: =$AE$108 -> 21082.95 | AL108: =$AE$108 -> 21082.95 | AM108: =$AE$108 -> 21082.95 | ... AP108: =$AE$108 -> 21082.95 | AQ108: =$F108+(AD108*'3.Premissas de Despesas'!$B$25) -> 22366.26 | AR108: =$AQ$108 -> 22366.26 | AS108: =$AQ$108 -> 22366.26 | AT108: =$AQ$108 -> 22366.26 | AU108: =$AQ$108 -> 22366.26 | AV108: =$AQ$108 -> 22366.26 | AW108: =$AQ$108 -> 22366.26 | AX108: =$AQ$108 -> 22366.26 | AY108: =$AQ$108 -> 22366.26 | ... BB108: =$AQ$108 -> 22366.26 | BC108: =$F108+(AP108*'3.Premissas de Despesas'!$B$26) -> 23603.737 | BD108: =$BC$108 -> 23603.737 | BE108: =$BC$108 -> 23603.737 | BF108: =$BC$108 -> 23603.737 | BG108: =$BC$108 -> 23603.737 | BH108: =$BC$108 -> 23603.737 | BI108: =$BC$108 -> 23603.737 | BJ108: =$BC$108 -> 23603.737 | BK108: =$BC$108 -> 23603.737 | ... BN108: =$BC$108 -> 23603.737 | BP108: =SUM(G108:R108) -> 219996 | BQ108: =SUM(T108:AD108) -> 221829.3 | BR108: =SUM(AE108:AP108) -> 252995.4 | BS108: =SUM(AQ108:BB108) -> 268395.12 | BT108: =SUM(BC108:BN108) -> 283244.85
S109: =$F109+(F109*'3.Premissas de Despesas'!$B$23) -> 0 | T109: =$S$109 -> 0 | U109: =$S$109 -> 0 | V109: =$S$109 -> 0 | W109: =$S$109 -> 0 | X109: =$S$109 -> 0 | Y109: =$S$109 -> 0 | Z109: =$S$109 -> 0 | AA109: =$S$109 -> 0 | ... AD109: =$S$109 -> 0 | AE109: =$F109+(R109*'3.Premissas de Despesas'!$B$24) -> 0 | AF109: =$AE$109 -> 0 | AG109: =$AE$109 -> 0 | AH109: =$AE$109 -> 0 | AI109: =$AE$109 -> 0 | AJ109: =$AE$109 -> 0 | AK109: =$AE$109 -> 0 | AL109: =$AE$109 -> 0 | AM109: =$AE$109 -> 0 | ... AP109: =$AE$109 -> 0 | AQ109: =$F109+(AD109*'3.Premissas de Despesas'!$B$25) -> 0 | AR109: =$AQ$109 -> 0 | AS109: =$AQ$109 -> 0 | AT109: =$AQ$109 -> 0 | AU109: =$AQ$109 -> 0 | AV109: =$AQ$109 -> 0 | AW109: =$AQ$109 -> 0 | AX109: =$AQ$109 -> 0 | AY109: =$AQ$109 -> 0 | ... BB109: =$AQ$109 -> 0 | BC109: =$F109+(AP109*'3.Premissas de Despesas'!$B$26) -> 0 | BD109: =$BC$109 -> 0 | BE109: =$BC$109 -> 0 | BF109: =$BC$109 -> 0 | BG109: =$BC$109 -> 0 | BH109: =$BC$109 -> 0 | BI109: =$BC$109 -> 0 | BJ109: =$BC$109 -> 0 | BK109: =$BC$109 -> 0 | ... BN109: =$BC$109 -> 0 | BP109: =SUM(G109:R109) -> 0 | BQ109: =SUM(T109:AD109) -> 0 | BR109: =SUM(AE109:AP109) -> 0 | BS109: =SUM(AQ109:BB109) -> 0 | BT109: =SUM(BC109:BN109) -> 0
B110: Pesquisa e Desenvolvimento | S110: =$F110+(F110*'3.Premissas de Despesas'!$B$23) -> 0 | T110: =$S$110 -> 0 | U110: =$S$110 -> 0 | V110: =$S$110 -> 0 | W110: =$S$110 -> 0 | X110: =$S$110 -> 0 | Y110: =$S$110 -> 0 | Z110: =$S$110 -> 0 | AA110: =$S$110 -> 0 | ... AD110: =$S$110 -> 0 | AE110: =$F110+(R110*'3.Premissas de Despesas'!$B$24) -> 0 | AF110: =$AE$110 -> 0 | AG110: =$AE$110 -> 0 | AH110: =$AE$110 -> 0 | AI110: =$AE$110 -> 0 | AJ110: =$AE$110 -> 0 | AK110: =$AE$110 -> 0 | AL110: =$AE$110 -> 0 | AM110: =$AE$110 -> 0 | ... AP110: =$AE$110 -> 0 | AQ110: =$F110+(AD110*'3.Premissas de Despesas'!$B$25) -> 0 | AR110: =$AQ$110 -> 0 | AS110: =$AQ$110 -> 0 | AT110: =$AQ$110 -> 0 | AU110: =$AQ$110 -> 0 | AV110: =$AQ$110 -> 0 | AW110: =$AQ$110 -> 0 | AX110: =$AQ$110 -> 0 | AY110: =$AQ$110 -> 0 | ... BB110: =$AQ$110 -> 0 | BC110: =$F110+(AP110*'3.Premissas de Despesas'!$B$26) -> 0 | BD110: =$BC$110 -> 0 | BE110: =$BC$110 -> 0 | BF110: =$BC$110 -> 0 | BG110: =$BC$110 -> 0 | BH110: =$BC$110 -> 0 | BI110: =$BC$110 -> 0 | BJ110: =$BC$110 -> 0 | BK110: =$BC$110 -> 0 | ... BN110: =$BC$110 -> 0 | BP110: =SUM(G110:R110) -> 0 | BQ110: =SUM(T110:AD110) -> 0 | BR110: =SUM(AE110:AP110) -> 0 | BS110: =SUM(AQ110:BB110) -> 0 | BT110: =SUM(BC110:BN110) -> 0
C111: Serviços de P&D, software, ferramentas - % da Rec. | F111: ='3.Premissas de Despesas'!B8 -> 12000 | G111: =$F111 -> 12000 | H111: =$F111 -> 12000 | I111: =$F111 -> 12000 | J111: =$F111 -> 12000 | K111: =$F111 -> 12000 | L111: =$F111 -> 12000 | M111: =$F111 -> 12000 | N111: =$F111 -> 12000 | ... R111: =$F111 -> 12000 | S111: =$F111+(F111*'3.Premissas de Despesas'!$B$23) -> 13200 | T111: =$S$111 -> 13200 | U111: =$S$111 -> 13200 | V111: =$S$111 -> 13200 | W111: =$S$111 -> 13200 | X111: =$S$111 -> 13200 | Y111: =$S$111 -> 13200 | Z111: =$S$111 -> 13200 | AA111: =$S$111 -> 13200 | ... AD111: =$S$111 -> 13200 | AE111: =$F111+(R111*'3.Premissas de Despesas'!$B$24) -> 13800 | AF111: =$AE$111 -> 13800 | AG111: =$AE$111 -> 13800 | AH111: =$AE$111 -> 13800 | AI111: =$AE$111 -> 13800 | AJ111: =$AE$111 -> 13800 | AK111: =$AE$111 -> 13800 | AL111: =$AE$111 -> 13800 | AM111: =$AE$111 -> 13800 | ... AP111: =$AE$111 -> 13800 | AQ111: =$F111+(AD111*'3.Premissas de Despesas'!$B$25) -> 14640 | AR111: =$AQ$111 -> 14640 | AS111: =$AQ$111 -> 14640 | AT111: =$AQ$111 -> 14640 | AU111: =$AQ$111 -> 14640 | AV111: =$AQ$111 -> 14640 | AW111: =$AQ$111 -> 14640 | AX111: =$AQ$111 -> 14640 | AY111: =$AQ$111 -> 14640 | ... BB111: =$AQ$111 -> 14640 | BC111: =$F111+(AP111*'3.Premissas de Despesas'!$B$26) -> 15450 | BD111: =$BC$111 -> 15450 | BE111: =$BC$111 -> 15450 | BF111: =$BC$111 -> 15450 | BG111: =$BC$111 -> 15450 | BH111: =$BC$111 -> 15450 | BI111: =$BC$111 -> 15450 | BJ111: =$BC$111 -> 15450 | BK111: =$BC$111 -> 15450 | ... BN111: =$BC$111 -> 15450 | BP111: =SUM(G111:R111) -> 144000 | BQ111: =SUM(T111:AD111) -> 145200 | BR111: =SUM(AE111:AP111) -> 165600 | BS111: =SUM(AQ111:BB111) -> 175680 | BT111: =SUM(BC111:BN111) -> 185400
C112: Folha de pagamento de P&D | F112: ='3.Premissas de Despesas'!B9 -> 37500 | G112: =$F112 -> 37500 | H112: =$F112 -> 37500 | I112: =$F112 -> 37500 | J112: =$F112 -> 37500 | K112: =$F112 -> 37500 | L112: =$F112 -> 37500 | M112: =$F112 -> 37500 | N112: =$F112 -> 37500 | ... R112: =$F112 -> 37500 | S112: =$F112+(F112*'3.Premissas de Despesas'!$B$23) -> 41250 | T112: =$S$112 -> 41250 | U112: =$S$112 -> 41250 | V112: =$S$112 -> 41250 | W112: =$S$112 -> 41250 | X112: =$S$112 -> 41250 | Y112: =$S$112 -> 41250 | Z112: =$S$112 -> 41250 | AA112: =$S$112 -> 41250 | ... AD112: =$S$112 -> 41250 | AE112: =$F112+(R112*'3.Premissas de Despesas'!$B$24) -> 43125 | AF112: =$AE$112 -> 43125 | AG112: =$AE$112 -> 43125 | AH112: =$AE$112 -> 43125 | AI112: =$AE$112 -> 43125 | AJ112: =$AE$112 -> 43125 | AK112: =$AE$112 -> 43125 | AL112: =$AE$112 -> 43125 | AM112: =$AE$112 -> 43125 | ... AP112: =$AE$112 -> 43125 | AQ112: =$F112+(AD112*'3.Premissas de Despesas'!$B$25) -> 45750 | AR112: =$AQ$112 -> 45750 | AS112: =$AQ$112 -> 45750 | AT112: =$AQ$112 -> 45750 | AU112: =$AQ$112 -> 45750 | AV112: =$AQ$112 -> 45750 | AW112: =$AQ$112 -> 45750 | AX112: =$AQ$112 -> 45750 | AY112: =$AQ$112 -> 45750 | ... BB112: =$AQ$112 -> 45750 | BC112: =$F112+(AP112*'3.Premissas de Despesas'!$B$26) -> 48281.25 | BD112: =$BC$112 -> 48281.25 | BE112: =$BC$112 -> 48281.25 | BF112: =$BC$112 -> 48281.25 | BG112: =$BC$112 -> 48281.25 | BH112: =$BC$112 -> 48281.25 | BI112: =$BC$112 -> 48281.25 | BJ112: =$BC$112 -> 48281.25 | BK112: =$BC$112 -> 48281.25 | ... BN112: =$BC$112 -> 48281.25 | BP112: =SUM(G112:R112) -> 450000 | BQ112: =SUM(T112:AD112) -> 453750 | BR112: =SUM(AE112:AP112) -> 517500 | BS112: =SUM(AQ112:BB112) -> 549000 | BT112: =SUM(BC112:BN112) -> 579375
S113: =$F113+(F113*'3.Premissas de Despesas'!$B$23) -> 0 | T113: =$S$113 -> 0 | U113: =$S$113 -> 0 | V113: =$S$113 -> 0 | W113: =$S$113 -> 0 | X113: =$S$113 -> 0 | Y113: =$S$113 -> 0 | Z113: =$S$113 -> 0 | AA113: =$S$113 -> 0 | ... AD113: =$S$113 -> 0 | AE113: =$F113+(R113*'3.Premissas de Despesas'!$B$24) -> 0 | AF113: =$AE$113 -> 0 | AG113: =$AE$113 -> 0 | AH113: =$AE$113 -> 0 | AI113: =$AE$113 -> 0 | AJ113: =$AE$113 -> 0 | AK113: =$AE$113 -> 0 | AL113: =$AE$113 -> 0 | AM113: =$AE$113 -> 0 | ... AP113: =$AE$113 -> 0 | AQ113: =$F113+(AD113*'3.Premissas de Despesas'!$B$25) -> 0 | AR113: =$AQ$113 -> 0 | AS113: =$AQ$113 -> 0 | AT113: =$AQ$113 -> 0 | AU113: =$AQ$113 -> 0 | AV113: =$AQ$113 -> 0 | AW113: =$AQ$113 -> 0 | AX113: =$AQ$113 -> 0 | AY113: =$AQ$113 -> 0 | ... BB113: =$AQ$113 -> 0 | BC113: =$F113+(AP113*'3.Premissas de Despesas'!$B$26) -> 0 | BD113: =$BC$113 -> 0 | BE113: =$BC$113 -> 0 | BF113: =$BC$113 -> 0 | BG113: =$BC$113 -> 0 | BH113: =$BC$113 -> 0 | BI113: =$BC$113 -> 0 | BJ113: =$BC$113 -> 0 | BK113: =$BC$113 -> 0 | ... BN113: =$BC$113 -> 0 | BP113: =SUM(G113:R113) -> 0 | BQ113: =SUM(T113:AD113) -> 0 | BR113: =SUM(AE113:AP113) -> 0 | BS113: =SUM(AQ113:BB113) -> 0 | BT113: =SUM(BC113:BN113) -> 0
B114: Geral & Admin | S114: =$F114+(F114*'3.Premissas de Despesas'!$B$23) -> 0 | T114: =$S$114 -> 0 | U114: =$S$114 -> 0 | V114: =$S$114 -> 0 | W114: =$S$114 -> 0 | X114: =$S$114 -> 0 | Y114: =$S$114 -> 0 | Z114: =$S$114 -> 0 | AA114: =$S$114 -> 0 | ... AD114: =$S$114 -> 0 | AE114: =$F114+(R114*'3.Premissas de Despesas'!$B$24) -> 0 | AF114: =$AE$114 -> 0 | AG114: =$AE$114 -> 0 | AH114: =$AE$114 -> 0 | AI114: =$AE$114 -> 0 | AJ114: =$AE$114 -> 0 | AK114: =$AE$114 -> 0 | AL114: =$AE$114 -> 0 | AM114: =$AE$114 -> 0 | ... AP114: =$AE$114 -> 0 | AQ114: =$F114+(AD114*'3.Premissas de Despesas'!$B$25) -> 0 | AR114: =$AQ$114 -> 0 | AS114: =$AQ$114 -> 0 | AT114: =$AQ$114 -> 0 | AU114: =$AQ$114 -> 0 | AV114: =$AQ$114 -> 0 | AW114: =$AQ$114 -> 0 | AX114: =$AQ$114 -> 0 | AY114: =$AQ$114 -> 0 | ... BB114: =$AQ$114 -> 0 | BC114: =$F114+(AP114*'3.Premissas de Despesas'!$B$26) -> 0 | BD114: =$BC$114 -> 0 | BE114: =$BC$114 -> 0 | BF114: =$BC$114 -> 0 | BG114: =$BC$114 -> 0 | BH114: =$BC$114 -> 0 | BI114: =$BC$114 -> 0 | BJ114: =$BC$114 -> 0 | BK114: =$BC$114 -> 0 | ... BN114: =$BC$114 -> 0 | BP114: =SUM(G114:R114) -> 0 | BQ114: =SUM(T114:AD114) -> 0 | BR114: =SUM(AE114:AP114) -> 0 | BS114: =SUM(AQ114:BB114) -> 0 | BT114: =SUM(BC114:BN114) -> 0
C115: Aluguel, Energia, Luz e Custos Fixos | F115: ='3.Premissas de Despesas'!B12 -> 3000 | G115: =$F115 -> 3000 | H115: =$F115 -> 3000 | I115: =$F115 -> 3000 | J115: =$F115 -> 3000 | K115: =$F115 -> 3000 | L115: =$F115 -> 3000 | M115: =$F115 -> 3000 | N115: =$F115 -> 3000 | ... R115: =$F115 -> 3000 | S115: =$F115+(F115*'3.Premissas de Despesas'!$B$23) -> 3300 | T115: =$S$115 -> 3300 | U115: =$S$115 -> 3300 | V115: =$S$115 -> 3300 | W115: =$S$115 -> 3300 | X115: =$S$115 -> 3300 | Y115: =$S$115 -> 3300 | Z115: =$S$115 -> 3300 | AA115: =$S$115 -> 3300 | ... AD115: =$S$115 -> 3300 | AE115: =$F115+(R115*'3.Premissas de Despesas'!$B$24) -> 3450 | AF115: =$AE$115 -> 3450 | AG115: =$AE$115 -> 3450 | AH115: =$AE$115 -> 3450 | AI115: =$AE$115 -> 3450 | AJ115: =$AE$115 -> 3450 | AK115: =$AE$115 -> 3450 | AL115: =$AE$115 -> 3450 | AM115: =$AE$115 -> 3450 | ... AP115: =$AE$115 -> 3450 | AQ115: =$F115+(AD115*'3.Premissas de Despesas'!$B$25) -> 3660 | AR115: =$AQ$115 -> 3660 | AS115: =$AQ$115 -> 3660 | AT115: =$AQ$115 -> 3660 | AU115: =$AQ$115 -> 3660 | AV115: =$AQ$115 -> 3660 | AW115: =$AQ$115 -> 3660 | AX115: =$AQ$115 -> 3660 | AY115: =$AQ$115 -> 3660 | ... BB115: =$AQ$115 -> 3660 | BC115: =$F115+(AP115*'3.Premissas de Despesas'!$B$26) -> 3862.5 | BD115: =$BC$115 -> 3862.5 | BE115: =$BC$115 -> 3862.5 | BF115: =$BC$115 -> 3862.5 | BG115: =$BC$115 -> 3862.5 | BH115: =$BC$115 -> 3862.5 | BI115: =$BC$115 -> 3862.5 | BJ115: =$BC$115 -> 3862.5 | BK115: =$BC$115 -> 3862.5 | ... BN115: =$BC$115 -> 3862.5 | BP115: =SUM(G115:R115) -> 36000 | BQ115: =SUM(T115:AD115) -> 36300 | BR115: =SUM(AE115:AP115) -> 41400 | BS115: =SUM(AQ115:BB115) -> 43920 | BT115: =SUM(BC115:BN115) -> 46350
C116: VIagens e Despesas Extras | F116: ='3.Premissas de Despesas'!B13 -> 2000 | G116: =$F116 -> 2000 | H116: =$F116 -> 2000 | I116: =$F116 -> 2000 | J116: =$F116 -> 2000 | K116: =$F116 -> 2000 | L116: =$F116 -> 2000 | M116: =$F116 -> 2000 | N116: =$F116 -> 2000 | ... R116: =$F116 -> 2000 | S116: =$F116+(F116*'3.Premissas de Despesas'!$B$23) -> 2200 | T116: =$S$116 -> 2200 | U116: =$S$116 -> 2200 | V116: =$S$116 -> 2200 | W116: =$S$116 -> 2200 | X116: =$S$116 -> 2200 | Y116: =$S$116 -> 2200 | Z116: =$S$116 -> 2200 | AA116: =$S$116 -> 2200 | ... AD116: =$S$116 -> 2200 | AE116: =$F116+(R116*'3.Premissas de Despesas'!$B$24) -> 2300 | AF116: =$AE$116 -> 2300 | AG116: =$AE$116 -> 2300 | AH116: =$AE$116 -> 2300 | AI116: =$AE$116 -> 2300 | AJ116: =$AE$116 -> 2300 | AK116: =$AE$116 -> 2300 | AL116: =$AE$116 -> 2300 | AM116: =$AE$116 -> 2300 | ... AP116: =$AE$116 -> 2300 | AQ116: =$F116+(AD116*'3.Premissas de Despesas'!$B$25) -> 2440 | AR116: =$AQ$116 -> 2440 | AS116: =$AQ$116 -> 2440 | AT116: =$AQ$116 -> 2440 | AU116: =$AQ$116 -> 2440 | AV116: =$AQ$116 -> 2440 | AW116: =$AQ$116 -> 2440 | AX116: =$AQ$116 -> 2440 | AY116: =$AQ$116 -> 2440 | ... BB116: =$AQ$116 -> 2440 | BC116: =$F116+(AP116*'3.Premissas de Despesas'!$B$26) -> 2575 | BD116: =$BC$116 -> 2575 | BE116: =$BC$116 -> 2575 | BF116: =$BC$116 -> 2575 | BG116: =$BC$116 -> 2575 | BH116: =$BC$116 -> 2575 | BI116: =$BC$116 -> 2575 | BJ116: =$BC$116 -> 2575 | BK116: =$BC$116 -> 2575 | ... BN116: =$BC$116 -> 2575 | BP116: =SUM(G116:R116) -> 24000 | BQ116: =SUM(T116:AD116) -> 24200 | BR116: =SUM(AE116:AP116) -> 27600 | BS116: =SUM(AQ116:BB116) -> 29280 | BT116: =SUM(BC116:BN116) -> 30900
...

Sheet Resumo
A1: Resumo da Projeção Financeira - Startup One - Fiap
A2: Demonstração do Resultado do Exercício
C4: Ano 01 | D4: Ano 02 | E4: Ano 03 | F4: Ano 04 | G4: Ano 05
A5: Receitas Brutas | C5: ='5.Projeção Financeira'!BP61 -> 446164.29 | D5: ='5.Projeção Financeira'!BQ61 -> 1249874.4 | E5: ='5.Projeção Financeira'!BR61 -> 2805786.8 | F5: ='5.Projeção Financeira'!BS61 -> 5390282.8 | G5: ='5.Projeção Financeira'!BT61 -> 9504461.7
A6: (-) Impostos | C6: =IF('1.Premissas Receitas'!B8=1,0.18,IF('1.Premissas Receitas'!B8=2,0.05,IF('1.Premissas Receitas'!B8=1,0.1,0.1)))*C5 -> 22308.215 | D6: =IF('1.Premissas Receitas'!C8=1,0.18,IF('1.Premissas Receitas'!C8=2,0.05,IF('1.Premissas Receitas'!C8=1,0.1,0.1)))*D5 -> 62493.72 | E6: =IF('1.Premissas Receitas'!D8=1,0.18,IF('1.Premissas Receitas'!D8=2,0.05,IF('1.Premissas Receitas'!D8=1,0.1,0.1)))*E5 -> 140289.34 | F6: =IF('1.Premissas Receitas'!E8=1,0.18,IF('1.Premissas Receitas'!E8=2,0.05,IF('1.Premissas Receitas'!E8=1,0.1,0.1)))*F5 -> 539028.28 | G6: =IF('1.Premissas Receitas'!F8=1,0.18,IF('1.Premissas Receitas'!F8=2,0.05,IF('1.Premissas Receitas'!F8=1,0.1,0.1)))*G5 -> 950446.17
A7: Receitas Líquidas | C7: =C5-C6 -> 423856.08 | D7: =D5-D6 -> 1187380.7 | E7: =E5-E6 -> 2665497.5 | F7: =F5-F6 -> 4851254.5 | G7: =G5-G6 -> 8554015.5
A8: (-)Custo Sob Serviço | C8: ='5.Projeção Financeira'!BP100 -> 113030.05 | D8: ='5.Projeção Financeira'!BQ100 -> 203609.74 | E8: ='5.Projeção Financeira'!BR100 -> 394170.63 | F8: ='5.Projeção Financeira'!BS100 -> 654749.21 | G8: ='5.Projeção Financeira'!BT100 -> 1042274.9
A9: (-) Despesas Operacionais | C9: ='5.Projeção Financeira'!BP119 -> 1257996 | D9: ='5.Projeção Financeira'!BQ119 -> 1268479.3 | E9: ='5.Projeção Financeira'!BR119 -> 1446695.4 | F9: ='5.Projeção Financeira'!BS119 -> 1534755.1 | G9: ='5.Projeção Financeira'!BT119 -> 1619669.8
A10: (-) Despesas Operacionais | C10: ='5.Projeção Financeira'!BP125 -> 192000 | D10: ='5.Projeção Financeira'!BQ125 -> 193600 | E10: ='5.Projeção Financeira'!BR125 -> 195200 | F10: ='5.Projeção Financeira'!BS125 -> 196800 | G10: ='5.Projeção Financeira'!BT125 -> 198400
A11: Resultado antes do IR | C11: =C7-C9-C8-C10 -> -1139170 | D11: =D7-D9-D8-D10 -> -478308.36 | E11: =E7-E9-E8-E10 -> 629431.43 | F11: =F7-F9-F8-F10 -> 2464950.2 | G11: =G7-G9-G8-G10 -> 5693670.7
A12: (-) Imposto de Renda | C12: =IF(C11>0,C11*0.25,0) -> 0 | D12: =IF(D11>0,D11*0.25,0) -> 0 | E12: =IF(E11>0,E11*0.25,0) -> 157357.86 | F12: =IF(F11>0,F11*0.25,0) -> 616237.54 | G12: =IF(G11>0,G11*0.25,0) -> 1423417.7
A13: Lucro/Prejuízo Líquido | C13: =C11-C12 -> -1139170 | D13: =D11-D12 -> -478308.36 | E13: =E11-E12 -> 472073.57 | F13: =F11-F12 -> 1848712.6 | G13: =G11-G12 -> 4270253
A16: Demonstração do Fluxo de Caixa
C17: Ano 01 | D17: Ano 02 | E17: Ano 03 | F17: Ano 04 | G17: Ano 05
A18: Entradas | C18: =C5 -> 446164.29 | D18: =D5 -> 1249874.4 | E18: =E5 -> 2805786.8 | F18: =F5 -> 5390282.8 | G18: =G5 -> 9504461.7
A19: (-) Saídas | C19: =C6+C9+C12+C8 -> 1393334.3 | D19: =D6+D9+D12+D8 -> 1534582.8 | E19: =E6+E9+E12+E8 -> 2138513.2 | F19: =F6+F9+F12+F8 -> 3344770.2 | G19: =G6+G9+G12+G8 -> 5035808.6
A20: (+) Depreciação
A21: Fluxo de Caixa | C21: =C18-C19+C20 -> -947169.97 | D21: =D18-D19+D20 -> -284708.36 | E21: =E18-E19+E20 -> 667273.57 | F21: =F18-F19+F20 -> 2045512.6 | G21: =G18-G19+G20 -> 4468653
A25: Taxa Interna de Retorno Estimada: | D25: =IRR(B29:G29) -> 0.4701289 | E25: ao ano
A27: Investimento
A28: Necessidade de Investimento | B28: Ano 0 | C28: Ano 01 | D28: Ano 02 | E28: Ano 03 | F28: Ano 04 | G28: Ano 05
A29: Fluxo de Caixa | B29: =-'4.Premissas de Investimento'!B1 -> -170000 | C29: =C13+C20 -> -1139170 | D29: =D13+D20 -> -478308.36 | E29: =E13+E20 -> 472073.57 | F29: =F13+F20 -> 1848712.6 | G29: =G13+G20 -> 4270253

Sheet 6.Unit Economics
A1: Unit Economics — CAC, LTV e Payback
A4: Métrica | B4: Ano 1 | C4: Ano 2 | D4: Ano 3 | E4: Ano 4 | F4: Ano 5 | G4: Comentário / Fonte
A6: INSUMOS (linkados das abas existentes)
A7: Receita bruta anual (R$) | B7: ='5.Projeção Financeira'!BP61 -> 446164.29 | C7: ='5.Projeção Financeira'!BQ61 -> 1249874.4 | D7: ='5.Projeção Financeira'!BR61 -> 2805786.8 | E7: ='5.Projeção Financeira'!BS61 -> 5390282.8 | F7: ='5.Projeção Financeira'!BT61 -> 9504461.7 | G7: Puxa de 5.Projeção Financeira, linha 61
A8: Gastos totais V&M (serviços + folha) (R$) | B8: ='5.Projeção Financeira'!BP107+'5.Projeção Financeira'!BP108 -> 315996 | C8: ='5.Projeção Financeira'!BQ107+'5.Projeção Financeira'!BQ108 -> 318629.3 | D8: ='5.Projeção Financeira'!BR107+'5.Projeção Financeira'!BR108 -> 363395.4 | E8: ='5.Projeção Financeira'!BS107+'5.Projeção Financeira'!BS108 -> 385515.12 | F8: ='5.Projeção Financeira'!BT107+'5.Projeção Financeira'!BT108 -> 406844.85 | G8: 5.Projeção linha 107+108 (mídia + salários vendas/marketing)
A9: Novos clientes brutos adquiridos (unid.) | B9: ='5.Projeção Financeira'!BP27 -> 66.229471 | C9: ='5.Projeção Financeira'!BQ27 -> 119.30425 | D9: ='5.Projeção Financeira'!BR27 -> 230.96258 | E9: ='5.Projeção Financeira'!BS27 -> 383.64747 | F9: ='5.Projeção Financeira'!BT27 -> 610.71649 | G9: 5.Projeção linha 27 — vendas brutas antes do churn
A10: Custo dos serviços — COGS (R$) | B10: ='5.Projeção Financeira'!BP100 -> 113030.05 | C10: ='5.Projeção Financeira'!BQ100 -> 203609.74 | D10: ='5.Projeção Financeira'!BR100 -> 394170.63 | E10: ='5.Projeção Financeira'!BS100 -> 654749.21 | F10: ='5.Projeção Financeira'!BT100 -> 1042274.9 | G10: 5.Projeção linha 100
A12: PREMISSAS EDITÁVEIS
A13: Churn mensal médio (%) | B13: 0.03 | G13: 3% ao mês = 30% ao ano. Prof. Marco A.: "2–3% é saudável em SaaS B2B". Alinhado com premissa da aba 1.Premissas Receitas B30.
A14: Prazo médio de contrato (meses) | B14: 12 | G14: Contrato guarda-chuva 12m padrão SaaS B2B. Prof. mencionou 12/24m como barreira de saída.
A15: % dos gastos V&M dedicados a aquisição (vs retenção) | B15: 0.7 | G15: Ajuste conservador: 70% do V&M vai para NEW logos, 30% para CS/retenção. Isso evita superestimar o CAC.
A17: CAC — Custo de Aquisição de Cliente
A18: CAC = (V&M × %aquisição) / Novos clientes (R$) | B18: =IF(B9<=0,0,(B8*$B$15)/B9) -> 3339.8606 | C18: =IF(C9<=0,0,(C8*$B$15)/C9) -> 1869.5102 | D18: =IF(D9<=0,0,(D8*$B$15)/D9) -> 1101.3766 | E18: =IF(E9<=0,0,(E8*$B$15)/E9) -> 703.4077 | F18: =IF(F9<=0,0,(F8*$B$15)/F9) -> 466.3234 | G18: Quanto vocês gastam de V&M para trazer 1 cliente novo.
A20: TICKET MÉDIO E MARGEM BRUTA (calculado a partir da receita real)
A21: Base ativa de clientes ao final do ano (unid.) | B21: ='5.Projeção Financeira'!BP27-ABS('5.Projeção Financeira'!BP36) -> 65.461004 | C21: =B21+'5.Projeção Financeira'!BQ27-ABS('5.Projeção Financeira'!BQ36) -> 183.27602 | D21: =C21+'5.Projeção Financeira'!BR27-ABS('5.Projeção Financeira'!BR36) -> 411.39776 | E21: =D21+'5.Projeção Financeira'!BS27-ABS('5.Projeção Financeira'!BS36) -> 790.30409 | F21: =E21+'5.Projeção Financeira'!BT27-ABS('5.Projeção Financeira'!BT36) -> 1394.1968 | G21: Novos brutos acumulados − Churn acumulado. Puxa linhas 27 e 36 do modelo.
A22: Base ativa MÉDIA no ano (unid.) | B22: =B21/2 -> 32.730502 | C22: =(B21+C21)/2 -> 124.36851 | D22: =(C21+D21)/2 -> 297.33689 | E22: =(D21+E21)/2 -> 600.85092 | F22: =(E21+F21)/2 -> 1092.2505 | G22: Base ativa média = (base início + base fim) / 2.
A23: Ticket médio ANUAL por cliente (R$) | B23: =IF(B22<=0,0,B7/B22) -> 13631.453 | C23: =IF(C22<=0,0,C7/C22) -> 10049.766 | D23: =IF(D22<=0,0,D7/D22) -> 9436.3899 | E23: =IF(E22<=0,0,E7/E22) -> 8971.0818 | F23: =IF(F22<=0,0,F7/F22) -> 8701.7237 | G23: Receita bruta ÷ base ativa média. Este é o ticket REAL, não o parâmetro do SOM.
A24: Ticket médio MENSAL por cliente (R$) | B24: =B23/12 -> 1135.9544 | C24: =C23/12 -> 837.48049 | D24: =D23/12 -> 786.36583 | E24: =E23/12 -> 747.59015 | F24: =F23/12 -> 725.14364
A25: Margem bruta % (Receita − COGS) / Receita | B25: =IF(B7<=0,0,(B7-B10)/B7) -> 0.74666271 | C25: =IF(C7<=0,0,(C7-C10)/C7) -> 0.83709584 | D25: =IF(D7<=0,0,(D7-D10)/D7) -> 0.85951512 | E25: =IF(E7<=0,0,(E7-E10)/E7) -> 0.87853157 | F25: =IF(F7<=0,0,(F7-F10)/F7) -> 0.89033835 | G25: Meta SaaS: >70%. Modelo do colega opera em 74–89%. ✓
A27: LTV — Lifetime Value do Cliente
A28: Vida útil média do cliente (meses) = 1 / Churn | B28: =IF($B$13<=0,0,1/$B$13) -> 33.333333 | C28: =IF($B$13<=0,0,1/$B$13) -> 33.333333 | D28: =IF($B$13<=0,0,1/$B$13) -> 33.333333 | E28: =IF($B$13<=0,0,1/$B$13) -> 33.333333 | F28: =IF($B$13<=0,0,1/$B$13) -> 33.333333 | G28: Com 3%/mês → cliente fica ~33 meses (~2,8 anos).
A29: LTV = Ticket mensal × Margem × Vida útil (R$) | B29: =B24*B25*B28 -> 28272.493 | C29: =C24*C25*C28 -> 23368.381 | D29: =D24*D25*D28 -> 22529.777 | E29: =E24*E25*E28 -> 21892.718 | F29: =F24*F25*F28 -> 21520.773 | G29: Valor total que o cliente gera de lucro bruto durante toda a relação.
A31: MÉTRICAS-CHAVE (o professor vai olhar aqui)
A32: LTV / CAC (meta: ≥ 3x) | B32: =IF(B18<=0,0,B29/B18) -> 8.4651717 | C32: =IF(C18<=0,0,C29/C18) -> 12.499734 | D32: =IF(D18<=0,0,D29/D18) -> 20.456016 | E32: =IF(E18<=0,0,E29/E18) -> 31.123797 | F32: =IF(F18<=0,0,F29/F18) -> 46.149889
A33: Payback do CAC (meses — meta: ≤ 12) | B33: =IF(B24*B25<=0,999,B18/(B24*B25)) -> 3.9377032 | C33: =IF(C24*C25<=0,999,C18/(C24*C25)) -> 2.6667234 | D33: =IF(D24*D25<=0,999,D18/(D24*D25)) -> 1.6295125 | E33: =IF(E24*E25<=0,999,E18/(E24*E25)) -> 1.0709919 | F33: =IF(F24*F25<=0,999,F18/(F24*F25)) -> 0.72228416
A34: Diagnóstico LTV/CAC | B34: =IF(B32>=3,"✓ Saudável",IF(B32>=1,"⚠ Atenção","✗ Crítico")) -> ✓ Saudável | C34: =IF(C32>=3,"✓ Saudável",IF(C32>=1,"⚠ Atenção","✗ Crítico")) -> ✓ Saudável | D34: =IF(D32>=3,"✓ Saudável",IF(D32>=1,"⚠ Atenção","✗ Crítico")) -> ✓ Saudável | E34: =IF(E32>=3,"✓ Saudável",IF(E32>=1,"⚠ Atenção","✗ Crítico")) -> ✓ Saudável | F34: =IF(F32>=3,"✓ Saudável",IF(F32>=1,"⚠ Atenção","✗ Crítico")) -> ✓ Saudável
A35: Diagnóstico Payback | B35: =IF(B33<=12,"✓ Saudável",IF(B33<=18,"⚠ Atenção","✗ Crítico")) -> ✓ Saudável | C35: =IF(C33<=12,"✓ Saudável",IF(C33<=18,"⚠ Atenção","✗ Crítico")) -> ✓ Saudável | D35: =IF(D33<=12,"✓ Saudável",IF(D33<=18,"⚠ Atenção","✗ Crítico")) -> ✓ Saudável | E35: =IF(E33<=12,"✓ Saudável",IF(E33<=18,"⚠ Atenção","✗ Crítico")) -> ✓ Saudável | F35: =IF(F33<=12,"✓ Saudável",IF(F33<=18,"⚠ Atenção","✗ Crítico")) -> ✓ Saudável
A38: FÓRMULAS DE REFERÊNCIA
A39: CAC | B39: Gastos V&M × % dedicado a aquisição ÷ Novos clientes brutos
A40: LTV | B40: Ticket mensal × Margem bruta × Vida útil (meses)
A41: LTV/CAC | B41: Retorno em R$ que cada R$ 1 gasto em vendas gera ao longo da vida do cliente
A42: Payback | B42: Meses para recuperar o CAC via receita descontada da margem bruta
A43: Ticket médio | B43: Receita bruta anual ÷ base ativa média de clientes (NÃO é o preço do SOM)
A44: Vida útil | B44: 1 / Churn mensal (em meses). Com 3%/mês → 33 meses.

Sheet 7.Break-Even e Runway
A1: Break-Even, Fluxo Acumulado e Necessidade de Captação
A4: Linha | B4: Ano 1 | C4: Ano 2 | D4: Ano 3 | E4: Ano 4 | F4: Ano 5 | G4: Comentário
A6: RECEITA vs. CUSTO TOTAL (o descolamento)
A7: Receita bruta anual (R$) | B7: ='5.Projeção Financeira'!BP61 -> 446164.29 | C7: ='5.Projeção Financeira'!BQ61 -> 1249874.4 | D7: ='5.Projeção Financeira'!BR61 -> 2805786.8 | E7: ='5.Projeção Financeira'!BS61 -> 5390282.8 | F7: ='5.Projeção Financeira'!BT61 -> 9504461.7
A8: Custo total (COGS + OPEX + Outras) (R$) | B8: =Resumo!C8+Resumo!C9+Resumo!C10 -> 1563026.1 | C8: =Resumo!D8+Resumo!D9+Resumo!D10 -> 1665689 | D8: =Resumo!E8+Resumo!E9+Resumo!E10 -> 2036066 | E8: =Resumo!F8+Resumo!F9+Resumo!F10 -> 2386304.3 | F8: =Resumo!G8+Resumo!G9+Resumo!G10 -> 2860344.8
A9: Δ (Receita − Custo) (R$) | B9: =B7-B8 -> -1116861.8 | C9: =C7-C8 -> -415814.64 | D9: =D7-D8 -> 769720.77 | E9: =E7-E8 -> 3003978.5 | F9: =F7-F8 -> 6644116.9
A10: Break-even do ano? (Receita > Custo) | B10: =IF(B9>0,"✓ SIM","✗ NÃO") -> ✗ NÃO | C10: =IF(C9>0,"✓ SIM","✗ NÃO") -> ✗ NÃO | D10: =IF(D9>0,"✓ SIM","✗ NÃO") -> ✓ SIM | E10: =IF(E9>0,"✓ SIM","✗ NÃO") -> ✓ SIM | F10: =IF(F9>0,"✓ SIM","✗ NÃO") -> ✓ SIM
A12: FLUXO DE CAIXA ACUMULADO E CAPTAÇÃO
A13: Fluxo de caixa anual (R$) | B13: =Resumo!C21 -> -947169.97 | C13: =Resumo!D21 -> -284708.36 | D13: =Resumo!E21 -> 667273.57 | E13: =Resumo!F21 -> 2045512.6 | F13: =Resumo!G21 -> 4468653
A14: Investimento inicial (Ano 0) (R$) | B14: =-'4.Premissas de Investimento'!B1 -> -170000 | G14: Puxa de 4.Premissas de Investimento B1 (hoje: R$ 170k).
A15: Fluxo de caixa ACUMULADO (R$) | B15: =B14+B13 -> -1117170 | C15: =B15+C13 -> -1401878.3 | D15: =C15+D13 -> -734604.77 | E15: =D15+E13 -> 1310907.9 | F15: =E15+F13 -> 5779560.9
A16: Menor caixa acumulado no período (pico de queima) | B16: =MIN(B15:F15) -> -1401878.3 | G16: É o "vale" do gráfico de caixa acumulado. Vocês precisam de captação nesse valor absoluto.
A17: CAPTAÇÃO ADICIONAL NECESSÁRIA (Seed round) (R$) | B17: =MAX(0,-MIN(B15:F15)) -> 1401878.3 | G17: Este é o número que vocês vão pedir para o investidor. Com margem de segurança de 20%, some 20% em cima.
A18: Captação recomendada (com buffer +20%) (R$) | B18: =B17*1.2 -> 1682254
A20: ANO DE PAY-BACK DO INVESTIMENTO (fluxo acumulado > 0)
A21: Payback do projeto (ano em que caixa acumulado vira positivo) | B21: =IF(B15>0,"Ano 1",IF(C15>0,"Ano 2",IF(D15>0,"Ano 3",IF(E15>0,"Ano 4",IF(F15>0,"Ano 5","> Ano 5 (rever modelo)"))))) -> Ano 4
A23: ANÁLISE CRÍTICA — Investimento inicial é suficiente?
A24: Investimento inicial atual (aba 4) | B24: ='4.Premissas de Investimento'!B1 -> 170000
A25: Gap: Captação necessária − Investimento atual (R$) | B25: =B17-B24 -> 1231878.3
A26: Veredito | B26: =IF(B25<=0,"✓ Investimento inicial cobre a queima. Modelo viável sem captação adicional.","✗ Investimento inicial INSUFICIENTE. É preciso captar rodada seed no valor calculado acima.") -> ✗ Investimento inicial INSUFICIENTE. É preciso captar rodada seed no valor calculado acima.
A29: COMO INTERPRETAR ESTA ABA
A30: • A curva Receita cruza a curva Custo no primeiro ano em que "Δ (Receita − Custo)" fica positivo (linha 9).
A31: • Isso valida o "descolamento" que o Prof. Marco A. cobrou na reunião: receita cresce em curva, custo cresce linear.
A32: • O pico de queima (linha 16) é o valor MAIS NEGATIVO do fluxo acumulado — é ali que vocês PRECISAM ter caixa.
A33: • A captação recomendada (linha 18) inclui buffer de 20% para imprevistos: overrun de custo, atraso de vendas.
A34: • Se o "Gap" (linha 25) for positivo, o R$ 170k inicial não fecha a conta. Vocês precisam pitchar essa diferença.

Sheet 8.Cenarios
A1: Análise de Sensibilidade — 3 Cenários
A4: Variável | B4: Pessimista | C4: Base | D4: Otimista | E4: Justificativa
A6: MULTIPLICADORES POR CENÁRIO (amarelo = ajustável)
A7: Multiplicador de RECEITA vs. Base | B7: 0.6 | C7: 1 | D7: 1.3 | E7: Pess: -40% (metade da aquisição prevista). Otim: +30% (upsell + expansão internacional).
A8: Multiplicador de CUSTO vs. Base | B8: 1.15 | C8: 1 | D8: 0.95 | E8: Pess: +15% (contratação emergencial, dólar). Otim: -5% (eficiência com IA).
A9: Churn mensal | B9: 0.05 | C9: 0.03 | D9: 0.02 | E9: Pess: 5% (concorrência entra forte). Base: 3% (premissa do colega). Otim: 2% (produto sticky).
A10: Ticket médio ANUAL (R$) | B10: ='6.Unit Economics'!F23*0.75 -> 6526.2928 | C10: ='6.Unit Economics'!F23 -> 8701.7237 | D10: ='6.Unit Economics'!F23*1.35 -> 11747.327 | E10: Pess: 25% abaixo do ticket real do Ano 5. Base: ticket real do Ano 5. Otim: 35% acima do ticket real.
A12: RESULTADOS PROJETADOS — Ano 5
A13: Receita bruta Ano 5 (R$) | B13: =B7*'5.Projeção Financeira'!BT61 -> 5702677 | C13: =C7*'5.Projeção Financeira'!BT61 -> 9504461.7 | D13: =D7*'5.Projeção Financeira'!BT61 -> 12355800
A14: Custo total Ano 5 (COGS + OPEX + Impostos + IR) (R$) | B14: =B13-B33 -> 4320417.4 | C14: =C13-C33 -> 5234208.6 | D14: =D13-D33 -> 6053630.7
A15: Resultado líquido Ano 5 (R$) | B15: =B33 -> 1382259.6 | C15: =C33 -> 4270253 | D15: =D33 -> 6302169.5
A16: Margem líquida Ano 5 (%) | B16: =IF(B13<=0,0,B15/B13) -> 0.24238785 | C16: =IF(C13<=0,0,C15/C13) -> 0.44928931 | D16: =IF(D13<=0,0,D15/D13) -> 0.51005757
A18: UNIT ECONOMICS POR CENÁRIO
A19: Vida útil do cliente (meses) | B19: =IF(B9<=0,0,1/B9) -> 20 | C19: =IF(C9<=0,0,1/C9) -> 33.333333 | D19: =IF(D9<=0,0,1/D9) -> 50
A20: Ticket mensal (R$) | B20: =B10/12 -> 543.85773 | C20: =C10/12 -> 725.14364 | D20: =D10/12 -> 978.94392
A21: Margem bruta % (estimada) | B21: =IF(B13<=0,0,1-(B8*'5.Projeção Financeira'!BT100)/B13) -> 0.78981517 | C21: =IF(C13<=0,0,1-(C8*'5.Projeção Financeira'!BT100)/C13) -> 0.89033835 | D21: =IF(D13<=0,0,1-(D8*'5.Projeção Financeira'!BT100)/D13) -> 0.91986264
A22: LTV estimado (R$) | B22: =B20*B21*B19 -> 8590.9418 | C22: =C20*C21*C19 -> 21520.773 | D22: =D20*D21*D19 -> 45024.697
A23: CAC estimado (R$) | B23: ='6.Unit Economics'!F18*(B8/B7) -> 893.78653 | C23: ='6.Unit Economics'!F18*(C8/C7) -> 466.3234 | D23: ='6.Unit Economics'!F18*(D8/D7) -> 340.7748
A24: LTV / CAC | B24: =IF(B23<=0,0,B22/B23) -> 9.6118497 | C24: =IF(C23<=0,0,C22/C23) -> 46.149889 | D24: =IF(D23<=0,0,D22/D23) -> 132.12449
A25: Diagnóstico | B25: =IF(B24>=3,"✓ Viável",IF(B24>=1,"⚠ Atenção","✗ Modelo quebra")) -> ✓ Viável | C25: =IF(C24>=3,"✓ Viável",IF(C24>=1,"⚠ Atenção","✗ Modelo quebra")) -> ✓ Viável | D25: =IF(D24>=3,"✓ Viável",IF(D24>=1,"⚠ Atenção","✗ Modelo quebra")) -> ✓ Viável
A27: TIR ESTIMADA POR CENÁRIO (5 anos)
A28: Investimento inicial (Ano 0) | B28: =-'4.Premissas de Investimento'!B1 -> -170000 | C28: =-'4.Premissas de Investimento'!B1 -> -170000 | D28: =-'4.Premissas de Investimento'!B1 -> -170000
A29: Fluxo Ano 1 (aprox.) | B29: =((B7*Resumo!C5)-(IFERROR(Resumo!C6/Resumo!C5,0.05)*(B7*Resumo!C5))-(B8*Resumo!C8)-(B8*Resumo!C9)-(B8*Resumo!C10))-IF(((B7*Resumo!C5)-(IFERROR(Resumo!C6/Resumo!C5,0.05)*(B7*Resumo!C5))-(B8*Resumo!C8)-(B8*Resumo!C9)-(B8*Resumo!C10))>0,0.25*((B7*Resumo!C5)-(IFERROR(Resumo!C6/Resumo!C5,0.05)*(B7*Resumo!C5))-(B8*Resumo!C8)-(B8*Resumo!C9)-(B8*Resumo!C10)),0) -> -1543166.3 | C29: =((C7*Resumo!C5)-(IFERROR(Resumo!C6/Resumo!C5,0.05)*(C7*Resumo!C5))-(C8*Resumo!C8)-(C8*Resumo!C9)-(C8*Resumo!C10))-IF(((C7*Resumo!C5)-(IFERROR(Resumo!C6/Resumo!C5,0.05)*(C7*Resumo!C5))-(C8*Resumo!C8)-(C8*Resumo!C9)-(C8*Resumo!C10))>0,0.25*((C7*Resumo!C5)-(IFERROR(Resumo!C6/Resumo!C5,0.05)*(C7*Resumo!C5))-(C8*Resumo!C8)-(C8*Resumo!C9)-(C8*Resumo!C10)),0) -> -1139170 | D29: =((D7*Resumo!C5)-(IFERROR(Resumo!C6/Resumo!C5,0.05)*(D7*Resumo!C5))-(D8*Resumo!C8)-(D8*Resumo!C9)-(D8*Resumo!C10))-IF(((D7*Resumo!C5)-(IFERROR(Resumo!C6/Resumo!C5,0.05)*(D7*Resumo!C5))-(D8*Resumo!C8)-(D8*Resumo!C9)-(D8*Resumo!C10))>0,0.25*((D7*Resumo!C5)-(IFERROR(Resumo!C6/Resumo!C5,0.05)*(D7*Resumo!C5))-(D8*Resumo!C8)-(D8*Resumo!C9)-(D8*Resumo!C10)),0) -> -933861.85
A30: Fluxo Ano 2 (aprox.) | B30: =((B7*Resumo!D5)-(IFERROR(Resumo!D6/Resumo!D5,0.05)*(B7*Resumo!D5))-(B8*Resumo!D8)-(B8*Resumo!D9)-(B8*Resumo!D10))-IF(((B7*Resumo!D5)-(IFERROR(Resumo!D6/Resumo!D5,0.05)*(B7*Resumo!D5))-(B8*Resumo!D8)-(B8*Resumo!D9)-(B8*Resumo!D10))>0,0.25*((B7*Resumo!D5)-(IFERROR(Resumo!D6/Resumo!D5,0.05)*(B7*Resumo!D5))-(B8*Resumo!D8)-(B8*Resumo!D9)-(B8*Resumo!D10)),0) -> -1203114 | C30: =((C7*Resumo!D5)-(IFERROR(Resumo!D6/Resumo!D5,0.05)*(C7*Resumo!D5))-(C8*Resumo!D8)-(C8*Resumo!D9)-(C8*Resumo!D10))-IF(((C7*Resumo!D5)-(IFERROR(Resumo!D6/Resumo!D5,0.05)*(C7*Resumo!D5))-(C8*Resumo!D8)-(C8*Resumo!D9)-(C8*Resumo!D10))>0,0.25*((C7*Resumo!D5)-(IFERROR(Resumo!D6/Resumo!D5,0.05)*(C7*Resumo!D5))-(C8*Resumo!D8)-(C8*Resumo!D9)-(C8*Resumo!D10)),0) -> -478308.36 | D30: =((D7*Resumo!D5)-(IFERROR(Resumo!D6/Resumo!D5,0.05)*(D7*Resumo!D5))-(D8*Resumo!D8)-(D8*Resumo!D9)-(D8*Resumo!D10))-IF(((D7*Resumo!D5)-(IFERROR(Resumo!D6/Resumo!D5,0.05)*(D7*Resumo!D5))-(D8*Resumo!D8)-(D8*Resumo!D9)-(D8*Resumo!D10))>0,0.25*((D7*Resumo!D5)-(IFERROR(Resumo!D6/Resumo!D5,0.05)*(D7*Resumo!D5))-(D8*Resumo!D8)-(D8*Resumo!D9)-(D8*Resumo!D10)),0) -> -38809.707
A31: Fluxo Ano 3 (aprox.) | B31: =((B7*Resumo!E5)-(IFERROR(Resumo!E6/Resumo!E5,0.05)*(B7*Resumo!E5))-(B8*Resumo!E8)-(B8*Resumo!E9)-(B8*Resumo!E10))-IF(((B7*Resumo!E5)-(IFERROR(Resumo!E6/Resumo!E5,0.05)*(B7*Resumo!E5))-(B8*Resumo!E8)-(B8*Resumo!E9)-(B8*Resumo!E10))>0,0.25*((B7*Resumo!E5)-(IFERROR(Resumo!E6/Resumo!E5,0.05)*(B7*Resumo!E5))-(B8*Resumo!E8)-(B8*Resumo!E9)-(B8*Resumo!E10)),0) -> -742177.46 | C31: =((C7*Resumo!E5)-(IFERROR(Resumo!E6/Resumo!E5,0.05)*(C7*Resumo!E5))-(C8*Resumo!E8)-(C8*Resumo!E9)-(C8*Resumo!E10))-IF(((C7*Resumo!E5)-(IFERROR(Resumo!E6/Resumo!E5,0.05)*(C7*Resumo!E5))-(C8*Resumo!E8)-(C8*Resumo!E9)-(C8*Resumo!E10))>0,0.25*((C7*Resumo!E5)-(IFERROR(Resumo!E6/Resumo!E5,0.05)*(C7*Resumo!E5))-(C8*Resumo!E8)-(C8*Resumo!E9)-(C8*Resumo!E10)),0) -> 472073.57 | D31: =((D7*Resumo!E5)-(IFERROR(Resumo!E6/Resumo!E5,0.05)*(D7*Resumo!E5))-(D8*Resumo!E8)-(D8*Resumo!E9)-(D8*Resumo!E10))-IF(((D7*Resumo!E5)-(IFERROR(Resumo!E6/Resumo!E5,0.05)*(D7*Resumo!E5))-(D8*Resumo!E8)-(D8*Resumo!E9)-(D8*Resumo!E10))>0,0.25*((D7*Resumo!E5)-(IFERROR(Resumo!E6/Resumo!E5,0.05)*(D7*Resumo!E5))-(D8*Resumo!E8)-(D8*Resumo!E9)-(D8*Resumo!E10)),0) -> 1148163
A32: Fluxo Ano 4 (aprox.) | B32: =((B7*Resumo!F5)-(IFERROR(Resumo!F6/Resumo!F5,0.05)*(B7*Resumo!F5))-(B8*Resumo!F8)-(B8*Resumo!F9)-(B8*Resumo!F10))-IF(((B7*Resumo!F5)-(IFERROR(Resumo!F6/Resumo!F5,0.05)*(B7*Resumo!F5))-(B8*Resumo!F8)-(B8*Resumo!F9)-(B8*Resumo!F10))>0,0.25*((B7*Resumo!F5)-(IFERROR(Resumo!F6/Resumo!F5,0.05)*(B7*Resumo!F5))-(B8*Resumo!F8)-(B8*Resumo!F9)-(B8*Resumo!F10)),0) -> 124877.04 | C32: =((C7*Resumo!F5)-(IFERROR(Resumo!F6/Resumo!F5,0.05)*(C7*Resumo!F5))-(C8*Resumo!F8)-(C8*Resumo!F9)-(C8*Resumo!F10))-IF(((C7*Resumo!F5)-(IFERROR(Resumo!F6/Resumo!F5,0.05)*(C7*Resumo!F5))-(C8*Resumo!F8)-(C8*Resumo!F9)-(C8*Resumo!F10))>0,0.25*((C7*Resumo!F5)-(IFERROR(Resumo!F6/Resumo!F5,0.05)*(C7*Resumo!F5))-(C8*Resumo!F8)-(C8*Resumo!F9)-(C8*Resumo!F10)),0) -> 1848712.6 | D32: =((D7*Resumo!F5)-(IFERROR(Resumo!F6/Resumo!F5,0.05)*(D7*Resumo!F5))-(D8*Resumo!F8)-(D8*Resumo!F9)-(D8*Resumo!F10))-IF(((D7*Resumo!F5)-(IFERROR(Resumo!F6/Resumo!F5,0.05)*(D7*Resumo!F5))-(D8*Resumo!F8)-(D8*Resumo!F9)-(D8*Resumo!F10))>0,0.25*((D7*Resumo!F5)-(IFERROR(Resumo!F6/Resumo!F5,0.05)*(D7*Resumo!F5))-(D8*Resumo!F8)-(D8*Resumo!F9)-(D8*Resumo!F10)),0) -> 3029731.3
A33: Fluxo Ano 5 (aprox.) | B33: =((B7*Resumo!G5)-(IFERROR(Resumo!G6/Resumo!G5,0.05)*(B7*Resumo!G5))-(B8*Resumo!G8)-(B8*Resumo!G9)-(B8*Resumo!G10))-IF(((B7*Resumo!G5)-(IFERROR(Resumo!G6/Resumo!G5,0.05)*(B7*Resumo!G5))-(B8*Resumo!G8)-(B8*Resumo!G9)-(B8*Resumo!G10))>0,0.25*((B7*Resumo!G5)-(IFERROR(Resumo!G6/Resumo!G5,0.05)*(B7*Resumo!G5))-(B8*Resumo!G8)-(B8*Resumo!G9)-(B8*Resumo!G10)),0) -> 1382259.6 | C33: =((C7*Resumo!G5)-(IFERROR(Resumo!G6/Resumo!G5,0.05)*(C7*Resumo!G5))-(C8*Resumo!G8)-(C8*Resumo!G9)-(C8*Resumo!G10))-IF(((C7*Resumo!G5)-(IFERROR(Resumo!G6/Resumo!G5,0.05)*(C7*Resumo!G5))-(C8*Resumo!G8)-(C8*Resumo!G9)-(C8*Resumo!G10))>0,0.25*((C7*Resumo!G5)-(IFERROR(Resumo!G6/Resumo!G5,0.05)*(C7*Resumo!G5))-(C8*Resumo!G8)-(C8*Resumo!G9)-(C8*Resumo!G10)),0) -> 4270253 | D33: =((D7*Resumo!G5)-(IFERROR(Resumo!G6/Resumo!G5,0.05)*(D7*Resumo!G5))-(D8*Resumo!G8)-(D8*Resumo!G9)-(D8*Resumo!G10))-IF(((D7*Resumo!G5)-(IFERROR(Resumo!G6/Resumo!G5,0.05)*(D7*Resumo!G5))-(D8*Resumo!G8)-(D8*Resumo!G9)-(D8*Resumo!G10))>0,0.25*((D7*Resumo!G5)-(IFERROR(Resumo!G6/Resumo!G5,0.05)*(D7*Resumo!G5))-(D8*Resumo!G8)-(D8*Resumo!G9)-(D8*Resumo!G10)),0) -> 6302169.5
A34: TIR (5 anos) | B34: =IFERROR(IRR(B28:B33,-0.5),IFERROR(IRR(B28:B33),"Não recupera em 5 anos")) -> -0.24624269 | C34: =IFERROR(IRR(C28:C33,-0.5),IFERROR(IRR(C28:C33),"Não recupera em 5 anos")) -> 0.4701289 | D34: =IFERROR(IRR(D28:D33,-0.5),IFERROR(IRR(D28:D33),"Não recupera em 5 anos")) -> 0.88488733
A35: TMA (Taxa Mínima de Atratividade) | B35: 0.2 | C35: 0.2 | D35: 0.2 | E35: 20% ao ano — mais que a SELIC (15%).
A36: Diagnóstico TIR vs. TMA | B36: =IF(ISNUMBER(B34),IF(B34>B35,"✓ Atrativo (TIR > TMA)",IF(B34>0,"⚠ Retorno positivo mas abaixo da TMA","✗ Prejuízo — não atrativo")),"✗ Projeto quebra em 5 anos") -> ✗ Prejuízo — não atrativo | C36: =IF(ISNUMBER(C34),IF(C34>C35,"✓ Atrativo (TIR > TMA)",IF(C34>0,"⚠ Retorno positivo mas abaixo da TMA","✗ Prejuízo — não atrativo")),"✗ Projeto quebra em 5 anos") -> ✓ Atrativo (TIR > TMA) | D36: =IF(ISNUMBER(D34),IF(D34>D35,"✓ Atrativo (TIR > TMA)",IF(D34>0,"⚠ Retorno positivo mas abaixo da TMA","✗ Prejuízo — não atrativo")),"✗ Projeto quebra em 5 anos") -> ✓ Atrativo (TIR > TMA)
A38: RESUMO EXECUTIVO — o que dizer na banca
A39: Cenário Base | B39: É o modelo do colega intacto: multiplicadores todos em 1,0x. TIR e LTV/CAC dentro das metas.
A40: Cenário Otimista | B40: Assume expansão internacional e ticket 35% maior. Serve para mostrar upside — nunca é o número que se pitcha.
A41: Cenário Pessimista | B41: Assume aquisição -40%, churn 5%, custos +15%. É o que o investidor VAI perguntar. Se o modelo ainda gera valor aqui, ele é robusto.
A42: Ponto de defesa | B42: Se o pessimista der TIR > 0 ou LTV/CAC > 1, o modelo passa no stress test. Se der negativo, precisa rever premissas.
